Workbook

Sheet financial data sp500 companies
A1: S. NO. | B1: date | C1: firm | D1: Ticker | E1: Research Development | F1: Income Before Tax | G1: Net Income | H1: Selling General Administrative | I1: Gross Profit | J1: Ebit | K1: Operating Income | L1: Interest Expense | M1: Income Tax Expense | N1: Total Revenue | O1: Total Operating Expenses | P1: Cost Of Revenue | Q1: Total Other Income Expense Net | R1: Net Income From Continuing Ops | S1: Net Income Applicable To Common Shares
A2: 0 | B2: 44469 | C2: 3M | D2: MMM | E2: 482000000 | F2: 1761000000 | G2: 1434000000 | H2: 1739000000 | I2: 4089000000 | J2: 1868000000 | K2: 1868000000 | L2: -117000000 | M2: 324000000 | N2: 8942000000 | O2: 7074000000 | P2: 4853000000 | Q2: -107000000 | R2: 1437000000 | S2: 1434000000
A3: 1 | B3: 44377 | C3: 3M | D3: MMM | E3: 514000000 | F3: 1940000000 | G3: 1524000000 | H3: 1666000000 | I3: 4231000000 | J3: 2051000000 | K3: 2051000000 | L3: -121000000 | M3: 415000000 | N3: 8950000000 | O3: 6899000000 | P3: 4719000000 | Q3: -111000000 | R3: 1525000000 | S3: 1524000000
A4: 2 | B4: 44286 | C4: 3M | D4: MMM | E4: 520000000 | F4: 1946000000 | G4: 1624000000 | H4: 1720000000 | I4: 4327000000 | J4: 2087000000 | K4: 2087000000 | L4: -132000000 | M4: 319000000 | N4: 8851000000 | O4: 6764000000 | P4: 4524000000 | Q4: -141000000 | R4: 1627000000 | S4: 1624000000
A5: 3 | B5: 44196 | C5: 3M | D5: MMM | E5: 449000000 | F5: 1706000000 | G5: 1389000000 | H5: 1814000000 | I5: 4246000000 | J5: 1983000000 | K5: 1983000000 | L5: -141000000 | M5: 316000000 | N5: 8583000000 | O5: 6600000000 | P5: 4337000000 | Q5: -277000000 | R5: 1390000000 | S5: 1389000000
A6: 4 | B6: 44469 | C6: 3M | D6: MMM | E6: 482000000 | F6: 1761000000 | G6: 1434000000 | H6: 1739000000 | I6: 4089000000 | J6: 1868000000 | K6: 1868000000 | L6: -117000000 | M6: 324000000 | N6: 8942000000 | O6: 7074000000 | P6: 4853000000 | Q6: -107000000 | R6: 1437000000 | S6: 1434000000
A7: 5 | B7: 44377 | C7: 3M | D7: MMM | E7: 514000000 | F7: 1940000000 | G7: 1524000000 | H7: 1666000000 | I7: 4231000000 | J7: 2051000000 | K7: 2051000000 | L7: -121000000 | M7: 415000000 | N7: 8950000000 | O7: 6899000000 | P7: 4719000000 | Q7: -111000000 | R7: 1525000000 | S7: 1524000000
A8: 6 | B8: 44286 | C8: 3M | D8: MMM | E8: 520000000 | F8: 1946000000 | G8: 1624000000 | H8: 1720000000 | I8: 4327000000 | J8: 2087000000 | K8: 2087000000 | L8: -132000000 | M8: 319000000 | N8: 8851000000 | O8: 6764000000 | P8: 4524000000 | Q8: -141000000 | R8: 1627000000 | S8: 1624000000
A9: 7 | B9: 44196 | C9: 3M | D9: MMM | E9: 449000000 | F9: 1706000000 | G9: 1389000000 | H9: 1814000000 | I9: 4246000000 | J9: 1983000000 | K9: 1983000000 | L9: -141000000 | M9: 316000000 | N9: 8583000000 | O9: 6600000000 | P9: 4337000000 | Q9: -277000000 | R9: 1390000000 | S9: 1389000000
A10: 8 | B10: 44469 | C10: A. O. Smith | D10: AOS | F10: 166400000 | G10: 131600000 | H10: 174300000 | I10: 340300000 | J10: 166000000 | K10: 166000000 | L10: -1000000 | M10: 34800000 | N10: 914600000 | O10: 748600000 | P10: 574300000 | Q10: 400000 | R10: 131600000 | S10: 131600000
A11: 9 | B11: 44377 | C11: A. O. Smith | D11: AOS | F11: 151300000 | G11: 118200000 | H11: 169800000 | I11: 321400000 | J11: 151600000 | K11: 151600000 | L11: -900000 | M11: 33100000 | N11: 859800000 | O11: 708200000 | P11: 538400000 | Q11: -300000 | R11: 118200000 | S11: 118200000
A12: 10 | B12: 44286 | C12: A. O. Smith | D12: AOS | F12: 126100000 | G12: 97700000 | H12: 166500000 | I12: 288600000 | J12: 122100000 | K12: 122100000 | L12: -1000000 | M12: 28400000 | N12: 769000000 | O12: 646900000 | P12: 480400000 | Q12: 4000000 | R12: 97700000 | S12: 97700000
A13: 11 | B13: 44196 | C13: A. O. Smith | D13: AOS | F13: 151900000 | G13: 120000000 | H13: 184700000 | I13: 324100000 | J13: 139400000 | K13: 139400000 | L13: -1000000 | M13: 31900000 | N13: 834500000 | O13: 695100000 | P13: 510400000 | Q13: 12500000 | R13: 120000000 | S13: 120000000
A14: 12 | B14: 44469 | C14: Abbott Laboratories | D14: ABT | E14: 672000000 | F14: 2493000000 | G14: 2100000000 | H14: 2699000000 | I14: 6505000000 | J14: 2614000000 | K14: 2614000000 | L14: -133000000 | M14: 393000000 | N14: 10928000000 | O14: 8314000000 | P14: 4423000000 | Q14: -121000000 | R14: 2100000000 | S14: 2092000000
A15: 13 | B15: 44377 | C15: Abbott Laboratories | D15: ABT | E15: 654000000 | F15: 1348000000 | G15: 1189000000 | H15: 2658000000 | I15: 5786000000 | J15: 1970000000 | K15: 1970000000 | L15: -134000000 | M15: 159000000 | N15: 10223000000 | O15: 8253000000 | P15: 4437000000 | Q15: -622000000 | R15: 1189000000 | S15: 1184000000
A16: 14 | B16: 44286 | C16: Abbott Laboratories | D16: ABT | E16: 654000000 | F16: 2043000000 | G16: 1793000000 | H16: 2716000000 | I16: 6056000000 | J16: 2177000000 | K16: 2177000000 | L16: -135000000 | M16: 250000000 | N16: 10456000000 | O16: 8279000000 | P16: 4400000000 | Q16: -134000000 | R16: 1793000000 | S16: 1785000000
A17: 15 | B17: 44196 | C17: Abbott Laboratories | D17: ABT | E17: 643000000 | F17: 2388000000 | G17: 2162000000 | H17: 2525000000 | I17: 6207000000 | J17: 2531000000 | K17: 2531000000 | L17: -136000000 | M17: 230000000 | N17: 10701000000 | O17: 8170000000 | P17: 4494000000 | Q17: -143000000 | R17: 2158000000 | S17: 2151000000
A18: 16 | B18: 44469 | C18: AbbVie | D18: ABBV | E18: 1655000000 | F18: 3688000000 | G18: 3179000000 | H18: 2946000000 | I18: 9998000000 | J18: 4897000000 | K18: 4897000000 | L18: -596000000 | M18: 508000000 | N18: 14342000000 | O18: 9445000000 | P18: 4344000000 | Q18: -1209000000 | R18: 3180000000 | S18: 3158000000
A19: 17 | B19: 44377 | C19: AbbVie | D19: ABBV | E19: 1784000000 | F19: 1163000000 | G19: 766000000 | H19: 3049000000 | I19: 9461000000 | J19: 4696000000 | K19: 4696000000 | L19: -615000000 | M19: 394000000 | N19: 13959000000 | O19: 9263000000 | P19: 4498000000 | Q19: -3533000000 | R19: 769000000 | S19: 751000000
A20: 18 | B20: 44286 | C20: AbbVie | D20: ABBV | E20: 1731000000 | F20: 3867000000 | G20: 3553000000 | H20: 2741000000 | I20: 8818000000 | J20: 4346000000 | K20: 4346000000 | L20: -632000000 | M20: 312000000 | N20: 13010000000 | O20: 8664000000 | P20: 4192000000 | Q20: -479000000 | R20: 3555000000 | S20: 3536000000
A21: 19 | B21: 44196 | C21: AbbVie | D21: ABBV | E21: 1821000000 | F21: -1507000000 | G21: 36000000 | H21: 3099000000 | I21: 10448000000 | J21: 5528000000 | K21: 5528000000 | L21: -629000000 | M21: -1545000000 | N21: 13858000000 | O21: 8330000000 | P21: 3410000000 | Q21: -7035000000 | R21: 38000000 | S21: 20000000
A22: 20 | B22: 44469 | C22: Abiomed | D22: ABMD | E22: 41041000 | F22: 67271000 | G22: 56953000 | H22: 102779000 | I22: 204256000 | J22: 60436000 | K22: 60436000 | M22: 10318000 | N22: 248142000 | O22: 187706000 | P22: 43886000 | Q22: 6835000 | R22: 56953000 | S22: 56953000
A23: 21 | B23: 44377 | C23: Abiomed | D23: ABMD | E23: 36837000 | F23: -9350000 | G23: -26525000 | H23: 103484000 | I23: 207397000 | J23: 67076000 | K23: 67076000 | M23: 17175000 | N23: 252585000 | O23: 185509000 | P23: 45188000 | Q23: -76426000 | R23: -26525000 | S23: -26525000
A24: 22 | B24: 44286 | C24: Abiomed | D24: ABMD | E24: 32599000 | F24: 73494000 | G24: 56856000 | H24: 100374000 | I24: 195167000 | J24: 62194000 | K24: 62194000 | M24: 16638000 | N24: 241245000 | O24: 179051000 | P24: 46078000 | Q24: 11300000 | R24: 56856000 | S24: 56856000
A25: 23 | B25: 44196 | C25: Abiomed | D25: ABMD | E25: 32105000 | F25: 80735000 | G25: 61868000 | H25: 86198000 | I25: 190553000 | J25: 72250000 | K25: 72250000 | M25: 18867000 | N25: 231663000 | O25: 159413000 | P25: 41110000 | Q25: 8485000 | R25: 61868000 | S25: 61868000
A26: 24 | B26: 44439 | C26: Accenture | D26: ACN | F26: 1917805000 | G26: 1416248000 | H26: 2507527000 | I26: 4466216000 | J26: 1958689000 | K26: 1958689000 | L26: -12977000 | M26: 480382000 | N26: 13419284000 | O26: 11460595000 | P26: 8953068000 | Q26: -40884000 | R26: 1437423000 | S26: 1416248000
A27: 25 | B27: 44347 | C27: Accenture | D27: ACN | F27: 2094001000 | G27: 1549426000 | H27: 2285728000 | I27: 4404384000 | J27: 2118656000 | K27: 2118656000 | L27: -28739000 | M27: 524429000 | N27: 13263795000 | O27: 11145139000 | P27: 8859411000 | Q27: -24655000 | R27: 1569572000 | S27: 1549426000
A28: 26 | B28: 44255 | C28: Accenture | D28: ACN | F28: 1762443000 | G28: 1440859000 | H28: 1941717000 | I28: 3595232000 | J28: 1653515000 | K28: 1653515000 | L28: -8922000 | M28: 300950000 | N28: 12088125000 | O28: 10434610000 | P28: 8492893000 | Q28: 108928000 | R28: 1461493000 | S28: 1440859000
A29: 27 | B29: 44165 | C29: Accenture | D29: ACN | F29: 1986867000 | G29: 1500276000 | H29: 2007627000 | I29: 3898296000 | J29: 1890669000 | K29: 1890669000 | L29: -8854000 | M29: 464810000 | N29: 11762185000 | O29: 9871516000 | P29: 7863889000 | Q29: 96198000 | R29: 1522057000 | S29: 1500276000
A30: 28 | B30: 44469 | C30: Activision Blizzard | D30: ATVI | E30: 329000000 | F30: 759000000 | G30: 639000000 | H30: 387000000 | I30: 1543000000 | J30: 827000000 | K30: 827000000 | L30: -27000000 | M30: 120000000 | N30: 2070000000 | O30: 1243000000 | P30: 527000000 | Q30: -68000000 | R30: 639000000 | S30: 639000000
A31: 29 | B31: 44377 | C31: Activision Blizzard | D31: ATVI | E31: 335000000 | F31: 1002000000 | G31: 876000000 | H31: 434000000 | I31: 1741000000 | J31: 972000000 | K31: 972000000 | L31: -27000000 | M31: 126000000 | N31: 2296000000 | O31: 1324000000 | P31: 555000000 | Q31: 30000000 | R31: 876000000 | S31: 876000000
A32: 30 | B32: 44286 | C32: Activision Blizzard | D32: ATVI | E32: 353000000 | F32: 765000000 | G32: 619000000 | H32: 519000000 | I32: 1697000000 | J32: 825000000 | K32: 825000000 | L32: -28000000 | M32: 146000000 | N32: 2275000000 | O32: 1450000000 | P32: 578000000 | Q32: -60000000 | R32: 619000000 | S32: 619000000
A33: 31 | B33: 44196 | C33: Activision Blizzard | D33: ATVI | E33: 348000000 | F33: 563000000 | G33: 509000000 | H33: 597000000 | I33: 1595000000 | J33: 650000000 | K33: 650000000 | L33: -27000000 | M33: 54000000 | N33: 2412000000 | O33: 1762000000 | P33: 817000000 | Q33: -87000000 | R33: 509000000 | S33: 509000000
A34: 32 | B34: 44469 | C34: ADM | D34: ADM | F34: 653000000 | G34: 526000000 | H34: 716000000 | I34: 1326000000 | J34: 607000000 | K34: 607000000 | L34: -61000000 | M34: 120000000 | N34: 20340000000 | O34: 19733000000 | P34: 19014000000 | Q34: 46000000 | R34: 533000000 | S34: 526000000
A35: 33 | B35: 44377 | C35: ADM | D35: ADM | F35: 825000000 | G35: 712000000 | H35: 815000000 | I35: 1463000000 | J35: 642000000 | K35: 642000000 | L35: -40000000 | M35: 113000000 | N35: 22926000000 | O35: 22284000000 | P35: 21463000000 | Q35: 183000000 | R35: 712000000 | S35: 712000000
A36: 34 | B36: 44286 | C36: ADM | D36: ADM | F36: 824000000 | G36: 689000000 | H36: 697000000 | I36: 1548000000 | J36: 843000000 | K36: 843000000 | L36: -87000000 | M36: 131000000 | N36: 18893000000 | O36: 18050000000 | P36: 17345000000 | Q36: -19000000 | R36: 693000000 | S36: 689000000
A37: 35 | B37: 44196 | C37: ADM | D37: ADM | F37: 756000000 | G37: 687000000 | H37: 720000000 | I37: 1352000000 | J37: 615000000 | K37: 615000000 | L37: -69000000 | M37: 63000000 | N37: 17978000000 | O37: 17363000000 | P37: 16626000000 | Q37: 141000000 | R37: 693000000 | S37: 687000000
A38: 36 | B38: 44442 | C38: Adobe | D38: ADBE | E38: 651000000 | F38: 1418000000 | G38: 1212000000 | H38: 1333000000 | I38: 3468000000 | J38: 1441000000 | K38: 1441000000 | L38: -27000000 | M38: 206000000 | N38: 3935000000 | O38: 2494000000 | P38: 467000000 | Q38: -23000000 | R38: 1212000000 | S38: 1212000000
A39: 37 | B39: 44351 | C39: Adobe | D39: ADBE | E39: 612000000 | F39: 1386000000 | G39: 1116000000 | H39: 1329000000 | I39: 3391000000 | J39: 1406000000 | K39: 1406000000 | L39: -28000000 | M39: 270000000 | N39: 3835000000 | O39: 2429000000 | P39: 444000000 | Q39: -20000000 | R39: 1116000000 | S39: 1116000000
A40: 38 | B40: 44260 | C40: Adobe | D40: ADBE | E40: 620000000 | F40: 1433000000 | G40: 1261000000 | H40: 1339000000 | I40: 3458000000 | J40: 1454000000 | K40: 1454000000 | L40: -30000000 | M40: 172000000 | N40: 3905000000 | O40: 2451000000 | P40: 447000000 | Q40: -21000000 | R40: 1261000000 | S40: 1261000000
A41: 39 | B41: 44162 | C41: Adobe | D41: ADBE | E41: 558000000 | F41: 1197000000 | G41: 2250000000 | H41: 1184000000 | I41: 2996000000 | J41: 1215000000 | K41: 1215000000 | L41: -27000000 | M41: -1053000000 | N41: 3424000000 | O41: 2209000000 | P41: 428000000 | Q41: -18000000 | R41: 2250000000 | S41: 2250000000
A42: 40 | B42: 44394 | C42: Advance Auto Parts | D42: AAP | F42: 237765000 | G42: 178696000 | H42: 932793000 | I42: 1189416000 | J42: 256623000 | K42: 256623000 | L42: -8306000 | M42: 59069000 | N42: 2649415000 | O42: 2392792000 | P42: 1459999000 | Q42: -18858000 | R42: 178696000 | S42: 178696000
A43: 41 | B43: 44394 | C43: Advance Auto Parts | D43: AAP | F43: 237765000 | G43: 178696000 | H43: 932793000 | I43: 1189416000 | J43: 256623000 | K43: 256623000 | L43: -8306000 | M43: 0 | N43: 2649415000 | O43: 0 | P43: 0 | Q43: 0 | R43: 178696000 | S43: 178696000
A44: 42 | B44: 44310 | C44: Advance Auto Parts | D44: AAP | F44: 245774000 | G44: 185930000 | H44: 1200138000 | I44: 1487229000 | J44: 287091000 | K44: 287091000 | L44: -11191000 | M44: 59844000 | N44: 3330370000 | O44: 3043279000 | P44: 1843141000 | Q44: -41317000 | R44: 185930000 | S44: 185930000
A45: 43 | B45: 44303 | C45: Advance Auto Parts | D45: AAP | F45: 245774000 | G45: 182313000 | H45: 1200138000 | I45: 1338322500 | J45: 271856500 | K45: 287091000 | L45: -9748500 | M45: 0 | N45: 2989892500 | O45: 0 | P45: 0 | Q45: 0 | R45: 185930000 | S45: 185930000
A46: 44 | B46: 44464 | C46: Advanced Micro Devices | D46: AMD | E46: 765000000 | F46: 1005000000 | G46: 923000000 | H46: 368000000 | I46: 2086000000 | J46: 956000000 | K46: 956000000 | L46: -7000000 | M46: 82000000 | N46: 4313000000 | O46: 3357000000 | P46: 2227000000 | Q46: 49000000 | R46: 923000000 | S46: 923000000
A47: 45 | B47: 44373 | C47: Advanced Micro Devices | D47: AMD | E47: 659000000 | F47: 823000000 | G47: 710000000 | H47: 331000000 | I47: 1830000000 | J47: 841000000 | K47: 841000000 | L47: -10000000 | M47: 113000000 | N47: 3850000000 | O47: 3009000000 | P47: 2020000000 | Q47: -18000000 | R47: 710000000 | S47: 710000000
A48: 46 | B48: 44282 | C48: Advanced Micro Devices | D48: AMD | E48: 610000000 | F48: 644000000 | G48: 555000000 | H48: 304000000 | I48: 1587000000 | J48: 677000000 | K48: 677000000 | L48: -9000000 | M48: 89000000 | N48: 3445000000 | O48: 2768000000 | P48: 1858000000 | Q48: -33000000 | R48: 555000000 | S48: 555000000
A49: 47 | B49: 44191 | C49: Advanced Micro Devices | D49: AMD | E49: 573000000 | F49: 549000000 | G49: 1781000000 | H49: 308000000 | I49: 1451000000 | J49: 570000000 | K49: 570000000 | L49: -9000000 | M49: -1232000000 | N49: 3244000000 | O49: 2674000000 | P49: 1793000000 | Q49: -21000000 | R49: 1781000000 | S49: 1781000000
A50: 48 | B50: 44469 | C50: AES Corp | D50: AES | F50: 611000000 | G50: 343000000 | H50: 39000000 | I50: 760000000 | J50: 721000000 | K50: 721000000 | L50: -242000000 | M50: 126000000 | N50: 3036000000 | O50: 2315000000 | P50: 2276000000 | Q50: -110000000 | R50: 485000000 | S50: 343000000
A51: 49 | B51: 44377 | C51: AES Corp | D51: AES | F51: -140000000 | G51: 28000000 | H51: 45000000 | I51: 728000000 | J51: 683000000 | K51: 683000000 | L51: -237000000 | M51: -59000000 | N51: 2700000000 | O51: 2017000000 | P51: 1972000000 | Q51: -823000000 | R51: -81000000 | S51: 28000000
A52: 50 | B52: 44286 | C52: AES Corp | D52: AES | F52: -21000000 | G52: -148000000 | H52: 46000000 | I52: 664000000 | J52: 618000000 | K52: 618000000 | L52: -190000000 | M52: 8000000 | N52: 2635000000 | O52: 2017000000 | P52: 1971000000 | Q52: -639000000 | R52: -29000000 | S52: -148000000
A53: 51 | B53: 44196 | C53: AES Corp | D53: AES | F53: 562000000 | G53: 318000000 | H53: 47000000 | I53: 724000000 | J53: 677000000 | K53: 677000000 | L53: -297000000 | M53: 161000000 | N53: 2560000000 | O53: 1883000000 | P53: 1836000000 | Q53: -115000000 | R53: 401000000 | S53: 318000000
A54: 52 | B54: 44469 | C54: Aflac | D54: AFL | F54: 1113000000 | G54: 888000000 | H54: 869000000 | I54: 2039000000 | J54: 1170000000 | K54: 1170000000 | L54: -57000000 | M54: 225000000 | N54: 5237000000 | O54: 4067000000 | P54: 3198000000 | Q54: -57000000 | R54: 888000000 | S54: 888000000
A55: 53 | B55: 44377 | C55: Aflac | D55: AFL | F55: 1373000000 | G55: 1105000000 | H55: 881000000 | I55: 2316000000 | J55: 1435000000 | K55: 1435000000 | L55: -62000000 | M55: 268000000 | N55: 5564000000 | O55: 4129000000 | P55: 3248000000 | Q55: -62000000 | R55: 1105000000 | S55: 1105000000
A56: 54 | B56: 44286 | C56: Aflac | D56: AFL | F56: 1603000000 | G56: 1293000000 | H56: 832000000 | I56: 2497000000 | J56: 1665000000 | K56: 1665000000 | L56: -62000000 | M56: 310000000 | N56: 5869000000 | O56: 4204000000 | P56: 3372000000 | Q56: -62000000 | R56: 1293000000 | S56: 1293000000
A57: 55 | B57: 44196 | C57: Aflac | D57: AFL | F57: 1217000000 | G57: 952000000 | H57: 1038000000 | I57: 2316000000 | J57: 1278000000 | K57: 1278000000 | L57: -61000000 | M57: 265000000 | N57: 5913000000 | O57: 4635000000 | P57: 3597000000 | Q57: -61000000 | R57: 952000000 | S57: 952000000
A58: 56 | B58: 44408 | C58: Agilent Technologies | D58: A | E58: 113000000 | F58: 327000000 | G58: 264000000 | H58: 390000000 | I58: 852000000 | J58: 349000000 | K58: 349000000 | L58: -21000000 | M58: 63000000 | N58: 1586000000 | O58: 1237000000 | P58: 734000000 | Q58: -22000000 | R58: 264000000 | S58: 264000000
A59: 57 | B59: 44316 | C59: Agilent Technologies | D59: A | E59: 109000000 | F59: 273000000 | G59: 216000000 | H59: 420000000 | I59: 817000000 | J59: 288000000 | K59: 288000000 | L59: -20000000 | M59: 57000000 | N59: 1525000000 | O59: 1237000000 | P59: 708000000 | Q59: -15000000 | R59: 216000000 | S59: 216000000
A60: 58 | B60: 44227 | C60: Agilent Technologies | D60: A | E60: 103000000 | F60: 312000000 | G60: 288000000 | H60: 398000000 | I60: 838000000 | J60: 337000000 | K60: 337000000 | L60: -19000000 | M60: 24000000 | N60: 1548000000 | O60: 1211000000 | P60: 710000000 | Q60: -25000000 | R60: 288000000 | S60: 288000000
A61: 59 | B61: 44135 | C61: Agilent Technologies | D61: A | E61: 102000000 | F61: 283000000 | G61: 222000000 | H61: 342000000 | I61: 788000000 | J61: 344000000 | K61: 344000000 | L61: -19000000 | M61: 61000000 | N61: 1483000000 | O61: 1139000000 | P61: 695000000 | Q61: -61000000 | R61: 222000000 | S61: 222000000
A62: 60 | B62: 44469 | C62: Air Products & Chemicals | D62: APD | E62: 25700000 | F62: 692300000 | G62: 610400000 | H62: 202100000 | I62: 834800000 | J62: 616700000 | K62: 616700000 | L62: -33400000 | M62: 125300000 | N62: 2841100000 | O62: 2224400000 | P62: 2006300000 | Q62: 75600000 | R62: 567000000 | S62: 610400000
A63: 61 | B63: 44377 | C63: Air Products & Chemicals | D63: APD | E63: 23200000 | F63: 625800000 | G63: 533600000 | H63: 192600000 | I63: 802800000 | J63: 598400000 | K63: 598400000 | L63: -35600000 | M63: 101700000 | N63: 2604700000 | O63: 2006300000 | P63: 1801900000 | Q63: 27400000 | R63: 524100000 | S63: 533600000
A64: 62 | B64: 44286 | C64: Air Products & Chemicals | D64: APD | E64: 21100000 | F64: 599000000 | G64: 473100000 | H64: 189100000 | I64: 756500000 | J64: 555800000 | K64: 555800000 | L64: -36100000 | M64: 121900000 | N64: 2502000000 | O64: 1946200000 | P64: 1745500000 | Q64: 43200000 | R64: 477100000 | S64: 473100000
A65: 63 | B65: 44196 | C65: Air Products & Chemicals | D65: APD | E65: 23500000 | F65: 590300000 | G65: 482000000 | H65: 182100000 | I65: 742800000 | J65: 562500000 | K65: 562500000 | L65: -36700000 | M65: 113900000 | N65: 2375200000 | O65: 1812700000 | P65: 1632400000 | Q65: 27800000 | R65: 476400000 | S65: 482000000
A66: 64 | B66: 44469 | C66: Akamai Technologies | D66: AKAM | E66: 82899000 | F66: 192564000 | G66: 178916000 | H66: 241463000 | I66: 543467000 | J66: 207146000 | K66: 207146000 | L66: -18144000 | M66: 13648000 | N66: 860333000 | O66: 653187000 | P66: 316866000 | Q66: -14582000 | R66: 178916000 | S66: 178916000
A67: 65 | B67: 44377 | C67: Akamai Technologies | D67: AKAM | E67: 77255000 | F67: 174506000 | G67: 156497000 | H67: 246049000 | I67: 532824000 | J67: 197460000 | K67: 197460000 | L67: -18037000 | M67: 18009000 | N67: 852824000 | O67: 655364000 | P67: 320000000 | Q67: -22954000 | R67: 156497000 | S67: 156497000
A68: 66 | B68: 44286 | C68: Akamai Technologies | D68: AKAM | E68: 82045000 | F68: 167593000 | G68: 155695000 | H68: 253005000 | I68: 536021000 | J68: 189544000 | K68: 189544000 | L68: -17834000 | M68: 11898000 | N68: 842708000 | O68: 653164000 | P68: 306687000 | Q68: -21951000 | R68: 155695000 | S68: 155695000
A69: 67 | B69: 44196 | C69: Akamai Technologies | D69: AKAM | E69: 67228000 | F69: 117528000 | G69: 113370000 | H69: 298739000 | I69: 542440000 | J69: 165579000 | K69: 165579000 | L69: -17342000 | M69: 4158000 | N69: 846287000 | O69: 680708000 | P69: 303847000 | Q69: -48051000 | R69: 113370000 | S69: 113370000
... A73: 71 | B73: 44196 | C73: Alaska Air Group | D73: ALB | E73: 15375000 | F73: 92076000 | G73: 84635000 | H73: 115008000 | I73: 266720000 | J73: 136337000 | K73: 136337000 | L73: -19152000 | M73: -10101000 | N73: 879147000 | O73: 742810000 | P73: 612427000 | Q73: -44261000 | R73: 102177000 | S73: 84635000
A74: 72 | B74: 44469 | C74: Albemarle Corporation | D74: ALK | F74: 245000000 | G74: 194000000 | H74: 49000000 | I74: 562000000 | J74: 257000000 | K74: 257000000 | L74: -27000000 | M74: 51000000 | N74: 1953000000 | O74: 1696000000 | P74: 1391000000 | Q74: -12000000 | R74: 194000000 | S74: 194000000
A75: 73 | B75: 44377 | C75: Albemarle Corporation | D75: ALK | F75: 528000000 | G75: 397000000 | H75: 41000000 | I75: 246000000 | J75: -36000000 | K75: -36000000 | L75: -36000000 | M75: 131000000 | N75: 1527000000 | O75: 1563000000 | P75: 1281000000 | Q75: 564000000 | R75: 397000000 | S75: 397000000
A76: 74 | B76: 44286 | C76: Albemarle Corporation | D76: ALK | F76: -173000000 | G76: -131000000 | H76: 33000000 | I76: -312000000 | J76: -573000000 | K76: -573000000 | L76: -29000000 | M76: -42000000 | N76: 797000000 | O76: 1370000000 | P76: 1109000000 | Q76: 400000000 | R76: -131000000 | S76: -131000000
A77: 75 | B77: 44196 | C77: Albemarle Corporation | D77: ALK | F77: -643000000 | G77: -447000000 | H77: 18000000 | I77: -213000000 | J77: -449000000 | K77: -449000000 | L77: -31000000 | M77: -196000000 | N77: 808000000 | O77: 1257000000 | P77: 1021000000 | Q77: -194000000 | R77: -447000000 | S77: -447000000
A78: 76 | B78: 44469 | C78: Alexandria Real Estate Equities | D78: ARE | F78: 124433000 | G78: 103147000 | H78: 37931000 | I78: 384855000 | J78: 136082000 | K78: 136082000 | L78: -35678000 | M78: 0 | N78: 550850000 | O78: 414768000 | P78: 165995000 | Q78: -11649000 | R78: 124433000 | S78: 101264000
A79: 77 | B79: 44377 | C79: Alexandria Real Estate Equities | D79: ARE | F79: 404520000 | G79: 385084000 | H79: 37880000 | I79: 368273000 | J79: 140341000 | K79: 140341000 | L79: -35158000 | M79: 0 | N79: 512228000 | O79: 371887000 | P79: 143955000 | Q79: 264179000 | R79: 404520000 | S79: 380563000
A80: 78 | B80: 44286 | C80: Alexandria Real Estate Equities | D80: ARE | F80: 25533000 | G80: 8121000 | H80: 33996000 | I80: 345498000 | J80: 130589000 | K80: 130589000 | L80: -36467000 | M80: 0 | N80: 483386000 | O80: 352797000 | P80: 137888000 | Q80: -105056000 | R80: 25533000 | S80: 7979000
A81: 79 | B81: 44196 | C81: Alexandria Real Estate Equities | D81: ARE | F81: 457133000 | G81: 441484000 | H81: 32690000 | I81: 330546000 | J81: 120106000 | K81: 120106000 | L81: -37538000 | M81: 0 | N81: 467313000 | O81: 347207000 | P81: 136767000 | Q81: 337027000 | R81: 457133000 | S81: 436620000
A82: 80 | B82: 44469 | C82: Align Technology | D82: ALGN | E82: 65587000 | F82: 261988000 | G82: 180969000 | H82: 428409000 | I82: 755156000 | J82: 261160000 | K82: 261160000 | M82: 81019000 | N82: 1015906000 | O82: 754746000 | P82: 260750000 | Q82: 828000 | R82: 180969000 | S82: 180969000
A83: 81 | B83: 44377 | C83: Align Technology | D83: ALGN | E83: 57715000 | F83: 268802000 | G83: 199714000 | H83: 431921000 | I83: 758538000 | J83: 268902000 | K83: 268902000 | M83: 69088000 | N83: 1010808000 | O83: 741906000 | P83: 252270000 | Q83: -100000 | R83: 199714000 | S83: 199714000
A84: 82 | B84: 44286 | C84: Align Technology | D84: ALGN | E84: 54537000 | F84: 261621000 | G84: 200376000 | H84: 397115000 | I84: 677098000 | J84: 225446000 | K84: 225446000 | M84: 61245000 | N84: 894771000 | O84: 669325000 | P84: 217673000 | Q84: 36175000 | R84: 200376000 | S84: 200376000
A85: 83 | B85: 44196 | C85: Align Technology | D85: ALGN | E85: 48887000 | F85: 214542000 | G85: 158988000 | H85: 348392000 | I85: 610463000 | J85: 213184000 | K85: 213184000 | M85: 55554000 | N85: 834520000 | O85: 621336000 | P85: 224057000 | Q85: 1358000 | R85: 158988000 | S85: 158988000
A86: 84 | B86: 44469 | C86: Allegion | D86: ALLE | F86: 140800000 | G86: 143500000 | H86: 160000000 | I86: 300500000 | J86: 140500000 | K86: 140500000 | L86: -12300000 | M86: -2800000 | N86: 717000000 | O86: 576500000 | P86: 416500000 | Q86: 300000 | R86: 143600000 | S86: 143500000
A87: 85 | B87: 44377 | C87: Allegion | D87: ALLE | F87: 136200000 | G87: 118700000 | H87: 173100000 | I87: 320500000 | J87: 147400000 | K87: 147400000 | L87: -12400000 | M87: 17400000 | N87: 746900000 | O87: 599500000 | P87: 426400000 | Q87: -11200000 | R87: 118800000 | S87: 118700000
A88: 86 | B88: 44286 | C88: Allegion | D88: ALLE | F88: 122500000 | G88: 108000000 | H88: 164200000 | I88: 297400000 | J88: 133200000 | K88: 133200000 | L88: -12300000 | M88: 14300000 | N88: 694300000 | O88: 561100000 | P88: 396900000 | Q88: -10700000 | R88: 108200000 | S88: 108000000
A89: 87 | B89: 44196 | C89: Allegion | D89: ALLE | F89: 105800000 | G89: 93300000 | H89: 156600000 | I89: 320700000 | J89: 164100000 | K89: 164100000 | L89: -12300000 | M89: 12400000 | N89: 727300000 | O89: 563200000 | P89: 406600000 | Q89: -58300000 | R89: 93400000 | S89: 93300000
A90: 88 | B90: 44469 | C90: Alliant Energy | D90: LNT | F90: 235000000 | G90: 256000000 | I90: 480000000 | J90: 289000000 | K90: 289000000 | L90: -71000000 | M90: -21000000 | N90: 1024000000 | O90: 735000000 | P90: 544000000 | Q90: -54000000 | R90: 256000000 | S90: 256000000
A91: 89 | B91: 44377 | C91: Alliant Energy | D91: LNT | F91: 127000000 | G91: 144000000 | I91: 367000000 | J91: 176000000 | K91: 176000000 | L91: -71000000 | M91: -17000000 | N91: 817000000 | O91: 641000000 | P91: 450000000 | Q91: -49000000 | R91: 144000000 | S91: 144000000
A92: 90 | B92: 44286 | C92: Alliant Energy | D92: LNT | F92: 143000000 | G92: 171000000 | I92: 388000000 | J92: 198000000 | K92: 198000000 | L92: -72000000 | M92: -28000000 | N92: 901000000 | O92: 703000000 | P92: 513000000 | Q92: -55000000 | R92: 171000000 | S92: 171000000
A93: 91 | B93: 44196 | C93: Alliant Energy | D93: LNT | F93: 54000000 | G93: 64000000 | H93: 24000000 | I93: 299000000 | J93: 88000000 | K93: 88000000 | L93: -70000000 | M93: -10000000 | N93: 817000000 | O93: 729000000 | P93: 518000000 | Q93: -34000000 | R93: 64000000 | S93: 64000000
A94: 92 | B94: 44469 | C94: Allstate Corp | D94: ALL | F94: 226000000 | G94: 538000000 | H94: 1930000000 | I94: 2357000000 | J94: 318000000 | K94: 318000000 | L94: -69000000 | M94: 20000000 | N94: 12480000000 | O94: 12162000000 | P94: 10123000000 | Q94: -92000000 | R94: 206000000 | S94: 508000000
A95: 93 | B95: 44377 | C95: Allstate Corp | D95: ALL | F95: 1797000000 | G95: 1625000000 | H95: 1549000000 | I95: 3642000000 | J95: 1988000000 | K95: 1988000000 | L95: -91000000 | M95: 362000000 | N95: 12646000000 | O95: 10658000000 | P95: 9004000000 | Q95: -191000000 | R95: 1435000000 | S95: 1595000000
A96: 94 | B96: 44286 | C96: Allstate Corp | D96: ALL | F96: 3032000000 | G96: -1381000000 | H96: 1399000000 | I96: 4643000000 | J96: 3191000000 | K96: 3191000000 | L96: -86000000 | M96: 626000000 | N96: 12451000000 | O96: 9260000000 | P96: 7808000000 | Q96: -159000000 | R96: 2406000000 | S96: -1408000000
A97: 95 | B97: 44196 | C97: Allstate Corp | D97: ALL | F97: 3310000000 | G97: 2624000000 | H97: 1131000000 | I97: 4590000000 | J97: 3429000000 | K97: 3429000000 | L97: -80000000 | M97: 686000000 | N97: 12018000000 | O97: 8589000000 | P97: 7428000000 | Q97: -119000000 | R97: 2624000000 | S97: 2598000000
A98: 96 | B98: 44377 | C98: Alphabet (Class A) | D98: GOOGL | E98: 7675000000 | F98: 21985000000 | G98: 18525000000 | H98: 8617000000 | I98: 35653000000 | J98: 19361000000 | K98: 19361000000 | L98: -76000000 | M98: 3460000000 | N98: 61880000000 | O98: 42519000000 | P98: 26227000000 | Q98: 2624000000 | R98: 18525000000 | S98: 18525000000
A99: 97 | B99: 44286 | C99: Alphabet (Class A) | D99: GOOGL | E99: 7485000000 | F99: 21283000000 | G99: 17930000000 | H99: 7289000000 | I99: 31211000000 | J99: 16437000000 | K99: 16437000000 | L99: -76000000 | M99: 3353000000 | N99: 55314000000 | O99: 38877000000 | P99: 24103000000 | Q99: 4846000000 | R99: 17930000000 | S99: 17930000000
A100: 98 | B100: 44196 | C100: Alphabet (Class A) | D100: GOOGL | E100: 7022000000 | F100: 18689000000 | G100: 15227000000 | H100: 8145000000 | I100: 30818000000 | J100: 15651000000 | K100: 15651000000 | L100: -53000000 | M100: 3462000000 | N100: 56898000000 | O100: 41247000000 | P100: 26080000000 | Q100: 3038000000 | R100: 15227000000 | S100: 15227000000
A101: 99 | B101: 44104 | C101: Alphabet (Class A) | D101: GOOGL | E101: 6856000000 | F101: 13359000000 | G101: 11247000000 | H101: 6987000000 | I101: 25056000000 | J101: 11213000000 | K101: 11213000000 | L101: -48000000 | M101: 2112000000 | N101: 46173000000 | O101: 34960000000 | P101: 21117000000 | Q101: 2146000000 | R101: 11247000000 | S101: 11247000000
A102: 100 | B102: 44377 | C102: Alphabet (Class C) | D102: GOOG | E102: 7675000000 | F102: 21985000000 | G102: 18525000000 | H102: 8617000000 | I102: 35653000000 | J102: 19361000000 | K102: 19361000000 | L102: -76000000 | M102: 3460000000 | N102: 61880000000 | O102: 42519000000 | P102: 26227000000 | Q102: 2624000000 | R102: 18525000000 | S102: 18525000000
A103: 101 | B103: 44286 | C103: Alphabet (Class C) | D103: GOOG | E103: 7485000000 | F103: 21283000000 | G103: 17930000000 | H103: 7289000000 | I103: 31211000000 | J103: 16437000000 | K103: 16437000000 | L103: -76000000 | M103: 3353000000 | N103: 55314000000 | O103: 38877000000 | P103: 24103000000 | Q103: 4846000000 | R103: 17930000000 | S103: 17930000000
...

Sheet Raw_Data
A1: S. NO. | B1: date | C1: firm | D1: Ticker | E1: Research Development | F1: Income Before Tax | G1: Net Income | H1: Selling General Administrative | I1: Gross Profit | J1: Ebit | K1: Operating Income | L1: Interest Expense | M1: Income Tax Expense | N1: Total Revenue | O1: Total Operating Expenses | P1: Cost Of Revenue | Q1: Total Other Income Expense Net | R1: Net Income From Continuing Ops | S1: Net Income Applicable To Common Shares
A2: 0 | B2: 44469 | C2: 3M | D2: MMM | E2: 482000000 | F2: 1761000000 | G2: 1434000000 | H2: 1739000000 | I2: 4089000000 | J2: 1868000000 | K2: 1868000000 | L2: -117000000 | M2: 324000000 | N2: 8942000000 | O2: 7074000000 | P2: 4853000000 | Q2: -107000000 | R2: 1437000000 | S2: 1434000000
A3: 1 | B3: 44377 | C3: 3M | D3: MMM | E3: 514000000 | F3: 1940000000 | G3: 1524000000 | H3: 1666000000 | I3: 4231000000 | J3: 2051000000 | K3: 2051000000 | L3: -121000000 | M3: 415000000 | N3: 8950000000 | O3: 6899000000 | P3: 4719000000 | Q3: -111000000 | R3: 1525000000 | S3: 1524000000 | W3: =Raw_Data!C2&"|"&Raw_Data!D2&"|"&TEXT(Raw_Data!B2,"yyyy-mm-dd") -> 3M|MMM|2021-09-30
A4: 2 | B4: 44286 | C4: 3M | D4: MMM | E4: 520000000 | F4: 1946000000 | G4: 1624000000 | H4: 1720000000 | I4: 4327000000 | J4: 2087000000 | K4: 2087000000 | L4: -132000000 | M4: 319000000 | N4: 8851000000 | O4: 6764000000 | P4: 4524000000 | Q4: -141000000 | R4: 1627000000 | S4: 1624000000 | W4: =Raw_Data!C3&"|"&Raw_Data!D3&"|"&TEXT(Raw_Data!B3,"yyyy-mm-dd") -> 3M|MMM|2021-06-30
A5: 3 | B5: 44196 | C5: 3M | D5: MMM | E5: 449000000 | F5: 1706000000 | G5: 1389000000 | H5: 1814000000 | I5: 4246000000 | J5: 1983000000 | K5: 1983000000 | L5: -141000000 | M5: 316000000 | N5: 8583000000 | O5: 6600000000 | P5: 4337000000 | Q5: -277000000 | R5: 1390000000 | S5: 1389000000 | W5: =Raw_Data!C4&"|"&Raw_Data!D4&"|"&TEXT(Raw_Data!B4,"yyyy-mm-dd") -> 3M|MMM|2021-03-31
A6: 4 | B6: 44469 | C6: 3M | D6: MMM | E6: 482000000 | F6: 1761000000 | G6: 1434000000 | H6: 1739000000 | I6: 4089000000 | J6: 1868000000 | K6: 1868000000 | L6: -117000000 | M6: 324000000 | N6: 8942000000 | O6: 7074000000 | P6: 4853000000 | Q6: -107000000 | R6: 1437000000 | S6: 1434000000 | W6: =Raw_Data!C5&"|"&Raw_Data!D5&"|"&TEXT(Raw_Data!B5,"yyyy-mm-dd") -> 3M|MMM|2020-12-31
A7: 5 | B7: 44377 | C7: 3M | D7: MMM | E7: 514000000 | F7: 1940000000 | G7: 1524000000 | H7: 1666000000 | I7: 4231000000 | J7: 2051000000 | K7: 2051000000 | L7: -121000000 | M7: 415000000 | N7: 8950000000 | O7: 6899000000 | P7: 4719000000 | Q7: -111000000 | R7: 1525000000 | S7: 1524000000 | W7: =Raw_Data!C6&"|"&Raw_Data!D6&"|"&TEXT(Raw_Data!B6,"yyyy-mm-dd") -> 3M|MMM|2021-09-30
A8: 6 | B8: 44286 | C8: 3M | D8: MMM | E8: 520000000 | F8: 1946000000 | G8: 1624000000 | H8: 1720000000 | I8: 4327000000 | J8: 2087000000 | K8: 2087000000 | L8: -132000000 | M8: 319000000 | N8: 8851000000 | O8: 6764000000 | P8: 4524000000 | Q8: -141000000 | R8: 1627000000 | S8: 1624000000 | W8: =Raw_Data!C7&"|"&Raw_Data!D7&"|"&TEXT(Raw_Data!B7,"yyyy-mm-dd") -> 3M|MMM|2021-06-30
A9: 7 | B9: 44196 | C9: 3M | D9: MMM | E9: 449000000 | F9: 1706000000 | G9: 1389000000 | H9: 1814000000 | I9: 4246000000 | J9: 1983000000 | K9: 1983000000 | L9: -141000000 | M9: 316000000 | N9: 8583000000 | O9: 6600000000 | P9: 4337000000 | Q9: -277000000 | R9: 1390000000 | S9: 1389000000 | W9: =Raw_Data!C8&"|"&Raw_Data!D8&"|"&TEXT(Raw_Data!B8,"yyyy-mm-dd") -> 3M|MMM|2021-03-31
A10: 8 | B10: 44469 | C10: A. O. Smith | D10: AOS | F10: 166400000 | G10: 131600000 | H10: 174300000 | I10: 340300000 | J10: 166000000 | K10: 166000000 | L10: -1000000 | M10: 34800000 | N10: 914600000 | O10: 748600000 | P10: 574300000 | Q10: 400000 | R10: 131600000 | S10: 131600000 | W10: =Raw_Data!C9&"|"&Raw_Data!D9&"|"&TEXT(Raw_Data!B9,"yyyy-mm-dd") -> 3M|MMM|2020-12-31
A11: 9 | B11: 44377 | C11: A. O. Smith | D11: AOS | F11: 151300000 | G11: 118200000 | H11: 169800000 | I11: 321400000 | J11: 151600000 | K11: 151600000 | L11: -900000 | M11: 33100000 | N11: 859800000 | O11: 708200000 | P11: 538400000 | Q11: -300000 | R11: 118200000 | S11: 118200000 | W11: =Raw_Data!C10&"|"&Raw_Data!D10&"|"&TEXT(Raw_Data!B10,"yyyy-mm-dd") -> A. O. Smith|AOS|2021-09-30
A12: 10 | B12: 44286 | C12: A. O. Smith | D12: AOS | F12: 126100000 | G12: 97700000 | H12: 166500000 | I12: 288600000 | J12: 122100000 | K12: 122100000 | L12: -1000000 | M12: 28400000 | N12: 769000000 | O12: 646900000 | P12: 480400000 | Q12: 4000000 | R12: 97700000 | S12: 97700000 | W12: =Raw_Data!C11&"|"&Raw_Data!D11&"|"&TEXT(Raw_Data!B11,"yyyy-mm-dd") -> A. O. Smith|AOS|2021-06-30
A13: 11 | B13: 44196 | C13: A. O. Smith | D13: AOS | F13: 151900000 | G13: 120000000 | H13: 184700000 | I13: 324100000 | J13: 139400000 | K13: 139400000 | L13: -1000000 | M13: 31900000 | N13: 834500000 | O13: 695100000 | P13: 510400000 | Q13: 12500000 | R13: 120000000 | S13: 120000000 | W13: =Raw_Data!C12&"|"&Raw_Data!D12&"|"&TEXT(Raw_Data!B12,"yyyy-mm-dd") -> A. O. Smith|AOS|2021-03-31
A14: 12 | B14: 44469 | C14: Abbott Laboratories | D14: ABT | E14: 672000000 | F14: 2493000000 | G14: 2100000000 | H14: 2699000000 | I14: 6505000000 | J14: 2614000000 | K14: 2614000000 | L14: -133000000 | M14: 393000000 | N14: 10928000000 | O14: 8314000000 | P14: 4423000000 | Q14: -121000000 | R14: 2100000000 | S14: 2092000000 | W14: =Raw_Data!C13&"|"&Raw_Data!D13&"|"&TEXT(Raw_Data!B13,"yyyy-mm-dd") -> A. O. Smith|AOS|2020-12-31
A15: 13 | B15: 44377 | C15: Abbott Laboratories | D15: ABT | E15: 654000000 | F15: 1348000000 | G15: 1189000000 | H15: 2658000000 | I15: 5786000000 | J15: 1970000000 | K15: 1970000000 | L15: -134000000 | M15: 159000000 | N15: 10223000000 | O15: 8253000000 | P15: 4437000000 | Q15: -622000000 | R15: 1189000000 | S15: 1184000000 | W15: =Raw_Data!C14&"|"&Raw_Data!D14&"|"&TEXT(Raw_Data!B14,"yyyy-mm-dd") -> Abbott Laboratories|ABT|2021-09-30
A16: 14 | B16: 44286 | C16: Abbott Laboratories | D16: ABT | E16: 654000000 | F16: 2043000000 | G16: 1793000000 | H16: 2716000000 | I16: 6056000000 | J16: 2177000000 | K16: 2177000000 | L16: -135000000 | M16: 250000000 | N16: 10456000000 | O16: 8279000000 | P16: 4400000000 | Q16: -134000000 | R16: 1793000000 | S16: 1785000000 | W16: =Raw_Data!C15&"|"&Raw_Data!D15&"|"&TEXT(Raw_Data!B15,"yyyy-mm-dd") -> Abbott Laboratories|ABT|2021-06-30
A17: 15 | B17: 44196 | C17: Abbott Laboratories | D17: ABT | E17: 643000000 | F17: 2388000000 | G17: 2162000000 | H17: 2525000000 | I17: 6207000000 | J17: 2531000000 | K17: 2531000000 | L17: -136000000 | M17: 230000000 | N17: 10701000000 | O17: 8170000000 | P17: 4494000000 | Q17: -143000000 | R17: 2158000000 | S17: 2151000000 | W17: =Raw_Data!C16&"|"&Raw_Data!D16&"|"&TEXT(Raw_Data!B16,"yyyy-mm-dd") -> Abbott Laboratories|ABT|2021-03-31
A18: 16 | B18: 44469 | C18: AbbVie | D18: ABBV | E18: 1655000000 | F18: 3688000000 | G18: 3179000000 | H18: 2946000000 | I18: 9998000000 | J18: 4897000000 | K18: 4897000000 | L18: -596000000 | M18: 508000000 | N18: 14342000000 | O18: 9445000000 | P18: 4344000000 | Q18: -1209000000 | R18: 3180000000 | S18: 3158000000 | W18: =Raw_Data!C17&"|"&Raw_Data!D17&"|"&TEXT(Raw_Data!B17,"yyyy-mm-dd") -> Abbott Laboratories|ABT|2020-12-31
A19: 17 | B19: 44377 | C19: AbbVie | D19: ABBV | E19: 1784000000 | F19: 1163000000 | G19: 766000000 | H19: 3049000000 | I19: 9461000000 | J19: 4696000000 | K19: 4696000000 | L19: -615000000 | M19: 394000000 | N19: 13959000000 | O19: 9263000000 | P19: 4498000000 | Q19: -3533000000 | R19: 769000000 | S19: 751000000 | W19: =Raw_Data!C18&"|"&Raw_Data!D18&"|"&TEXT(Raw_Data!B18,"yyyy-mm-dd") -> AbbVie|ABBV|2021-09-30
A20: 18 | B20: 44286 | C20: AbbVie | D20: ABBV | E20: 1731000000 | F20: 3867000000 | G20: 3553000000 | H20: 2741000000 | I20: 8818000000 | J20: 4346000000 | K20: 4346000000 | L20: -632000000 | M20: 312000000 | N20: 13010000000 | O20: 8664000000 | P20: 4192000000 | Q20: -479000000 | R20: 3555000000 | S20: 3536000000 | W20: =Raw_Data!C19&"|"&Raw_Data!D19&"|"&TEXT(Raw_Data!B19,"yyyy-mm-dd") -> AbbVie|ABBV|2021-06-30
A21: 19 | B21: 44196 | C21: AbbVie | D21: ABBV | E21: 1821000000 | F21: -1507000000 | G21: 36000000 | H21: 3099000000 | I21: 10448000000 | J21: 5528000000 | K21: 5528000000 | L21: -629000000 | M21: -1545000000 | N21: 13858000000 | O21: 8330000000 | P21: 3410000000 | Q21: -7035000000 | R21: 38000000 | S21: 20000000 | W21: =Raw_Data!C20&"|"&Raw_Data!D20&"|"&TEXT(Raw_Data!B20,"yyyy-mm-dd") -> AbbVie|ABBV|2021-03-31
A22: 20 | B22: 44469 | C22: Abiomed | D22: ABMD | E22: 41041000 | F22: 67271000 | G22: 56953000 | H22: 102779000 | I22: 204256000 | J22: 60436000 | K22: 60436000 | M22: 10318000 | N22: 248142000 | O22: 187706000 | P22: 43886000 | Q22: 6835000 | R22: 56953000 | S22: 56953000 | W22: =Raw_Data!C21&"|"&Raw_Data!D21&"|"&TEXT(Raw_Data!B21,"yyyy-mm-dd") -> AbbVie|ABBV|2020-12-31
A23: 21 | B23: 44377 | C23: Abiomed | D23: ABMD | E23: 36837000 | F23: -9350000 | G23: -26525000 | H23: 103484000 | I23: 207397000 | J23: 67076000 | K23: 67076000 | M23: 17175000 | N23: 252585000 | O23: 185509000 | P23: 45188000 | Q23: -76426000 | R23: -26525000 | S23: -26525000 | W23: =Raw_Data!C22&"|"&Raw_Data!D22&"|"&TEXT(Raw_Data!B22,"yyyy-mm-dd") -> Abiomed|ABMD|2021-09-30
A24: 22 | B24: 44286 | C24: Abiomed | D24: ABMD | E24: 32599000 | F24: 73494000 | G24: 56856000 | H24: 100374000 | I24: 195167000 | J24: 62194000 | K24: 62194000 | M24: 16638000 | N24: 241245000 | O24: 179051000 | P24: 46078000 | Q24: 11300000 | R24: 56856000 | S24: 56856000 | W24: =Raw_Data!C23&"|"&Raw_Data!D23&"|"&TEXT(Raw_Data!B23,"yyyy-mm-dd") -> Abiomed|ABMD|2021-06-30
A25: 23 | B25: 44196 | C25: Abiomed | D25: ABMD | E25: 32105000 | F25: 80735000 | G25: 61868000 | H25: 86198000 | I25: 190553000 | J25: 72250000 | K25: 72250000 | M25: 18867000 | N25: 231663000 | O25: 159413000 | P25: 41110000 | Q25: 8485000 | R25: 61868000 | S25: 61868000 | W25: =Raw_Data!C24&"|"&Raw_Data!D24&"|"&TEXT(Raw_Data!B24,"yyyy-mm-dd") -> Abiomed|ABMD|2021-03-31
A26: 24 | B26: 44439 | C26: Accenture | D26: ACN | F26: 1917805000 | G26: 1416248000 | H26: 2507527000 | I26: 4466216000 | J26: 1958689000 | K26: 1958689000 | L26: -12977000 | M26: 480382000 | N26: 13419284000 | O26: 11460595000 | P26: 8953068000 | Q26: -40884000 | R26: 1437423000 | S26: 1416248000 | W26: =Raw_Data!C25&"|"&Raw_Data!D25&"|"&TEXT(Raw_Data!B25,"yyyy-mm-dd") -> Abiomed|ABMD|2020-12-31
A27: 25 | B27: 44347 | C27: Accenture | D27: ACN | F27: 2094001000 | G27: 1549426000 | H27: 2285728000 | I27: 4404384000 | J27: 2118656000 | K27: 2118656000 | L27: -28739000 | M27: 524429000 | N27: 13263795000 | O27: 11145139000 | P27: 8859411000 | Q27: -24655000 | R27: 1569572000 | S27: 1549426000 | W27: =Raw_Data!C26&"|"&Raw_Data!D26&"|"&TEXT(Raw_Data!B26,"yyyy-mm-dd") -> Accenture|ACN|2021-08-31
A28: 26 | B28: 44255 | C28: Accenture | D28: ACN | F28: 1762443000 | G28: 1440859000 | H28: 1941717000 | I28: 3595232000 | J28: 1653515000 | K28: 1653515000 | L28: -8922000 | M28: 300950000 | N28: 12088125000 | O28: 10434610000 | P28: 8492893000 | Q28: 108928000 | R28: 1461493000 | S28: 1440859000 | W28: =Raw_Data!C27&"|"&Raw_Data!D27&"|"&TEXT(Raw_Data!B27,"yyyy-mm-dd") -> Accenture|ACN|2021-05-31
A29: 27 | B29: 44165 | C29: Accenture | D29: ACN | F29: 1986867000 | G29: 1500276000 | H29: 2007627000 | I29: 3898296000 | J29: 1890669000 | K29: 1890669000 | L29: -8854000 | M29: 464810000 | N29: 11762185000 | O29: 9871516000 | P29: 7863889000 | Q29: 96198000 | R29: 1522057000 | S29: 1500276000 | W29: =Raw_Data!C28&"|"&Raw_Data!D28&"|"&TEXT(Raw_Data!B28,"yyyy-mm-dd") -> Accenture|ACN|2021-02-28
A30: 28 | B30: 44469 | C30: Activision Blizzard | D30: ATVI | E30: 329000000 | F30: 759000000 | G30: 639000000 | H30: 387000000 | I30: 1543000000 | J30: 827000000 | K30: 827000000 | L30: -27000000 | M30: 120000000 | N30: 2070000000 | O30: 1243000000 | P30: 527000000 | Q30: -68000000 | R30: 639000000 | S30: 639000000 | W30: =Raw_Data!C29&"|"&Raw_Data!D29&"|"&TEXT(Raw_Data!B29,"yyyy-mm-dd") -> Accenture|ACN|2020-11-30
A31: 29 | B31: 44377 | C31: Activision Blizzard | D31: ATVI | E31: 335000000 | F31: 1002000000 | G31: 876000000 | H31: 434000000 | I31: 1741000000 | J31: 972000000 | K31: 972000000 | L31: -27000000 | M31: 126000000 | N31: 2296000000 | O31: 1324000000 | P31: 555000000 | Q31: 30000000 | R31: 876000000 | S31: 876000000 | W31: =Raw_Data!C30&"|"&Raw_Data!D30&"|"&TEXT(Raw_Data!B30,"yyyy-mm-dd") -> Activision Blizzard|ATVI|2021-09-30
A32: 30 | B32: 44286 | C32: Activision Blizzard | D32: ATVI | E32: 353000000 | F32: 765000000 | G32: 619000000 | H32: 519000000 | I32: 1697000000 | J32: 825000000 | K32: 825000000 | L32: -28000000 | M32: 146000000 | N32: 2275000000 | O32: 1450000000 | P32: 578000000 | Q32: -60000000 | R32: 619000000 | S32: 619000000 | W32: =Raw_Data!C31&"|"&Raw_Data!D31&"|"&TEXT(Raw_Data!B31,"yyyy-mm-dd") -> Activision Blizzard|ATVI|2021-06-30
A33: 31 | B33: 44196 | C33: Activision Blizzard | D33: ATVI | E33: 348000000 | F33: 563000000 | G33: 509000000 | H33: 597000000 | I33: 1595000000 | J33: 650000000 | K33: 650000000 | L33: -27000000 | M33: 54000000 | N33: 2412000000 | O33: 1762000000 | P33: 817000000 | Q33: -87000000 | R33: 509000000 | S33: 509000000 | W33: =Raw_Data!C32&"|"&Raw_Data!D32&"|"&TEXT(Raw_Data!B32,"yyyy-mm-dd") -> Activision Blizzard|ATVI|2021-03-31
A34: 32 | B34: 44469 | C34: ADM | D34: ADM | F34: 653000000 | G34: 526000000 | H34: 716000000 | I34: 1326000000 | J34: 607000000 | K34: 607000000 | L34: -61000000 | M34: 120000000 | N34: 20340000000 | O34: 19733000000 | P34: 19014000000 | Q34: 46000000 | R34: 533000000 | S34: 526000000 | W34: =Raw_Data!C33&"|"&Raw_Data!D33&"|"&TEXT(Raw_Data!B33,"yyyy-mm-dd") -> Activision Blizzard|ATVI|2020-12-31
A35: 33 | B35: 44377 | C35: ADM | D35: ADM | F35: 825000000 | G35: 712000000 | H35: 815000000 | I35: 1463000000 | J35: 642000000 | K35: 642000000 | L35: -40000000 | M35: 113000000 | N35: 22926000000 | O35: 22284000000 | P35: 21463000000 | Q35: 183000000 | R35: 712000000 | S35: 712000000 | W35: =Raw_Data!C34&"|"&Raw_Data!D34&"|"&TEXT(Raw_Data!B34,"yyyy-mm-dd") -> ADM|ADM|2021-09-30
A36: 34 | B36: 44286 | C36: ADM | D36: ADM | F36: 824000000 | G36: 689000000 | H36: 697000000 | I36: 1548000000 | J36: 843000000 | K36: 843000000 | L36: -87000000 | M36: 131000000 | N36: 18893000000 | O36: 18050000000 | P36: 17345000000 | Q36: -19000000 | R36: 693000000 | S36: 689000000 | W36: =Raw_Data!C35&"|"&Raw_Data!D35&"|"&TEXT(Raw_Data!B35,"yyyy-mm-dd") -> ADM|ADM|2021-06-30
A37: 35 | B37: 44196 | C37: ADM | D37: ADM | F37: 756000000 | G37: 687000000 | H37: 720000000 | I37: 1352000000 | J37: 615000000 | K37: 615000000 | L37: -69000000 | M37: 63000000 | N37: 17978000000 | O37: 17363000000 | P37: 16626000000 | Q37: 141000000 | R37: 693000000 | S37: 687000000 | W37: =Raw_Data!C36&"|"&Raw_Data!D36&"|"&TEXT(Raw_Data!B36,"yyyy-mm-dd") -> ADM|ADM|2021-03-31
A38: 36 | B38: 44442 | C38: Adobe | D38: ADBE | E38: 651000000 | F38: 1418000000 | G38: 1212000000 | H38: 1333000000 | I38: 3468000000 | J38: 1441000000 | K38: 1441000000 | L38: -27000000 | M38: 206000000 | N38: 3935000000 | O38: 2494000000 | P38: 467000000 | Q38: -23000000 | R38: 1212000000 | S38: 1212000000 | W38: =Raw_Data!C37&"|"&Raw_Data!D37&"|"&TEXT(Raw_Data!B37,"yyyy-mm-dd") -> ADM|ADM|2020-12-31
A39: 37 | B39: 44351 | C39: Adobe | D39: ADBE | E39: 612000000 | F39: 1386000000 | G39: 1116000000 | H39: 1329000000 | I39: 3391000000 | J39: 1406000000 | K39: 1406000000 | L39: -28000000 | M39: 270000000 | N39: 3835000000 | O39: 2429000000 | P39: 444000000 | Q39: -20000000 | R39: 1116000000 | S39: 1116000000 | W39: =Raw_Data!C38&"|"&Raw_Data!D38&"|"&TEXT(Raw_Data!B38,"yyyy-mm-dd") -> Adobe|ADBE|2021-09-03
A40: 38 | B40: 44260 | C40: Adobe | D40: ADBE | E40: 620000000 | F40: 1433000000 | G40: 1261000000 | H40: 1339000000 | I40: 3458000000 | J40: 1454000000 | K40: 1454000000 | L40: -30000000 | M40: 172000000 | N40: 3905000000 | O40: 2451000000 | P40: 447000000 | Q40: -21000000 | R40: 1261000000 | S40: 1261000000 | W40: =Raw_Data!C39&"|"&Raw_Data!D39&"|"&TEXT(Raw_Data!B39,"yyyy-mm-dd") -> Adobe|ADBE|2021-06-04
A41: 39 | B41: 44162 | C41: Adobe | D41: ADBE | E41: 558000000 | F41: 1197000000 | G41: 2250000000 | H41: 1184000000 | I41: 2996000000 | J41: 1215000000 | K41: 1215000000 | L41: -27000000 | M41: -1053000000 | N41: 3424000000 | O41: 2209000000 | P41: 428000000 | Q41: -18000000 | R41: 2250000000 | S41: 2250000000 | W41: =Raw_Data!C40&"|"&Raw_Data!D40&"|"&TEXT(Raw_Data!B40,"yyyy-mm-dd") -> Adobe|ADBE|2021-03-05
A42: 40 | B42: 44394 | C42: Advance Auto Parts | D42: AAP | F42: 237765000 | G42: 178696000 | H42: 932793000 | I42: 1189416000 | J42: 256623000 | K42: 256623000 | L42: -8306000 | M42: 59069000 | N42: 2649415000 | O42: 2392792000 | P42: 1459999000 | Q42: -18858000 | R42: 178696000 | S42: 178696000 | W42: =Raw_Data!C41&"|"&Raw_Data!D41&"|"&TEXT(Raw_Data!B41,"yyyy-mm-dd") -> Adobe|ADBE|2020-11-27
A43: 41 | B43: 44394 | C43: Advance Auto Parts | D43: AAP | F43: 237765000 | G43: 178696000 | H43: 932793000 | I43: 1189416000 | J43: 256623000 | K43: 256623000 | L43: -8306000 | M43: 0 | N43: 2649415000 | O43: 0 | P43: 0 | Q43: 0 | R43: 178696000 | S43: 178696000 | W43: =Raw_Data!C42&"|"&Raw_Data!D42&"|"&TEXT(Raw_Data!B42,"yyyy-mm-dd") -> Advance Auto Parts|AAP|2021-07-17
A44: 42 | B44: 44310 | C44: Advance Auto Parts | D44: AAP | F44: 245774000 | G44: 185930000 | H44: 1200138000 | I44: 1487229000 | J44: 287091000 | K44: 287091000 | L44: -11191000 | M44: 59844000 | N44: 3330370000 | O44: 3043279000 | P44: 1843141000 | Q44: -41317000 | R44: 185930000 | S44: 185930000 | W44: =Raw_Data!C43&"|"&Raw_Data!D43&"|"&TEXT(Raw_Data!B43,"yyyy-mm-dd") -> Advance Auto Parts|AAP|2021-07-17
A45: 43 | B45: 44303 | C45: Advance Auto Parts | D45: AAP | F45: 245774000 | G45: 182313000 | H45: 1200138000 | I45: 1338322500 | J45: 271856500 | K45: 287091000 | L45: -9748500 | M45: 0 | N45: 2989892500 | O45: 0 | P45: 0 | Q45: 0 | R45: 185930000 | S45: 185930000 | W45: =Raw_Data!C44&"|"&Raw_Data!D44&"|"&TEXT(Raw_Data!B44,"yyyy-mm-dd") -> Advance Auto Parts|AAP|2021-04-24
A46: 44 | B46: 44464 | C46: Advanced Micro Devices | D46: AMD | E46: 765000000 | F46: 1005000000 | G46: 923000000 | H46: 368000000 | I46: 2086000000 | J46: 956000000 | K46: 956000000 | L46: -7000000 | M46: 82000000 | N46: 4313000000 | O46: 3357000000 | P46: 2227000000 | Q46: 49000000 | R46: 923000000 | S46: 923000000 | W46: =Raw_Data!C45&"|"&Raw_Data!D45&"|"&TEXT(Raw_Data!B45,"yyyy-mm-dd") -> Advance Auto Parts|AAP|2021-04-17
A47: 45 | B47: 44373 | C47: Advanced Micro Devices | D47: AMD | E47: 659000000 | F47: 823000000 | G47: 710000000 | H47: 331000000 | I47: 1830000000 | J47: 841000000 | K47: 841000000 | L47: -10000000 | M47: 113000000 | N47: 3850000000 | O47: 3009000000 | P47: 2020000000 | Q47: -18000000 | R47: 710000000 | S47: 710000000 | W47: =Raw_Data!C46&"|"&Raw_Data!D46&"|"&TEXT(Raw_Data!B46,"yyyy-mm-dd") -> Advanced Micro Devices|AMD|2021-09-25
A48: 46 | B48: 44282 | C48: Advanced Micro Devices | D48: AMD | E48: 610000000 | F48: 644000000 | G48: 555000000 | H48: 304000000 | I48: 1587000000 | J48: 677000000 | K48: 677000000 | L48: -9000000 | M48: 89000000 | N48: 3445000000 | O48: 2768000000 | P48: 1858000000 | Q48: -33000000 | R48: 555000000 | S48: 555000000 | W48: =Raw_Data!C47&"|"&Raw_Data!D47&"|"&TEXT(Raw_Data!B47,"yyyy-mm-dd") -> Advanced Micro Devices|AMD|2021-06-26
A49: 47 | B49: 44191 | C49: Advanced Micro Devices | D49: AMD | E49: 573000000 | F49: 549000000 | G49: 1781000000 | H49: 308000000 | I49: 1451000000 | J49: 570000000 | K49: 570000000 | L49: -9000000 | M49: -1232000000 | N49: 3244000000 | O49: 2674000000 | P49: 1793000000 | Q49: -21000000 | R49: 1781000000 | S49: 1781000000 | W49: =Raw_Data!C48&"|"&Raw_Data!D48&"|"&TEXT(Raw_Data!B48,"yyyy-mm-dd") -> Advanced Micro Devices|AMD|2021-03-27
A50: 48 | B50: 44469 | C50: AES Corp | D50: AES | F50: 611000000 | G50: 343000000 | H50: 39000000 | I50: 760000000 | J50: 721000000 | K50: 721000000 | L50: -242000000 | M50: 126000000 | N50: 3036000000 | O50: 2315000000 | P50: 2276000000 | Q50: -110000000 | R50: 485000000 | S50: 343000000 | W50: =Raw_Data!C49&"|"&Raw_Data!D49&"|"&TEXT(Raw_Data!B49,"yyyy-mm-dd") -> Advanced Micro Devices|AMD|2020-12-26
A51: 49 | B51: 44377 | C51: AES Corp | D51: AES | F51: -140000000 | G51: 28000000 | H51: 45000000 | I51: 728000000 | J51: 683000000 | K51: 683000000 | L51: -237000000 | M51: -59000000 | N51: 2700000000 | O51: 2017000000 | P51: 1972000000 | Q51: -823000000 | R51: -81000000 | S51: 28000000 | W51: =Raw_Data!C50&"|"&Raw_Data!D50&"|"&TEXT(Raw_Data!B50,"yyyy-mm-dd") -> AES Corp|AES|2021-09-30
A52: 50 | B52: 44286 | C52: AES Corp | D52: AES | F52: -21000000 | G52: -148000000 | H52: 46000000 | I52: 664000000 | J52: 618000000 | K52: 618000000 | L52: -190000000 | M52: 8000000 | N52: 2635000000 | O52: 2017000000 | P52: 1971000000 | Q52: -639000000 | R52: -29000000 | S52: -148000000 | W52: =Raw_Data!C51&"|"&Raw_Data!D51&"|"&TEXT(Raw_Data!B51,"yyyy-mm-dd") -> AES Corp|AES|2021-06-30
A53: 51 | B53: 44196 | C53: AES Corp | D53: AES | F53: 562000000 | G53: 318000000 | H53: 47000000 | I53: 724000000 | J53: 677000000 | K53: 677000000 | L53: -297000000 | M53: 161000000 | N53: 2560000000 | O53: 1883000000 | P53: 1836000000 | Q53: -115000000 | R53: 401000000 | S53: 318000000 | W53: =Raw_Data!C52&"|"&Raw_Data!D52&"|"&TEXT(Raw_Data!B52,"yyyy-mm-dd") -> AES Corp|AES|2021-03-31
A54: 52 | B54: 44469 | C54: Aflac | D54: AFL | F54: 1113000000 | G54: 888000000 | H54: 869000000 | I54: 2039000000 | J54: 1170000000 | K54: 1170000000 | L54: -57000000 | M54: 225000000 | N54: 5237000000 | O54: 4067000000 | P54: 3198000000 | Q54: -57000000 | R54: 888000000 | S54: 888000000 | W54: =Raw_Data!C53&"|"&Raw_Data!D53&"|"&TEXT(Raw_Data!B53,"yyyy-mm-dd") -> AES Corp|AES|2020-12-31
A55: 53 | B55: 44377 | C55: Aflac | D55: AFL | F55: 1373000000 | G55: 1105000000 | H55: 881000000 | I55: 2316000000 | J55: 1435000000 | K55: 1435000000 | L55: -62000000 | M55: 268000000 | N55: 5564000000 | O55: 4129000000 | P55: 3248000000 | Q55: -62000000 | R55: 1105000000 | S55: 1105000000 | W55: =Raw_Data!C54&"|"&Raw_Data!D54&"|"&TEXT(Raw_Data!B54,"yyyy-mm-dd") -> Aflac|AFL|2021-09-30
A56: 54 | B56: 44286 | C56: Aflac | D56: AFL | F56: 1603000000 | G56: 1293000000 | H56: 832000000 | I56: 2497000000 | J56: 1665000000 | K56: 1665000000 | L56: -62000000 | M56: 310000000 | N56: 5869000000 | O56: 4204000000 | P56: 3372000000 | Q56: -62000000 | R56: 1293000000 | S56: 1293000000 | W56: =Raw_Data!C55&"|"&Raw_Data!D55&"|"&TEXT(Raw_Data!B55,"yyyy-mm-dd") -> Aflac|AFL|2021-06-30
A57: 55 | B57: 44196 | C57: Aflac | D57: AFL | F57: 1217000000 | G57: 952000000 | H57: 1038000000 | I57: 2316000000 | J57: 1278000000 | K57: 1278000000 | L57: -61000000 | M57: 265000000 | N57: 5913000000 | O57: 4635000000 | P57: 3597000000 | Q57: -61000000 | R57: 952000000 | S57: 952000000 | W57: =Raw_Data!C56&"|"&Raw_Data!D56&"|"&TEXT(Raw_Data!B56,"yyyy-mm-dd") -> Aflac|AFL|2021-03-31
A58: 56 | B58: 44408 | C58: Agilent Technologies | D58: A | E58: 113000000 | F58: 327000000 | G58: 264000000 | H58: 390000000 | I58: 852000000 | J58: 349000000 | K58: 349000000 | L58: -21000000 | M58: 63000000 | N58: 1586000000 | O58: 1237000000 | P58: 734000000 | Q58: -22000000 | R58: 264000000 | S58: 264000000 | W58: =Raw_Data!C57&"|"&Raw_Data!D57&"|"&TEXT(Raw_Data!B57,"yyyy-mm-dd") -> Aflac|AFL|2020-12-31
A59: 57 | B59: 44316 | C59: Agilent Technologies | D59: A | E59: 109000000 | F59: 273000000 | G59: 216000000 | H59: 420000000 | I59: 817000000 | J59: 288000000 | K59: 288000000 | L59: -20000000 | M59: 57000000 | N59: 1525000000 | O59: 1237000000 | P59: 708000000 | Q59: -15000000 | R59: 216000000 | S59: 216000000 | W59: =Raw_Data!C58&"|"&Raw_Data!D58&"|"&TEXT(Raw_Data!B58,"yyyy-mm-dd") -> Agilent Technologies|A|2021-07-31
A60: 58 | B60: 44227 | C60: Agilent Technologies | D60: A | E60: 103000000 | F60: 312000000 | G60: 288000000 | H60: 398000000 | I60: 838000000 | J60: 337000000 | K60: 337000000 | L60: -19000000 | M60: 24000000 | N60: 1548000000 | O60: 1211000000 | P60: 710000000 | Q60: -25000000 | R60: 288000000 | S60: 288000000 | W60: =Raw_Data!C59&"|"&Raw_Data!D59&"|"&TEXT(Raw_Data!B59,"yyyy-mm-dd") -> Agilent Technologies|A|2021-04-30
A61: 59 | B61: 44135 | C61: Agilent Technologies | D61: A | E61: 102000000 | F61: 283000000 | G61: 222000000 | H61: 342000000 | I61: 788000000 | J61: 344000000 | K61: 344000000 | L61: -19000000 | M61: 61000000 | N61: 1483000000 | O61: 1139000000 | P61: 695000000 | Q61: -61000000 | R61: 222000000 | S61: 222000000 | W61: =Raw_Data!C60&"|"&Raw_Data!D60&"|"&TEXT(Raw_Data!B60,"yyyy-mm-dd") -> Agilent Technologies|A|2021-01-31
A62: 60 | B62: 44469 | C62: Air Products & Chemicals | D62: APD | E62: 25700000 | F62: 692300000 | G62: 610400000 | H62: 202100000 | I62: 834800000 | J62: 616700000 | K62: 616700000 | L62: -33400000 | M62: 125300000 | N62: 2841100000 | O62: 2224400000 | P62: 2006300000 | Q62: 75600000 | R62: 567000000 | S62: 610400000 | W62: =Raw_Data!C61&"|"&Raw_Data!D61&"|"&TEXT(Raw_Data!B61,"yyyy-mm-dd") -> Agilent Technologies|A|2020-10-31
A63: 61 | B63: 44377 | C63: Air Products & Chemicals | D63: APD | E63: 23200000 | F63: 625800000 | G63: 533600000 | H63: 192600000 | I63: 802800000 | J63: 598400000 | K63: 598400000 | L63: -35600000 | M63: 101700000 | N63: 2604700000 | O63: 2006300000 | P63: 1801900000 | Q63: 27400000 | R63: 524100000 | S63: 533600000 | W63: =Raw_Data!C62&"|"&Raw_Data!D62&"|"&TEXT(Raw_Data!B62,"yyyy-mm-dd") -> Air Products & Chemicals|APD|2021-09-30
A64: 62 | B64: 44286 | C64: Air Products & Chemicals | D64: APD | E64: 21100000 | F64: 599000000 | G64: 473100000 | H64: 189100000 | I64: 756500000 | J64: 555800000 | K64: 555800000 | L64: -36100000 | M64: 121900000 | N64: 2502000000 | O64: 1946200000 | P64: 1745500000 | Q64: 43200000 | R64: 477100000 | S64: 473100000 | W64: =Raw_Data!C63&"|"&Raw_Data!D63&"|"&TEXT(Raw_Data!B63,"yyyy-mm-dd") -> Air Products & Chemicals|APD|2021-06-30
A65: 63 | B65: 44196 | C65: Air Products & Chemicals | D65: APD | E65: 23500000 | F65: 590300000 | G65: 482000000 | H65: 182100000 | I65: 742800000 | J65: 562500000 | K65: 562500000 | L65: -36700000 | M65: 113900000 | N65: 2375200000 | O65: 1812700000 | P65: 1632400000 | Q65: 27800000 | R65: 476400000 | S65: 482000000 | W65: =Raw_Data!C64&"|"&Raw_Data!D64&"|"&TEXT(Raw_Data!B64,"yyyy-mm-dd") -> Air Products & Chemicals|APD|2021-03-31
A66: 64 | B66: 44469 | C66: Akamai Technologies | D66: AKAM | E66: 82899000 | F66: 192564000 | G66: 178916000 | H66: 241463000 | I66: 543467000 | J66: 207146000 | K66: 207146000 | L66: -18144000 | M66: 13648000 | N66: 860333000 | O66: 653187000 | P66: 316866000 | Q66: -14582000 | R66: 178916000 | S66: 178916000 | W66: =Raw_Data!C65&"|"&Raw_Data!D65&"|"&TEXT(Raw_Data!B65,"yyyy-mm-dd") -> Air Products & Chemicals|APD|2020-12-31
A67: 65 | B67: 44377 | C67: Akamai Technologies | D67: AKAM | E67: 77255000 | F67: 174506000 | G67: 156497000 | H67: 246049000 | I67: 532824000 | J67: 197460000 | K67: 197460000 | L67: -18037000 | M67: 18009000 | N67: 852824000 | O67: 655364000 | P67: 320000000 | Q67: -22954000 | R67: 156497000 | S67: 156497000 | W67: =Raw_Data!C66&"|"&Raw_Data!D66&"|"&TEXT(Raw_Data!B66,"yyyy-mm-dd") -> Akamai Technologies|AKAM|2021-09-30
A68: 66 | B68: 44286 | C68: Akamai Technologies | D68: AKAM | E68: 82045000 | F68: 167593000 | G68: 155695000 | H68: 253005000 | I68: 536021000 | J68: 189544000 | K68: 189544000 | L68: -17834000 | M68: 11898000 | N68: 842708000 | O68: 653164000 | P68: 306687000 | Q68: -21951000 | R68: 155695000 | S68: 155695000 | W68: =Raw_Data!C67&"|"&Raw_Data!D67&"|"&TEXT(Raw_Data!B67,"yyyy-mm-dd") -> Akamai Technologies|AKAM|2021-06-30
A69: 67 | B69: 44196 | C69: Akamai Technologies | D69: AKAM | E69: 67228000 | F69: 117528000 | G69: 113370000 | H69: 298739000 | I69: 542440000 | J69: 165579000 | K69: 165579000 | L69: -17342000 | M69: 4158000 | N69: 846287000 | O69: 680708000 | P69: 303847000 | Q69: -48051000 | R69: 113370000 | S69: 113370000 | W69: =Raw_Data!C68&"|"&Raw_Data!D68&"|"&TEXT(Raw_Data!B68,"yyyy-mm-dd") -> Akamai Technologies|AKAM|2021-03-31
... A73: 71 | B73: 44196 | C73: Alaska Air Group | D73: ALB | E73: 15375000 | F73: 92076000 | G73: 84635000 | H73: 115008000 | I73: 266720000 | J73: 136337000 | K73: 136337000 | L73: -19152000 | M73: -10101000 | N73: 879147000 | O73: 742810000 | P73: 612427000 | Q73: -44261000 | R73: 102177000 | S73: 84635000 | W73: =Raw_Data!C72&"|"&Raw_Data!D72&"|"&TEXT(Raw_Data!B72,"yyyy-mm-dd") -> Alaska Air Group|ALB|2021-03-31
A74: 72 | B74: 44469 | C74: Albemarle Corporation | D74: ALK | F74: 245000000 | G74: 194000000 | H74: 49000000 | I74: 562000000 | J74: 257000000 | K74: 257000000 | L74: -27000000 | M74: 51000000 | N74: 1953000000 | O74: 1696000000 | P74: 1391000000 | Q74: -12000000 | R74: 194000000 | S74: 194000000 | W74: =Raw_Data!C73&"|"&Raw_Data!D73&"|"&TEXT(Raw_Data!B73,"yyyy-mm-dd") -> Alaska Air Group|ALB|2020-12-31
A75: 73 | B75: 44377 | C75: Albemarle Corporation | D75: ALK | F75: 528000000 | G75: 397000000 | H75: 41000000 | I75: 246000000 | J75: -36000000 | K75: -36000000 | L75: -36000000 | M75: 131000000 | N75: 1527000000 | O75: 1563000000 | P75: 1281000000 | Q75: 564000000 | R75: 397000000 | S75: 397000000 | W75: =Raw_Data!C74&"|"&Raw_Data!D74&"|"&TEXT(Raw_Data!B74,"yyyy-mm-dd") -> Albemarle Corporation|ALK|2021-09-30
A76: 74 | B76: 44286 | C76: Albemarle Corporation | D76: ALK | F76: -173000000 | G76: -131000000 | H76: 33000000 | I76: -312000000 | J76: -573000000 | K76: -573000000 | L76: -29000000 | M76: -42000000 | N76: 797000000 | O76: 1370000000 | P76: 1109000000 | Q76: 400000000 | R76: -131000000 | S76: -131000000 | W76: =Raw_Data!C75&"|"&Raw_Data!D75&"|"&TEXT(Raw_Data!B75,"yyyy-mm-dd") -> Albemarle Corporation|ALK|2021-06-30
A77: 75 | B77: 44196 | C77: Albemarle Corporation | D77: ALK | F77: -643000000 | G77: -447000000 | H77: 18000000 | I77: -213000000 | J77: -449000000 | K77: -449000000 | L77: -31000000 | M77: -196000000 | N77: 808000000 | O77: 1257000000 | P77: 1021000000 | Q77: -194000000 | R77: -447000000 | S77: -447000000 | W77: =Raw_Data!C76&"|"&Raw_Data!D76&"|"&TEXT(Raw_Data!B76,"yyyy-mm-dd") -> Albemarle Corporation|ALK|2021-03-31
A78: 76 | B78: 44469 | C78: Alexandria Real Estate Equities | D78: ARE | F78: 124433000 | G78: 103147000 | H78: 37931000 | I78: 384855000 | J78: 136082000 | K78: 136082000 | L78: -35678000 | M78: 0 | N78: 550850000 | O78: 414768000 | P78: 165995000 | Q78: -11649000 | R78: 124433000 | S78: 101264000 | W78: =Raw_Data!C77&"|"&Raw_Data!D77&"|"&TEXT(Raw_Data!B77,"yyyy-mm-dd") -> Albemarle Corporation|ALK|2020-12-31
A79: 77 | B79: 44377 | C79: Alexandria Real Estate Equities | D79: ARE | F79: 404520000 | G79: 385084000 | H79: 37880000 | I79: 368273000 | J79: 140341000 | K79: 140341000 | L79: -35158000 | M79: 0 | N79: 512228000 | O79: 371887000 | P79: 143955000 | Q79: 264179000 | R79: 404520000 | S79: 380563000 | W79: =Raw_Data!C78&"|"&Raw_Data!D78&"|"&TEXT(Raw_Data!B78,"yyyy-mm-dd") -> Alexandria Real Estate Equities|ARE|2021-09-30
A80: 78 | B80: 44286 | C80: Alexandria Real Estate Equities | D80: ARE | F80: 25533000 | G80: 8121000 | H80: 33996000 | I80: 345498000 | J80: 130589000 | K80: 130589000 | L80: -36467000 | M80: 0 | N80: 483386000 | O80: 352797000 | P80: 137888000 | Q80: -105056000 | R80: 25533000 | S80: 7979000 | W80: =Raw_Data!C79&"|"&Raw_Data!D79&"|"&TEXT(Raw_Data!B79,"yyyy-mm-dd") -> Alexandria Real Estate Equities|ARE|2021-06-30
A81: 79 | B81: 44196 | C81: Alexandria Real Estate Equities | D81: ARE | F81: 457133000 | G81: 441484000 | H81: 32690000 | I81: 330546000 | J81: 120106000 | K81: 120106000 | L81: -37538000 | M81: 0 | N81: 467313000 | O81: 347207000 | P81: 136767000 | Q81: 337027000 | R81: 457133000 | S81: 436620000 | W81: =Raw_Data!C80&"|"&Raw_Data!D80&"|"&TEXT(Raw_Data!B80,"yyyy-mm-dd") -> Alexandria Real Estate Equities|ARE|2021-03-31
A82: 80 | B82: 44469 | C82: Align Technology | D82: ALGN | E82: 65587000 | F82: 261988000 | G82: 180969000 | H82: 428409000 | I82: 755156000 | J82: 261160000 | K82: 261160000 | M82: 81019000 | N82: 1015906000 | O82: 754746000 | P82: 260750000 | Q82: 828000 | R82: 180969000 | S82: 180969000 | W82: =Raw_Data!C81&"|"&Raw_Data!D81&"|"&TEXT(Raw_Data!B81,"yyyy-mm-dd") -> Alexandria Real Estate Equities|ARE|2020-12-31
A83: 81 | B83: 44377 | C83: Align Technology | D83: ALGN | E83: 57715000 | F83: 268802000 | G83: 199714000 | H83: 431921000 | I83: 758538000 | J83: 268902000 | K83: 268902000 | M83: 69088000 | N83: 1010808000 | O83: 741906000 | P83: 252270000 | Q83: -100000 | R83: 199714000 | S83: 199714000 | W83: =Raw_Data!C82&"|"&Raw_Data!D82&"|"&TEXT(Raw_Data!B82,"yyyy-mm-dd") -> Align Technology|ALGN|2021-09-30
A84: 82 | B84: 44286 | C84: Align Technology | D84: ALGN | E84: 54537000 | F84: 261621000 | G84: 200376000 | H84: 397115000 | I84: 677098000 | J84: 225446000 | K84: 225446000 | M84: 61245000 | N84: 894771000 | O84: 669325000 | P84: 217673000 | Q84: 36175000 | R84: 200376000 | S84: 200376000 | W84: =Raw_Data!C83&"|"&Raw_Data!D83&"|"&TEXT(Raw_Data!B83,"yyyy-mm-dd") -> Align Technology|ALGN|2021-06-30
A85: 83 | B85: 44196 | C85: Align Technology | D85: ALGN | E85: 48887000 | F85: 214542000 | G85: 158988000 | H85: 348392000 | I85: 610463000 | J85: 213184000 | K85: 213184000 | M85: 55554000 | N85: 834520000 | O85: 621336000 | P85: 224057000 | Q85: 1358000 | R85: 158988000 | S85: 158988000 | W85: =Raw_Data!C84&"|"&Raw_Data!D84&"|"&TEXT(Raw_Data!B84,"yyyy-mm-dd") -> Align Technology|ALGN|2021-03-31
A86: 84 | B86: 44469 | C86: Allegion | D86: ALLE | F86: 140800000 | G86: 143500000 | H86: 160000000 | I86: 300500000 | J86: 140500000 | K86: 140500000 | L86: -12300000 | M86: -2800000 | N86: 717000000 | O86: 576500000 | P86: 416500000 | Q86: 300000 | R86: 143600000 | S86: 143500000 | W86: =Raw_Data!C85&"|"&Raw_Data!D85&"|"&TEXT(Raw_Data!B85,"yyyy-mm-dd") -> Align Technology|ALGN|2020-12-31
A87: 85 | B87: 44377 | C87: Allegion | D87: ALLE | F87: 136200000 | G87: 118700000 | H87: 173100000 | I87: 320500000 | J87: 147400000 | K87: 147400000 | L87: -12400000 | M87: 17400000 | N87: 746900000 | O87: 599500000 | P87: 426400000 | Q87: -11200000 | R87: 118800000 | S87: 118700000 | W87: =Raw_Data!C86&"|"&Raw_Data!D86&"|"&TEXT(Raw_Data!B86,"yyyy-mm-dd") -> Allegion|ALLE|2021-09-30
A88: 86 | B88: 44286 | C88: Allegion | D88: ALLE | F88: 122500000 | G88: 108000000 | H88: 164200000 | I88: 297400000 | J88: 133200000 | K88: 133200000 | L88: -12300000 | M88: 14300000 | N88: 694300000 | O88: 561100000 | P88: 396900000 | Q88: -10700000 | R88: 108200000 | S88: 108000000 | W88: =Raw_Data!C87&"|"&Raw_Data!D87&"|"&TEXT(Raw_Data!B87,"yyyy-mm-dd") -> Allegion|ALLE|2021-06-30
A89: 87 | B89: 44196 | C89: Allegion | D89: ALLE | F89: 105800000 | G89: 93300000 | H89: 156600000 | I89: 320700000 | J89: 164100000 | K89: 164100000 | L89: -12300000 | M89: 12400000 | N89: 727300000 | O89: 563200000 | P89: 406600000 | Q89: -58300000 | R89: 93400000 | S89: 93300000 | W89: =Raw_Data!C88&"|"&Raw_Data!D88&"|"&TEXT(Raw_Data!B88,"yyyy-mm-dd") -> Allegion|ALLE|2021-03-31
A90: 88 | B90: 44469 | C90: Alliant Energy | D90: LNT | F90: 235000000 | G90: 256000000 | I90: 480000000 | J90: 289000000 | K90: 289000000 | L90: -71000000 | M90: -21000000 | N90: 1024000000 | O90: 735000000 | P90: 544000000 | Q90: -54000000 | R90: 256000000 | S90: 256000000 | W90: =Raw_Data!C89&"|"&Raw_Data!D89&"|"&TEXT(Raw_Data!B89,"yyyy-mm-dd") -> Allegion|ALLE|2020-12-31
A91: 89 | B91: 44377 | C91: Alliant Energy | D91: LNT | F91: 127000000 | G91: 144000000 | I91: 367000000 | J91: 176000000 | K91: 176000000 | L91: -71000000 | M91: -17000000 | N91: 817000000 | O91: 641000000 | P91: 450000000 | Q91: -49000000 | R91: 144000000 | S91: 144000000 | W91: =Raw_Data!C90&"|"&Raw_Data!D90&"|"&TEXT(Raw_Data!B90,"yyyy-mm-dd") -> Alliant Energy|LNT|2021-09-30
A92: 90 | B92: 44286 | C92: Alliant Energy | D92: LNT | F92: 143000000 | G92: 171000000 | I92: 388000000 | J92: 198000000 | K92: 198000000 | L92: -72000000 | M92: -28000000 | N92: 901000000 | O92: 703000000 | P92: 513000000 | Q92: -55000000 | R92: 171000000 | S92: 171000000 | W92: =Raw_Data!C91&"|"&Raw_Data!D91&"|"&TEXT(Raw_Data!B91,"yyyy-mm-dd") -> Alliant Energy|LNT|2021-06-30
A93: 91 | B93: 44196 | C93: Alliant Energy | D93: LNT | F93: 54000000 | G93: 64000000 | H93: 24000000 | I93: 299000000 | J93: 88000000 | K93: 88000000 | L93: -70000000 | M93: -10000000 | N93: 817000000 | O93: 729000000 | P93: 518000000 | Q93: -34000000 | R93: 64000000 | S93: 64000000 | W93: =Raw_Data!C92&"|"&Raw_Data!D92&"|"&TEXT(Raw_Data!B92,"yyyy-mm-dd") -> Alliant Energy|LNT|2021-03-31
A94: 92 | B94: 44469 | C94: Allstate Corp | D94: ALL | F94: 226000000 | G94: 538000000 | H94: 1930000000 | I94: 2357000000 | J94: 318000000 | K94: 318000000 | L94: -69000000 | M94: 20000000 | N94: 12480000000 | O94: 12162000000 | P94: 10123000000 | Q94: -92000000 | R94: 206000000 | S94: 508000000 | W94: =Raw_Data!C93&"|"&Raw_Data!D93&"|"&TEXT(Raw_Data!B93,"yyyy-mm-dd") -> Alliant Energy|LNT|2020-12-31
A95: 93 | B95: 44377 | C95: Allstate Corp | D95: ALL | F95: 1797000000 | G95: 1625000000 | H95: 1549000000 | I95: 3642000000 | J95: 1988000000 | K95: 1988000000 | L95: -91000000 | M95: 362000000 | N95: 12646000000 | O95: 10658000000 | P95: 9004000000 | Q95: -191000000 | R95: 1435000000 | S95: 1595000000 | W95: =Raw_Data!C94&"|"&Raw_Data!D94&"|"&TEXT(Raw_Data!B94,"yyyy-mm-dd") -> Allstate Corp|ALL|2021-09-30
A96: 94 | B96: 44286 | C96: Allstate Corp | D96: ALL | F96: 3032000000 | G96: -1381000000 | H96: 1399000000 | I96: 4643000000 | J96: 3191000000 | K96: 3191000000 | L96: -86000000 | M96: 626000000 | N96: 12451000000 | O96: 9260000000 | P96: 7808000000 | Q96: -159000000 | R96: 2406000000 | S96: -1408000000 | W96: =Raw_Data!C95&"|"&Raw_Data!D95&"|"&TEXT(Raw_Data!B95,"yyyy-mm-dd") -> Allstate Corp|ALL|2021-06-30
A97: 95 | B97: 44196 | C97: Allstate Corp | D97: ALL | F97: 3310000000 | G97: 2624000000 | H97: 1131000000 | I97: 4590000000 | J97: 3429000000 | K97: 3429000000 | L97: -80000000 | M97: 686000000 | N97: 12018000000 | O97: 8589000000 | P97: 7428000000 | Q97: -119000000 | R97: 2624000000 | S97: 2598000000 | W97: =Raw_Data!C96&"|"&Raw_Data!D96&"|"&TEXT(Raw_Data!B96,"yyyy-mm-dd") -> Allstate Corp|ALL|2021-03-31
A98: 96 | B98: 44377 | C98: Alphabet (Class A) | D98: GOOGL | E98: 7675000000 | F98: 21985000000 | G98: 18525000000 | H98: 8617000000 | I98: 35653000000 | J98: 19361000000 | K98: 19361000000 | L98: -76000000 | M98: 3460000000 | N98: 61880000000 | O98: 42519000000 | P98: 26227000000 | Q98: 2624000000 | R98: 18525000000 | S98: 18525000000 | W98: =Raw_Data!C97&"|"&Raw_Data!D97&"|"&TEXT(Raw_Data!B97,"yyyy-mm-dd") -> Allstate Corp|ALL|2020-12-31
A99: 97 | B99: 44286 | C99: Alphabet (Class A) | D99: GOOGL | E99: 7485000000 | F99: 21283000000 | G99: 17930000000 | H99: 7289000000 | I99: 31211000000 | J99: 16437000000 | K99: 16437000000 | L99: -76000000 | M99: 3353000000 | N99: 55314000000 | O99: 38877000000 | P99: 24103000000 | Q99: 4846000000 | R99: 17930000000 | S99: 17930000000 | W99: =Raw_Data!C98&"|"&Raw_Data!D98&"|"&TEXT(Raw_Data!B98,"yyyy-mm-dd") -> Alphabet (Class A)|GOOGL|2021-06-30
A100: 98 | B100: 44196 | C100: Alphabet (Class A) | D100: GOOGL | E100: 7022000000 | F100: 18689000000 | G100: 15227000000 | H100: 8145000000 | I100: 30818000000 | J100: 15651000000 | K100: 15651000000 | L100: -53000000 | M100: 3462000000 | N100: 56898000000 | O100: 41247000000 | P100: 26080000000 | Q100: 3038000000 | R100: 15227000000 | S100: 15227000000 | W100: =Raw_Data!C99&"|"&Raw_Data!D99&"|"&TEXT(Raw_Data!B99,"yyyy-mm-dd") -> Alphabet (Class A)|GOOGL|2021-03-31
A101: 99 | B101: 44104 | C101: Alphabet (Class A) | D101: GOOGL | E101: 6856000000 | F101: 13359000000 | G101: 11247000000 | H101: 6987000000 | I101: 25056000000 | J101: 11213000000 | K101: 11213000000 | L101: -48000000 | M101: 2112000000 | N101: 46173000000 | O101: 34960000000 | P101: 21117000000 | Q101: 2146000000 | R101: 11247000000 | S101: 11247000000 | W101: =Raw_Data!C100&"|"&Raw_Data!D100&"|"&TEXT(Raw_Data!B100,"yyyy-mm-dd") -> Alphabet (Class A)|GOOGL|2020-12-31
A102: 100 | B102: 44377 | C102: Alphabet (Class C) | D102: GOOG | E102: 7675000000 | F102: 21985000000 | G102: 18525000000 | H102: 8617000000 | I102: 35653000000 | J102: 19361000000 | K102: 19361000000 | L102: -76000000 | M102: 3460000000 | N102: 61880000000 | O102: 42519000000 | P102: 26227000000 | Q102: 2624000000 | R102: 18525000000 | S102: 18525000000 | W102: =Raw_Data!C101&"|"&Raw_Data!D101&"|"&TEXT(Raw_Data!B101,"yyyy-mm-dd") -> Alphabet (Class A)|GOOGL|2020-09-30
A103: 101 | B103: 44286 | C103: Alphabet (Class C) | D103: GOOG | E103: 7485000000 | F103: 21283000000 | G103: 17930000000 | H103: 7289000000 | I103: 31211000000 | J103: 16437000000 | K103: 16437000000 | L103: -76000000 | M103: 3353000000 | N103: 55314000000 | O103: 38877000000 | P103: 24103000000 | Q103: 4846000000 | R103: 17930000000 | S103: 17930000000 | W103: =Raw_Data!C102&"|"&Raw_Data!D102&"|"&TEXT(Raw_Data!B102,"yyyy-mm-dd") -> Alphabet (Class C)|GOOG|2021-06-30
...

Sheet Cleaned_Data
A1: S. NO. | B1: date | C1: firm | D1: Ticker | E1: Research Development | F1: Income Before Tax | G1: Net Income | H1: Selling General Administrative | I1: Gross Profit | J1: Ebit | K1: Operating Income | L1: Interest Expense | M1: Income Tax Expense | N1: Total Revenue | O1: Total Operating Expenses | P1: Cost Of Revenue | Q1: Total Other Income Expense Net | R1: Net Income From Continuing Ops | S1: Net Income Applicable To Common Shares
A2: 0 | B2: 44469 | C2: 3M | D2: MMM | E2: 482000000 | F2: 1761000000 | G2: 1434000000 | H2: 1739000000 | I2: 4089000000 | J2: 1868000000 | K2: 1868000000 | L2: -117000000 | M2: 324000000 | N2: 8942000000 | O2: 7074000000 | P2: 4853000000 | Q2: -107000000 | R2: 1437000000 | S2: 1434000000
A3: 1 | B3: 44377 | C3: 3M | D3: MMM | E3: 514000000 | F3: 1940000000 | G3: 1524000000 | H3: 1666000000 | I3: 4231000000 | J3: 2051000000 | K3: 2051000000 | L3: -121000000 | M3: 415000000 | N3: 8950000000 | O3: 6899000000 | P3: 4719000000 | Q3: -111000000 | R3: 1525000000 | S3: 1524000000
A4: 2 | B4: 44286 | C4: 3M | D4: MMM | E4: 520000000 | F4: 1946000000 | G4: 1624000000 | H4: 1720000000 | I4: 4327000000 | J4: 2087000000 | K4: 2087000000 | L4: -132000000 | M4: 319000000 | N4: 8851000000 | O4: 6764000000 | P4: 4524000000 | Q4: -141000000 | R4: 1627000000 | S4: 1624000000
A5: 3 | B5: 44196 | C5: 3M | D5: MMM | E5: 449000000 | F5: 1706000000 | G5: 1389000000 | H5: 1814000000 | I5: 4246000000 | J5: 1983000000 | K5: 1983000000 | L5: -141000000 | M5: 316000000 | N5: 8583000000 | O5: 6600000000 | P5: 4337000000 | Q5: -277000000 | R5: 1390000000 | S5: 1389000000
A6: 4 | B6: 44469 | C6: 3M | D6: MMM | E6: 482000000 | F6: 1761000000 | G6: 1434000000 | H6: 1739000000 | I6: 4089000000 | J6: 1868000000 | K6: 1868000000 | L6: -117000000 | M6: 324000000 | N6: 8942000000 | O6: 7074000000 | P6: 4853000000 | Q6: -107000000 | R6: 1437000000 | S6: 1434000000
A7: 5 | B7: 44377 | C7: 3M | D7: MMM | E7: 514000000 | F7: 1940000000 | G7: 1524000000 | H7: 1666000000 | I7: 4231000000 | J7: 2051000000 | K7: 2051000000 | L7: -121000000 | M7: 415000000 | N7: 8950000000 | O7: 6899000000 | P7: 4719000000 | Q7: -111000000 | R7: 1525000000 | S7: 1524000000
A8: 6 | B8: 44286 | C8: 3M | D8: MMM | E8: 520000000 | F8: 1946000000 | G8: 1624000000 | H8: 1720000000 | I8: 4327000000 | J8: 2087000000 | K8: 2087000000 | L8: -132000000 | M8: 319000000 | N8: 8851000000 | O8: 6764000000 | P8: 4524000000 | Q8: -141000000 | R8: 1627000000 | S8: 1624000000
A9: 7 | B9: 44196 | C9: 3M | D9: MMM | E9: 449000000 | F9: 1706000000 | G9: 1389000000 | H9: 1814000000 | I9: 4246000000 | J9: 1983000000 | K9: 1983000000 | L9: -141000000 | M9: 316000000 | N9: 8583000000 | O9: 6600000000 | P9: 4337000000 | Q9: -277000000 | R9: 1390000000 | S9: 1389000000
A10: 8 | B10: 44469 | C10: A. O. Smith | D10: AOS | F10: 166400000 | G10: 131600000 | H10: 174300000 | I10: 340300000 | J10: 166000000 | K10: 166000000 | L10: -1000000 | M10: 34800000 | N10: 914600000 | O10: 748600000 | P10: 574300000 | Q10: 400000 | R10: 131600000 | S10: 131600000
A11: 9 | B11: 44377 | C11: A. O. Smith | D11: AOS | F11: 151300000 | G11: 118200000 | H11: 169800000 | I11: 321400000 | J11: 151600000 | K11: 151600000 | L11: -900000 | M11: 33100000 | N11: 859800000 | O11: 708200000 | P11: 538400000 | Q11: -300000 | R11: 118200000 | S11: 118200000
A12: 10 | B12: 44286 | C12: A. O. Smith | D12: AOS | F12: 126100000 | G12: 97700000 | H12: 166500000 | I12: 288600000 | J12: 122100000 | K12: 122100000 | L12: -1000000 | M12: 28400000 | N12: 769000000 | O12: 646900000 | P12: 480400000 | Q12: 4000000 | R12: 97700000 | S12: 97700000
A13: 11 | B13: 44196 | C13: A. O. Smith | D13: AOS | F13: 151900000 | G13: 120000000 | H13: 184700000 | I13: 324100000 | J13: 139400000 | K13: 139400000 | L13: -1000000 | M13: 31900000 | N13: 834500000 | O13: 695100000 | P13: 510400000 | Q13: 12500000 | R13: 120000000 | S13: 120000000
A14: 12 | B14: 44469 | C14: Abbott Laboratories | D14: ABT | E14: 672000000 | F14: 2493000000 | G14: 2100000000 | H14: 2699000000 | I14: 6505000000 | J14: 2614000000 | K14: 2614000000 | L14: -133000000 | M14: 393000000 | N14: 10928000000 | O14: 8314000000 | P14: 4423000000 | Q14: -121000000 | R14: 2100000000 | S14: 2092000000
A15: 13 | B15: 44377 | C15: Abbott Laboratories | D15: ABT | E15: 654000000 | F15: 1348000000 | G15: 1189000000 | H15: 2658000000 | I15: 5786000000 | J15: 1970000000 | K15: 1970000000 | L15: -134000000 | M15: 159000000 | N15: 10223000000 | O15: 8253000000 | P15: 4437000000 | Q15: -622000000 | R15: 1189000000 | S15: 1184000000
A16: 14 | B16: 44286 | C16: Abbott Laboratories | D16: ABT | E16: 654000000 | F16: 2043000000 | G16: 1793000000 | H16: 2716000000 | I16: 6056000000 | J16: 2177000000 | K16: 2177000000 | L16: -135000000 | M16: 250000000 | N16: 10456000000 | O16: 8279000000 | P16: 4400000000 | Q16: -134000000 | R16: 1793000000 | S16: 1785000000
A17: 15 | B17: 44196 | C17: Abbott Laboratories | D17: ABT | E17: 643000000 | F17: 2388000000 | G17: 2162000000 | H17: 2525000000 | I17: 6207000000 | J17: 2531000000 | K17: 2531000000 | L17: -136000000 | M17: 230000000 | N17: 10701000000 | O17: 8170000000 | P17: 4494000000 | Q17: -143000000 | R17: 2158000000 | S17: 2151000000
A18: 16 | B18: 44469 | C18: AbbVie | D18: ABBV | E18: 1655000000 | F18: 3688000000 | G18: 3179000000 | H18: 2946000000 | I18: 9998000000 | J18: 4897000000 | K18: 4897000000 | L18: -596000000 | M18: 508000000 | N18: 14342000000 | O18: 9445000000 | P18: 4344000000 | Q18: -1209000000 | R18: 3180000000 | S18: 3158000000
A19: 17 | B19: 44377 | C19: AbbVie | D19: ABBV | E19: 1784000000 | F19: 1163000000 | G19: 766000000 | H19: 3049000000 | I19: 9461000000 | J19: 4696000000 | K19: 4696000000 | L19: -615000000 | M19: 394000000 | N19: 13959000000 | O19: 9263000000 | P19: 4498000000 | Q19: -3533000000 | R19: 769000000 | S19: 751000000
A20: 18 | B20: 44286 | C20: AbbVie | D20: ABBV | E20: 1731000000 | F20: 3867000000 | G20: 3553000000 | H20: 2741000000 | I20: 8818000000 | J20: 4346000000 | K20: 4346000000 | L20: -632000000 | M20: 312000000 | N20: 13010000000 | O20: 8664000000 | P20: 4192000000 | Q20: -479000000 | R20: 3555000000 | S20: 3536000000
A21: 19 | B21: 44196 | C21: AbbVie | D21: ABBV | E21: 1821000000 | F21: -1507000000 | G21: 36000000 | H21: 3099000000 | I21: 10448000000 | J21: 5528000000 | K21: 5528000000 | L21: -629000000 | M21: -1545000000 | N21: 13858000000 | O21: 8330000000 | P21: 3410000000 | Q21: -7035000000 | R21: 38000000 | S21: 20000000
A22: 20 | B22: 44469 | C22: Abiomed | D22: ABMD | E22: 41041000 | F22: 67271000 | G22: 56953000 | H22: 102779000 | I22: 204256000 | J22: 60436000 | K22: 60436000 | M22: 10318000 | N22: 248142000 | O22: 187706000 | P22: 43886000 | Q22: 6835000 | R22: 56953000 | S22: 56953000
A23: 21 | B23: 44377 | C23: Abiomed | D23: ABMD | E23: 36837000 | F23: -9350000 | G23: -26525000 | H23: 103484000 | I23: 207397000 | J23: 67076000 | K23: 67076000 | M23: 17175000 | N23: 252585000 | O23: 185509000 | P23: 45188000 | Q23: -76426000 | R23: -26525000 | S23: -26525000
A24: 22 | B24: 44286 | C24: Abiomed | D24: ABMD | E24: 32599000 | F24: 73494000 | G24: 56856000 | H24: 100374000 | I24: 195167000 | J24: 62194000 | K24: 62194000 | M24: 16638000 | N24: 241245000 | O24: 179051000 | P24: 46078000 | Q24: 11300000 | R24: 56856000 | S24: 56856000
A25: 23 | B25: 44196 | C25: Abiomed | D25: ABMD | E25: 32105000 | F25: 80735000 | G25: 61868000 | H25: 86198000 | I25: 190553000 | J25: 72250000 | K25: 72250000 | M25: 18867000 | N25: 231663000 | O25: 159413000 | P25: 41110000 | Q25: 8485000 | R25: 61868000 | S25: 61868000
A26: 24 | B26: 44439 | C26: Accenture | D26: ACN | F26: 1917805000 | G26: 1416248000 | H26: 2507527000 | I26: 4466216000 | J26: 1958689000 | K26: 1958689000 | L26: -12977000 | M26: 480382000 | N26: 13419284000 | O26: 11460595000 | P26: 8953068000 | Q26: -40884000 | R26: 1437423000 | S26: 1416248000
A27: 25 | B27: 44347 | C27: Accenture | D27: ACN | F27: 2094001000 | G27: 1549426000 | H27: 2285728000 | I27: 4404384000 | J27: 2118656000 | K27: 2118656000 | L27: -28739000 | M27: 524429000 | N27: 13263795000 | O27: 11145139000 | P27: 8859411000 | Q27: -24655000 | R27: 1569572000 | S27: 1549426000
A28: 26 | B28: 44255 | C28: Accenture | D28: ACN | F28: 1762443000 | G28: 1440859000 | H28: 1941717000 | I28: 3595232000 | J28: 1653515000 | K28: 1653515000 | L28: -8922000 | M28: 300950000 | N28: 12088125000 | O28: 10434610000 | P28: 8492893000 | Q28: 108928000 | R28: 1461493000 | S28: 1440859000
A29: 27 | B29: 44165 | C29: Accenture | D29: ACN | F29: 1986867000 | G29: 1500276000 | H29: 2007627000 | I29: 3898296000 | J29: 1890669000 | K29: 1890669000 | L29: -8854000 | M29: 464810000 | N29: 11762185000 | O29: 9871516000 | P29: 7863889000 | Q29: 96198000 | R29: 1522057000 | S29: 1500276000
A30: 28 | B30: 44469 | C30: Activision Blizzard | D30: ATVI | E30: 329000000 | F30: 759000000 | G30: 639000000 | H30: 387000000 | I30: 1543000000 | J30: 827000000 | K30: 827000000 | L30: -27000000 | M30: 120000000 | N30: 2070000000 | O30: 1243000000 | P30: 527000000 | Q30: -68000000 | R30: 639000000 | S30: 639000000
A31: 29 | B31: 44377 | C31: Activision Blizzard | D31: ATVI | E31: 335000000 | F31: 1002000000 | G31: 876000000 | H31: 434000000 | I31: 1741000000 | J31: 972000000 | K31: 972000000 | L31: -27000000 | M31: 126000000 | N31: 2296000000 | O31: 1324000000 | P31: 555000000 | Q31: 30000000 | R31: 876000000 | S31: 876000000
A32: 30 | B32: 44286 | C32: Activision Blizzard | D32: ATVI | E32: 353000000 | F32: 765000000 | G32: 619000000 | H32: 519000000 | I32: 1697000000 | J32: 825000000 | K32: 825000000 | L32: -28000000 | M32: 146000000 | N32: 2275000000 | O32: 1450000000 | P32: 578000000 | Q32: -60000000 | R32: 619000000 | S32: 619000000
A33: 31 | B33: 44196 | C33: Activision Blizzard | D33: ATVI | E33: 348000000 | F33: 563000000 | G33: 509000000 | H33: 597000000 | I33: 1595000000 | J33: 650000000 | K33: 650000000 | L33: -27000000 | M33: 54000000 | N33: 2412000000 | O33: 1762000000 | P33: 817000000 | Q33: -87000000 | R33: 509000000 | S33: 509000000
A34: 32 | B34: 44469 | C34: ADM | D34: ADM | F34: 653000000 | G34: 526000000 | H34: 716000000 | I34: 1326000000 | J34: 607000000 | K34: 607000000 | L34: -61000000 | M34: 120000000 | N34: 20340000000 | O34: 19733000000 | P34: 19014000000 | Q34: 46000000 | R34: 533000000 | S34: 526000000
A35: 33 | B35: 44377 | C35: ADM | D35: ADM | F35: 825000000 | G35: 712000000 | H35: 815000000 | I35: 1463000000 | J35: 642000000 | K35: 642000000 | L35: -40000000 | M35: 113000000 | N35: 22926000000 | O35: 22284000000 | P35: 21463000000 | Q35: 183000000 | R35: 712000000 | S35: 712000000
A36: 34 | B36: 44286 | C36: ADM | D36: ADM | F36: 824000000 | G36: 689000000 | H36: 697000000 | I36: 1548000000 | J36: 843000000 | K36: 843000000 | L36: -87000000 | M36: 131000000 | N36: 18893000000 | O36: 18050000000 | P36: 17345000000 | Q36: -19000000 | R36: 693000000 | S36: 689000000
A37: 35 | B37: 44196 | C37: ADM | D37: ADM | F37: 756000000 | G37: 687000000 | H37: 720000000 | I37: 1352000000 | J37: 615000000 | K37: 615000000 | L37: -69000000 | M37: 63000000 | N37: 17978000000 | O37: 17363000000 | P37: 16626000000 | Q37: 141000000 | R37: 693000000 | S37: 687000000
A38: 36 | B38: 44442 | C38: Adobe | D38: ADBE | E38: 651000000 | F38: 1418000000 | G38: 1212000000 | H38: 1333000000 | I38: 3468000000 | J38: 1441000000 | K38: 1441000000 | L38: -27000000 | M38: 206000000 | N38: 3935000000 | O38: 2494000000 | P38: 467000000 | Q38: -23000000 | R38: 1212000000 | S38: 1212000000
A39: 37 | B39: 44351 | C39: Adobe | D39: ADBE | E39: 612000000 | F39: 1386000000 | G39: 1116000000 | H39: 1329000000 | I39: 3391000000 | J39: 1406000000 | K39: 1406000000 | L39: -28000000 | M39: 270000000 | N39: 3835000000 | O39: 2429000000 | P39: 444000000 | Q39: -20000000 | R39: 1116000000 | S39: 1116000000
A40: 38 | B40: 44260 | C40: Adobe | D40: ADBE | E40: 620000000 | F40: 1433000000 | G40: 1261000000 | H40: 1339000000 | I40: 3458000000 | J40: 1454000000 | K40: 1454000000 | L40: -30000000 | M40: 172000000 | N40: 3905000000 | O40: 2451000000 | P40: 447000000 | Q40: -21000000 | R40: 1261000000 | S40: 1261000000
A41: 39 | B41: 44162 | C41: Adobe | D41: ADBE | E41: 558000000 | F41: 1197000000 | G41: 2250000000 | H41: 1184000000 | I41: 2996000000 | J41: 1215000000 | K41: 1215000000 | L41: -27000000 | M41: -1053000000 | N41: 3424000000 | O41: 2209000000 | P41: 428000000 | Q41: -18000000 | R41: 2250000000 | S41: 2250000000
A42: 40 | B42: 44394 | C42: Advance Auto Parts | D42: AAP | F42: 237765000 | G42: 178696000 | H42: 932793000 | I42: 1189416000 | J42: 256623000 | K42: 256623000 | L42: -8306000 | M42: 59069000 | N42: 2649415000 | O42: 2392792000 | P42: 1459999000 | Q42: -18858000 | R42: 178696000 | S42: 178696000
A43: 41 | B43: 44394 | C43: Advance Auto Parts | D43: AAP | F43: 237765000 | G43: 178696000 | H43: 932793000 | I43: 1189416000 | J43: 256623000 | K43: 256623000 | L43: -8306000 | M43: 0 | N43: 2649415000 | O43: 0 | P43: 0 | Q43: 0 | R43: 178696000 | S43: 178696000
A44: 42 | B44: 44310 | C44: Advance Auto Parts | D44: AAP | F44: 245774000 | G44: 185930000 | H44: 1200138000 | I44: 1487229000 | J44: 287091000 | K44: 287091000 | L44: -11191000 | M44: 59844000 | N44: 3330370000 | O44: 3043279000 | P44: 1843141000 | Q44: -41317000 | R44: 185930000 | S44: 185930000
A45: 43 | B45: 44303 | C45: Advance Auto Parts | D45: AAP | F45: 245774000 | G45: 182313000 | H45: 1200138000 | I45: 1338322500 | J45: 271856500 | K45: 287091000 | L45: -9748500 | M45: 0 | N45: 2989892500 | O45: 0 | P45: 0 | Q45: 0 | R45: 185930000 | S45: 185930000
A46: 44 | B46: 44464 | C46: Advanced Micro Devices | D46: AMD | E46: 765000000 | F46: 1005000000 | G46: 923000000 | H46: 368000000 | I46: 2086000000 | J46: 956000000 | K46: 956000000 | L46: -7000000 | M46: 82000000 | N46: 4313000000 | O46: 3357000000 | P46: 2227000000 | Q46: 49000000 | R46: 923000000 | S46: 923000000
A47: 45 | B47: 44373 | C47: Advanced Micro Devices | D47: AMD | E47: 659000000 | F47: 823000000 | G47: 710000000 | H47: 331000000 | I47: 1830000000 | J47: 841000000 | K47: 841000000 | L47: -10000000 | M47: 113000000 | N47: 3850000000 | O47: 3009000000 | P47: 2020000000 | Q47: -18000000 | R47: 710000000 | S47: 710000000
A48: 46 | B48: 44282 | C48: Advanced Micro Devices | D48: AMD | E48: 610000000 | F48: 644000000 | G48: 555000000 | H48: 304000000 | I48: 1587000000 | J48: 677000000 | K48: 677000000 | L48: -9000000 | M48: 89000000 | N48: 3445000000 | O48: 2768000000 | P48: 1858000000 | Q48: -33000000 | R48: 555000000 | S48: 555000000
A49: 47 | B49: 44191 | C49: Advanced Micro Devices | D49: AMD | E49: 573000000 | F49: 549000000 | G49: 1781000000 | H49: 308000000 | I49: 1451000000 | J49: 570000000 | K49: 570000000 | L49: -9000000 | M49: -1232000000 | N49: 3244000000 | O49: 2674000000 | P49: 1793000000 | Q49: -21000000 | R49: 1781000000 | S49: 1781000000
A50: 48 | B50: 44469 | C50: AES Corp | D50: AES | F50: 611000000 | G50: 343000000 | H50: 39000000 | I50: 760000000 | J50: 721000000 | K50: 721000000 | L50: -242000000 | M50: 126000000 | N50: 3036000000 | O50: 2315000000 | P50: 2276000000 | Q50: -110000000 | R50: 485000000 | S50: 343000000
A51: 49 | B51: 44377 | C51: AES Corp | D51: AES | F51: -140000000 | G51: 28000000 | H51: 45000000 | I51: 728000000 | J51: 683000000 | K51: 683000000 | L51: -237000000 | M51: -59000000 | N51: 2700000000 | O51: 2017000000 | P51: 1972000000 | Q51: -823000000 | R51: -81000000 | S51: 28000000
A52: 50 | B52: 44286 | C52: AES Corp | D52: AES | F52: -21000000 | G52: -148000000 | H52: 46000000 | I52: 664000000 | J52: 618000000 | K52: 618000000 | L52: -190000000 | M52: 8000000 | N52: 2635000000 | O52: 2017000000 | P52: 1971000000 | Q52: -639000000 | R52: -29000000 | S52: -148000000
A53: 51 | B53: 44196 | C53: AES Corp | D53: AES | F53: 562000000 | G53: 318000000 | H53: 47000000 | I53: 724000000 | J53: 677000000 | K53: 677000000 | L53: -297000000 | M53: 161000000 | N53: 2560000000 | O53: 1883000000 | P53: 1836000000 | Q53: -115000000 | R53: 401000000 | S53: 318000000
A54: 52 | B54: 44469 | C54: Aflac | D54: AFL | F54: 1113000000 | G54: 888000000 | H54: 869000000 | I54: 2039000000 | J54: 1170000000 | K54: 1170000000 | L54: -57000000 | M54: 225000000 | N54: 5237000000 | O54: 4067000000 | P54: 3198000000 | Q54: -57000000 | R54: 888000000 | S54: 888000000
A55: 53 | B55: 44377 | C55: Aflac | D55: AFL | F55: 1373000000 | G55: 1105000000 | H55: 881000000 | I55: 2316000000 | J55: 1435000000 | K55: 1435000000 | L55: -62000000 | M55: 268000000 | N55: 5564000000 | O55: 4129000000 | P55: 3248000000 | Q55: -62000000 | R55: 1105000000 | S55: 1105000000
A56: 54 | B56: 44286 | C56: Aflac | D56: AFL | F56: 1603000000 | G56: 1293000000 | H56: 832000000 | I56: 2497000000 | J56: 1665000000 | K56: 1665000000 | L56: -62000000 | M56: 310000000 | N56: 5869000000 | O56: 4204000000 | P56: 3372000000 | Q56: -62000000 | R56: 1293000000 | S56: 1293000000
A57: 55 | B57: 44196 | C57: Aflac | D57: AFL | F57: 1217000000 | G57: 952000000 | H57: 1038000000 | I57: 2316000000 | J57: 1278000000 | K57: 1278000000 | L57: -61000000 | M57: 265000000 | N57: 5913000000 | O57: 4635000000 | P57: 3597000000 | Q57: -61000000 | R57: 952000000 | S57: 952000000
A58: 56 | B58: 44408 | C58: Agilent Technologies | D58: A | E58: 113000000 | F58: 327000000 | G58: 264000000 | H58: 390000000 | I58: 852000000 | J58: 349000000 | K58: 349000000 | L58: -21000000 | M58: 63000000 | N58: 1586000000 | O58: 1237000000 | P58: 734000000 | Q58: -22000000 | R58: 264000000 | S58: 264000000
A59: 57 | B59: 44316 | C59: Agilent Technologies | D59: A | E59: 109000000 | F59: 273000000 | G59: 216000000 | H59: 420000000 | I59: 817000000 | J59: 288000000 | K59: 288000000 | L59: -20000000 | M59: 57000000 | N59: 1525000000 | O59: 1237000000 | P59: 708000000 | Q59: -15000000 | R59: 216000000 | S59: 216000000
A60: 58 | B60: 44227 | C60: Agilent Technologies | D60: A | E60: 103000000 | F60: 312000000 | G60: 288000000 | H60: 398000000 | I60: 838000000 | J60: 337000000 | K60: 337000000 | L60: -19000000 | M60: 24000000 | N60: 1548000000 | O60: 1211000000 | P60: 710000000 | Q60: -25000000 | R60: 288000000 | S60: 288000000
A61: 59 | B61: 44135 | C61: Agilent Technologies | D61: A | E61: 102000000 | F61: 283000000 | G61: 222000000 | H61: 342000000 | I61: 788000000 | J61: 344000000 | K61: 344000000 | L61: -19000000 | M61: 61000000 | N61: 1483000000 | O61: 1139000000 | P61: 695000000 | Q61: -61000000 | R61: 222000000 | S61: 222000000
A62: 60 | B62: 44469 | C62: Air Products & Chemicals | D62: APD | E62: 25700000 | F62: 692300000 | G62: 610400000 | H62: 202100000 | I62: 834800000 | J62: 616700000 | K62: 616700000 | L62: -33400000 | M62: 125300000 | N62: 2841100000 | O62: 2224400000 | P62: 2006300000 | Q62: 75600000 | R62: 567000000 | S62: 610400000
A63: 61 | B63: 44377 | C63: Air Products & Chemicals | D63: APD | E63: 23200000 | F63: 625800000 | G63: 533600000 | H63: 192600000 | I63: 802800000 | J63: 598400000 | K63: 598400000 | L63: -35600000 | M63: 101700000 | N63: 2604700000 | O63: 2006300000 | P63: 1801900000 | Q63: 27400000 | R63: 524100000 | S63: 533600000
A64: 62 | B64: 44286 | C64: Air Products & Chemicals | D64: APD | E64: 21100000 | F64: 599000000 | G64: 473100000 | H64: 189100000 | I64: 756500000 | J64: 555800000 | K64: 555800000 | L64: -36100000 | M64: 121900000 | N64: 2502000000 | O64: 1946200000 | P64: 1745500000 | Q64: 43200000 | R64: 477100000 | S64: 473100000
A65: 63 | B65: 44196 | C65: Air Products & Chemicals | D65: APD | E65: 23500000 | F65: 590300000 | G65: 482000000 | H65: 182100000 | I65: 742800000 | J65: 562500000 | K65: 562500000 | L65: -36700000 | M65: 113900000 | N65: 2375200000 | O65: 1812700000 | P65: 1632400000 | Q65: 27800000 | R65: 476400000 | S65: 482000000
A66: 64 | B66: 44469 | C66: Akamai Technologies | D66: AKAM | E66: 82899000 | F66: 192564000 | G66: 178916000 | H66: 241463000 | I66: 543467000 | J66: 207146000 | K66: 207146000 | L66: -18144000 | M66: 13648000 | N66: 860333000 | O66: 653187000 | P66: 316866000 | Q66: -14582000 | R66: 178916000 | S66: 178916000
A67: 65 | B67: 44377 | C67: Akamai Technologies | D67: AKAM | E67: 77255000 | F67: 174506000 | G67: 156497000 | H67: 246049000 | I67: 532824000 | J67: 197460000 | K67: 197460000 | L67: -18037000 | M67: 18009000 | N67: 852824000 | O67: 655364000 | P67: 320000000 | Q67: -22954000 | R67: 156497000 | S67: 156497000
A68: 66 | B68: 44286 | C68: Akamai Technologies | D68: AKAM | E68: 82045000 | F68: 167593000 | G68: 155695000 | H68: 253005000 | I68: 536021000 | J68: 189544000 | K68: 189544000 | L68: -17834000 | M68: 11898000 | N68: 842708000 | O68: 653164000 | P68: 306687000 | Q68: -21951000 | R68: 155695000 | S68: 155695000
A69: 67 | B69: 44196 | C69: Akamai Technologies | D69: AKAM | E69: 67228000 | F69: 117528000 | G69: 113370000 | H69: 298739000 | I69: 542440000 | J69: 165579000 | K69: 165579000 | L69: -17342000 | M69: 4158000 | N69: 846287000 | O69: 680708000 | P69: 303847000 | Q69: -48051000 | R69: 113370000 | S69: 113370000
... A73: 71 | B73: 44196 | C73: Alaska Air Group | D73: ALB | E73: 15375000 | F73: 92076000 | G73: 84635000 | H73: 115008000 | I73: 266720000 | J73: 136337000 | K73: 136337000 | L73: -19152000 | M73: -10101000 | N73: 879147000 | O73: 742810000 | P73: 612427000 | Q73: -44261000 | R73: 102177000 | S73: 84635000
A74: 72 | B74: 44469 | C74: Albemarle Corporation | D74: ALK | F74: 245000000 | G74: 194000000 | H74: 49000000 | I74: 562000000 | J74: 257000000 | K74: 257000000 | L74: -27000000 | M74: 51000000 | N74: 1953000000 | O74: 1696000000 | P74: 1391000000 | Q74: -12000000 | R74: 194000000 | S74: 194000000
A75: 73 | B75: 44377 | C75: Albemarle Corporation | D75: ALK | F75: 528000000 | G75: 397000000 | H75: 41000000 | I75: 246000000 | J75: -36000000 | K75: -36000000 | L75: -36000000 | M75: 131000000 | N75: 1527000000 | O75: 1563000000 | P75: 1281000000 | Q75: 564000000 | R75: 397000000 | S75: 397000000
A76: 74 | B76: 44286 | C76: Albemarle Corporation | D76: ALK | F76: -173000000 | G76: -131000000 | H76: 33000000 | I76: -312000000 | J76: -573000000 | K76: -573000000 | L76: -29000000 | M76: -42000000 | N76: 797000000 | O76: 1370000000 | P76: 1109000000 | Q76: 400000000 | R76: -131000000 | S76: -131000000
A77: 75 | B77: 44196 | C77: Albemarle Corporation | D77: ALK | F77: -643000000 | G77: -447000000 | H77: 18000000 | I77: -213000000 | J77: -449000000 | K77: -449000000 | L77: -31000000 | M77: -196000000 | N77: 808000000 | O77: 1257000000 | P77: 1021000000 | Q77: -194000000 | R77: -447000000 | S77: -447000000
A78: 76 | B78: 44469 | C78: Alexandria Real Estate Equities | D78: ARE | F78: 124433000 | G78: 103147000 | H78: 37931000 | I78: 384855000 | J78: 136082000 | K78: 136082000 | L78: -35678000 | M78: 0 | N78: 550850000 | O78: 414768000 | P78: 165995000 | Q78: -11649000 | R78: 124433000 | S78: 101264000
A79: 77 | B79: 44377 | C79: Alexandria Real Estate Equities | D79: ARE | F79: 404520000 | G79: 385084000 | H79: 37880000 | I79: 368273000 | J79: 140341000 | K79: 140341000 | L79: -35158000 | M79: 0 | N79: 512228000 | O79: 371887000 | P79: 143955000 | Q79: 264179000 | R79: 404520000 | S79: 380563000
A80: 78 | B80: 44286 | C80: Alexandria Real Estate Equities | D80: ARE | F80: 25533000 | G80: 8121000 | H80: 33996000 | I80: 345498000 | J80: 130589000 | K80: 130589000 | L80: -36467000 | M80: 0 | N80: 483386000 | O80: 352797000 | P80: 137888000 | Q80: -105056000 | R80: 25533000 | S80: 7979000
A81: 79 | B81: 44196 | C81: Alexandria Real Estate Equities | D81: ARE | F81: 457133000 | G81: 441484000 | H81: 32690000 | I81: 330546000 | J81: 120106000 | K81: 120106000 | L81: -37538000 | M81: 0 | N81: 467313000 | O81: 347207000 | P81: 136767000 | Q81: 337027000 | R81: 457133000 | S81: 436620000
A82: 80 | B82: 44469 | C82: Align Technology | D82: ALGN | E82: 65587000 | F82: 261988000 | G82: 180969000 | H82: 428409000 | I82: 755156000 | J82: 261160000 | K82: 261160000 | M82: 81019000 | N82: 1015906000 | O82: 754746000 | P82: 260750000 | Q82: 828000 | R82: 180969000 | S82: 180969000
A83: 81 | B83: 44377 | C83: Align Technology | D83: ALGN | E83: 57715000 | F83: 268802000 | G83: 199714000 | H83: 431921000 | I83: 758538000 | J83: 268902000 | K83: 268902000 | M83: 69088000 | N83: 1010808000 | O83: 741906000 | P83: 252270000 | Q83: -100000 | R83: 199714000 | S83: 199714000
A84: 82 | B84: 44286 | C84: Align Technology | D84: ALGN | E84: 54537000 | F84: 261621000 | G84: 200376000 | H84: 397115000 | I84: 677098000 | J84: 225446000 | K84: 225446000 | M84: 61245000 | N84: 894771000 | O84: 669325000 | P84: 217673000 | Q84: 36175000 | R84: 200376000 | S84: 200376000
A85: 83 | B85: 44196 | C85: Align Technology | D85: ALGN | E85: 48887000 | F85: 214542000 | G85: 158988000 | H85: 348392000 | I85: 610463000 | J85: 213184000 | K85: 213184000 | M85: 55554000 | N85: 834520000 | O85: 621336000 | P85: 224057000 | Q85: 1358000 | R85: 158988000 | S85: 158988000
A86: 84 | B86: 44469 | C86: Allegion | D86: ALLE | F86: 140800000 | G86: 143500000 | H86: 160000000 | I86: 300500000 | J86: 140500000 | K86: 140500000 | L86: -12300000 | M86: -2800000 | N86: 717000000 | O86: 576500000 | P86: 416500000 | Q86: 300000 | R86: 143600000 | S86: 143500000
A87: 85 | B87: 44377 | C87: Allegion | D87: ALLE | F87: 136200000 | G87: 118700000 | H87: 173100000 | I87: 320500000 | J87: 147400000 | K87: 147400000 | L87: -12400000 | M87: 17400000 | N87: 746900000 | O87: 599500000 | P87: 426400000 | Q87: -11200000 | R87: 118800000 | S87: 118700000
A88: 86 | B88: 44286 | C88: Allegion | D88: ALLE | F88: 122500000 | G88: 108000000 | H88: 164200000 | I88: 297400000 | J88: 133200000 | K88: 133200000 | L88: -12300000 | M88: 14300000 | N88: 694300000 | O88: 561100000 | P88: 396900000 | Q88: -10700000 | R88: 108200000 | S88: 108000000
A89: 87 | B89: 44196 | C89: Allegion | D89: ALLE | F89: 105800000 | G89: 93300000 | H89: 156600000 | I89: 320700000 | J89: 164100000 | K89: 164100000 | L89: -12300000 | M89: 12400000 | N89: 727300000 | O89: 563200000 | P89: 406600000 | Q89: -58300000 | R89: 93400000 | S89: 93300000
A90: 88 | B90: 44469 | C90: Alliant Energy | D90: LNT | F90: 235000000 | G90: 256000000 | I90: 480000000 | J90: 289000000 | K90: 289000000 | L90: -71000000 | M90: -21000000 | N90: 1024000000 | O90: 735000000 | P90: 544000000 | Q90: -54000000 | R90: 256000000 | S90: 256000000
A91: 89 | B91: 44377 | C91: Alliant Energy | D91: LNT | F91: 127000000 | G91: 144000000 | I91: 367000000 | J91: 176000000 | K91: 176000000 | L91: -71000000 | M91: -17000000 | N91: 817000000 | O91: 641000000 | P91: 450000000 | Q91: -49000000 | R91: 144000000 | S91: 144000000
A92: 90 | B92: 44286 | C92: Alliant Energy | D92: LNT | F92: 143000000 | G92: 171000000 | I92: 388000000 | J92: 198000000 | K92: 198000000 | L92: -72000000 | M92: -28000000 | N92: 901000000 | O92: 703000000 | P92: 513000000 | Q92: -55000000 | R92: 171000000 | S92: 171000000
A93: 91 | B93: 44196 | C93: Alliant Energy | D93: LNT | F93: 54000000 | G93: 64000000 | H93: 24000000 | I93: 299000000 | J93: 88000000 | K93: 88000000 | L93: -70000000 | M93: -10000000 | N93: 817000000 | O93: 729000000 | P93: 518000000 | Q93: -34000000 | R93: 64000000 | S93: 64000000
A94: 92 | B94: 44469 | C94: Allstate Corp | D94: ALL | F94: 226000000 | G94: 538000000 | H94: 1930000000 | I94: 2357000000 | J94: 318000000 | K94: 318000000 | L94: -69000000 | M94: 20000000 | N94: 12480000000 | O94: 12162000000 | P94: 10123000000 | Q94: -92000000 | R94: 206000000 | S94: 508000000
A95: 93 | B95: 44377 | C95: Allstate Corp | D95: ALL | F95: 1797000000 | G95: 1625000000 | H95: 1549000000 | I95: 3642000000 | J95: 1988000000 | K95: 1988000000 | L95: -91000000 | M95: 362000000 | N95: 12646000000 | O95: 10658000000 | P95: 9004000000 | Q95: -191000000 | R95: 1435000000 | S95: 1595000000
A96: 94 | B96: 44286 | C96: Allstate Corp | D96: ALL | F96: 3032000000 | G96: -1381000000 | H96: 1399000000 | I96: 4643000000 | J96: 3191000000 | K96: 3191000000 | L96: -86000000 | M96: 626000000 | N96: 12451000000 | O96: 9260000000 | P96: 7808000000 | Q96: -159000000 | R96: 2406000000 | S96: -1408000000
A97: 95 | B97: 44196 | C97: Allstate Corp | D97: ALL | F97: 3310000000 | G97: 2624000000 | H97: 1131000000 | I97: 4590000000 | J97: 3429000000 | K97: 3429000000 | L97: -80000000 | M97: 686000000 | N97: 12018000000 | O97: 8589000000 | P97: 7428000000 | Q97: -119000000 | R97: 2624000000 | S97: 2598000000
A98: 96 | B98: 44377 | C98: Alphabet (Class A) | D98: GOOGL | E98: 7675000000 | F98: 21985000000 | G98: 18525000000 | H98: 8617000000 | I98: 35653000000 | J98: 19361000000 | K98: 19361000000 | L98: -76000000 | M98: 3460000000 | N98: 61880000000 | O98: 42519000000 | P98: 26227000000 | Q98: 2624000000 | R98: 18525000000 | S98: 18525000000
A99: 97 | B99: 44286 | C99: Alphabet (Class A) | D99: GOOGL | E99: 7485000000 | F99: 21283000000 | G99: 17930000000 | H99: 7289000000 | I99: 31211000000 | J99: 16437000000 | K99: 16437000000 | L99: -76000000 | M99: 3353000000 | N99: 55314000000 | O99: 38877000000 | P99: 24103000000 | Q99: 4846000000 | R99: 17930000000 | S99: 17930000000
A100: 98 | B100: 44196 | C100: Alphabet (Class A) | D100: GOOGL | E100: 7022000000 | F100: 18689000000 | G100: 15227000000 | H100: 8145000000 | I100: 30818000000 | J100: 15651000000 | K100: 15651000000 | L100: -53000000 | M100: 3462000000 | N100: 56898000000 | O100: 41247000000 | P100: 26080000000 | Q100: 3038000000 | R100: 15227000000 | S100: 15227000000
A101: 99 | B101: 44104 | C101: Alphabet (Class A) | D101: GOOGL | E101: 6856000000 | F101: 13359000000 | G101: 11247000000 | H101: 6987000000 | I101: 25056000000 | J101: 11213000000 | K101: 11213000000 | L101: -48000000 | M101: 2112000000 | N101: 46173000000 | O101: 34960000000 | P101: 21117000000 | Q101: 2146000000 | R101: 11247000000 | S101: 11247000000
A102: 100 | B102: 44377 | C102: Alphabet (Class C) | D102: GOOG | E102: 7675000000 | F102: 21985000000 | G102: 18525000000 | H102: 8617000000 | I102: 35653000000 | J102: 19361000000 | K102: 19361000000 | L102: -76000000 | M102: 3460000000 | N102: 61880000000 | O102: 42519000000 | P102: 26227000000 | Q102: 2624000000 | R102: 18525000000 | S102: 18525000000
A103: 101 | B103: 44286 | C103: Alphabet (Class C) | D103: GOOG | E103: 7485000000 | F103: 21283000000 | G103: 17930000000 | H103: 7289000000 | I103: 31211000000 | J103: 16437000000 | K103: 16437000000 | L103: -76000000 | M103: 3353000000 | N103: 55314000000 | O103: 38877000000 | P103: 24103000000 | Q103: 4846000000 | R103: 17930000000 | S103: 17930000000
...

Sheet Financial_Analysis
A1: Metric | B1: Value | D1: Company Analysis | G1: Top 10 Companies | H1: Total Revenue | M1: =ISNUMBER(K24) -> FALSE
A2: Total Revenue | B2: =SUM(Cleaned_Data!N2:N2013) -> 13173344212500 | D2: Company | E2: Total Revenue | G2: =IFERROR(__xludf.DUMMYFUNCTION("SORTN(D3:E504,10,0,2,FALSE)"),"Walmart") -> Walmart | H2: =IFERROR(__xludf.DUMMYFUNCTION("""COMPUTED_VALUE"""),5.66145E11) -> 566145000000 | M2: =ISNUMBER(L24) -> FALSE
A3: Total Gross Profit | B3: =SUM(Cleaned_Data!I2:I2013) -> 5165530836500 | D3: {=UNIQUE(Cleaned_Data!C2:C2013)} -> 3M | E3: =SUMIF(Cleaned_Data!C$2:C$2013,D3,Cleaned_Data!N$2:N$2013) -> 70652000000 | G3: =IFERROR(__xludf.DUMMYFUNCTION("""COMPUTED_VALUE"""),"Amazon") -> Amazon | H3: =IFERROR(__xludf.DUMMYFUNCTION("""COMPUTED_VALUE"""),4.43298E11) -> 443298000000
A4: Total Operating Income | B4: =SUM(Cleaned_Data!K2:K2013) -> 2049131813000 | D4: A. O. Smith | E4: =SUMIF(Cleaned_Data!C$2:C$2013,D4,Cleaned_Data!N$2:N$2013) -> 3377900000 | G4: =IFERROR(__xludf.DUMMYFUNCTION("""COMPUTED_VALUE"""),"Apple") -> Apple | H4: =IFERROR(__xludf.DUMMYFUNCTION("""COMPUTED_VALUE"""),3.47155E11) -> 347155000000
A5: Total Net Income | B5: =SUM(Cleaned_Data!G2:G2013) -> 1441865680000 | D5: Abbott Laboratories | E5: =SUMIF(Cleaned_Data!C$2:C$2013,D5,Cleaned_Data!N$2:N$2013) -> 42308000000 | G5: =IFERROR(__xludf.DUMMYFUNCTION("""COMPUTED_VALUE"""),"CVS Health") -> CVS Health | H5: =IFERROR(__xludf.DUMMYFUNCTION("""COMPUTED_VALUE"""),2.77285E11) -> 277285000000
A6: Average Revenue | B6: =AVERAGE(Cleaned_Data!N2:N2013) -> 6547387780 | D6: AbbVie | E6: =SUMIF(Cleaned_Data!C$2:C$2013,D6,Cleaned_Data!N$2:N$2013) -> 55169000000 | G6: =IFERROR(__xludf.DUMMYFUNCTION("""COMPUTED_VALUE"""),"UnitedHealth Group") -> UnitedHealth Group | H6: =IFERROR(__xludf.DUMMYFUNCTION("""COMPUTED_VALUE"""),2.72099E11) -> 272099000000
A7: Median Revenue | B7: =MEDIAN(Cleaned_Data!N2:N2013) -> 2624661500 | D7: Abiomed | E7: =SUMIF(Cleaned_Data!C$2:C$2013,D7,Cleaned_Data!N$2:N$2013) -> 973635000 | G7: =IFERROR(__xludf.DUMMYFUNCTION("""COMPUTED_VALUE"""),"McKesson Corporation") -> McKesson Corporation | H7: =IFERROR(__xludf.DUMMYFUNCTION("""COMPUTED_VALUE"""),2.38228E11) -> 238228000000
D8: Accenture | E8: =SUMIF(Cleaned_Data!C$2:C$2013,D8,Cleaned_Data!N$2:N$2013) -> 50533389000 | G8: =IFERROR(__xludf.DUMMYFUNCTION("""COMPUTED_VALUE"""),"Alphabet (Class A)") -> Alphabet (Class A) | H8: =IFERROR(__xludf.DUMMYFUNCTION("""COMPUTED_VALUE"""),2.20265E11) -> 220265000000
A9: Profitability Metric | B9: Value | D9: Activision Blizzard | E9: =SUMIF(Cleaned_Data!C$2:C$2013,D9,Cleaned_Data!N$2:N$2013) -> 9053000000 | G9: =IFERROR(__xludf.DUMMYFUNCTION("""COMPUTED_VALUE"""),"Alphabet (Class C)") -> Alphabet (Class C) | H9: =IFERROR(__xludf.DUMMYFUNCTION("""COMPUTED_VALUE"""),2.20265E11) -> 220265000000
A10: Gross Profit Margin | B10: =B3/B2 -> 0.39211993 | D10: ADM | E10: =SUMIF(Cleaned_Data!C$2:C$2013,D10,Cleaned_Data!N$2:N$2013) -> 80137000000 | G10: =IFERROR(__xludf.DUMMYFUNCTION("""COMPUTED_VALUE"""),"ExxonMobil") -> ExxonMobil | H10: =IFERROR(__xludf.DUMMYFUNCTION("""COMPUTED_VALUE"""),2.15879E11) -> 215879000000
A11: Operating Margin | B11: =B4/B3 -> 0.39669337 | D11: Adobe | E11: =SUMIF(Cleaned_Data!C$2:C$2013,D11,Cleaned_Data!N$2:N$2013) -> 15099000000 | G11: =IFERROR(__xludf.DUMMYFUNCTION("""COMPUTED_VALUE"""),"AmerisourceBergen") -> AmerisourceBergen | H11: =IFERROR(__xludf.DUMMYFUNCTION("""COMPUTED_VALUE"""),2.0432119E11) -> 204321190000
A12: Net Profit Margin | B12: =B5/B4 -> 0.70364711 | D12: Advance Auto Parts | E12: =SUMIF(Cleaned_Data!C$2:C$2013,D12,Cleaned_Data!N$2:N$2013) -> 11619092500
D13: Advanced Micro Devices | E13: =SUMIF(Cleaned_Data!C$2:C$2013,D13,Cleaned_Data!N$2:N$2013) -> 14852000000
D14: AES Corp | E14: =SUMIF(Cleaned_Data!C$2:C$2013,D14,Cleaned_Data!N$2:N$2013) -> 10931000000
D15: Aflac | E15: =SUMIF(Cleaned_Data!C$2:C$2013,D15,Cleaned_Data!N$2:N$2013) -> 22583000000
A16: Metric | B16: 2020 | C16: 2021 | D16: Agilent Technologies | E16: =SUMIF(Cleaned_Data!C$2:C$2013,D16,Cleaned_Data!N$2:N$2013) -> 6142000000 | J16: J16 | K16: YoY Growth
A17: Total Revenue | B17: =SUMPRODUCT((YEAR(Cleaned_Data!$B$2:$B$2013)=2020)*Cleaned_Data!$N$2:$N$2013) -> 5602951341000 | C17: =SUMPRODUCT((YEAR(Cleaned_Data!$B$2:$B$2013)=2021)*Cleaned_Data!$N$2:$N$2013) -> 7570392871500 | D17: Air Products & Chemicals | E17: =SUMIF(Cleaned_Data!C$2:C$2013,D17,Cleaned_Data!N$2:N$2013) -> 10323000000 | J17: J17 | K17: =(C17-B17)/B17 -> 0.35114378
A18: Gross Profit | B18: =SUMPRODUCT((YEAR(Cleaned_Data!$B$2:$B$2013)=2020)*Cleaned_Data!$I$2:$I$2013) -> 2135633400000 | C18: =SUMPRODUCT((YEAR(Cleaned_Data!$B$2:$B$2013)=2021)*Cleaned_Data!$I$2:$I$2013) -> 3029897436500 | D18: Akamai Technologies | E18: =SUMIF(Cleaned_Data!C$2:C$2013,D18,Cleaned_Data!N$2:N$2013) -> 3402152000 | J18: J18 | K18: =(C18-B18)/B18 -> 0.41873481
A19: Operating Income | B19: =SUMPRODUCT((YEAR(Cleaned_Data!$B$2:$B$2013)=2020)*Cleaned_Data!$K$2:$K$2013) -> 781890796000 | C19: =SUMPRODUCT((YEAR(Cleaned_Data!$B$2:$B$2013)=2021)*Cleaned_Data!$K$2:$K$2013) -> 1267241017000 | D19: Alaska Air Group | E19: =SUMIF(Cleaned_Data!C$2:C$2013,D19,Cleaned_Data!N$2:N$2013) -> 3312900000 | J19: J19 | K19: =(C19-B19)/B19 -> 0.62073914
A20: Net Income | B20: =SUMPRODUCT((YEAR(Cleaned_Data!$B$2:$B$2013)=2020)*Cleaned_Data!$G$2:$G$2013) -> 476451314000 | C20: =SUMPRODUCT((YEAR(Cleaned_Data!$B$2:$B$2013)=2021)*Cleaned_Data!$G$2:$G$2013) -> 965414366000 | D20: Albemarle Corporation | E20: =SUMIF(Cleaned_Data!C$2:C$2013,D20,Cleaned_Data!N$2:N$2013) -> 5085000000 | J20: J20 | K20: =(C20-B20)/B20 -> 1.0262603
D21: Alexandria Real Estate Equities | E21: =SUMIF(Cleaned_Data!C$2:C$2013,D21,Cleaned_Data!N$2:N$2013) -> 2013777000
D22: Align Technology | E22: =SUMIF(Cleaned_Data!C$2:C$2013,D22,Cleaned_Data!N$2:N$2013) -> 3756005000
A23: Margin | B23: 2020 | C23: 2021 | D23: Allegion | E23: =SUMIF(Cleaned_Data!C$2:C$2013,D23,Cleaned_Data!N$2:N$2013) -> 2885500000 | J23: Financial_Analysis | O23: Company | P23: Operating Income | Q23: Revenue | R23: Operating Margin | T23: Company | U23: Operating Margin
A24: Gross Profit Margin | B24: =B18/B17 -> 0.38116223 | C24: =C18/C17 -> 0.40022988 | D24: Alliant Energy | E24: =SUMIF(Cleaned_Data!C$2:C$2013,D24,Cleaned_Data!N$2:N$2013) -> 3559000000 | J24: =IFERROR(__xludf.DUMMYFUNCTION("QUERY({Cleaned_Data!C2:C2013,Cleaned_Data!K2:K2013,Cleaned_Data!N2:N2013},""select Col1, sum(Col2), sum(Col3) where Col1 is not null group by Col1"",0)"),"") | K24: =IFERROR(__xludf.DUMMYFUNCTION("""COMPUTED_VALUE"""),"sum ") -> sum | L24: =IFERROR(__xludf.DUMMYFUNCTION("""COMPUTED_VALUE"""),"sum ") -> sum | M24: =IFERROR(K24*1/(L24*1),"") | O24: {=UNIQUE(Cleaned_Data!C2:C2013)} -> 3M | P24: =SUMIF(Cleaned_Data!C$2:C$2013,O24,Cleaned_Data!K$2:K$2013) -> 15978000000 | Q24: =SUMIF(Cleaned_Data!C$2:C$2013,O24,Cleaned_Data!N$2:N$2013) -> 70652000000 | R24: =IFERROR(P24/Q24,"") -> 0.22615071 | T24: =IFERROR(__xludf.DUMMYFUNCTION("SORTN(FILTER({O24:O525,R24:R525},Q24:Q525>1000000000),10,0,2,FALSE)"),"Visa") -> Visa | U24: =IFERROR(__xludf.DUMMYFUNCTION("""COMPUTED_VALUE"""),0.6476796043626087) -> 0.6476796
A25: Operating Margin | B25: =B19/B17 -> 0.13954981 | C25: =C19/C17 -> 0.16739435 | D25: Allstate Corp | E25: =SUMIF(Cleaned_Data!C$2:C$2013,D25,Cleaned_Data!N$2:N$2013) -> 49595000000 | J25: =IFERROR(__xludf.DUMMYFUNCTION("""COMPUTED_VALUE"""),"3M") -> 3M | K25: =IFERROR(__xludf.DUMMYFUNCTION("""COMPUTED_VALUE"""),1.5978E10) -> 15978000000 | L25: =IFERROR(__xludf.DUMMYFUNCTION("""COMPUTED_VALUE"""),7.0652E10) -> 70652000000 | O25: A. O. Smith | P25: =SUMIF(Cleaned_Data!C$2:C$2013,O25,Cleaned_Data!K$2:K$2013) -> 579100000 | Q25: =SUMIF(Cleaned_Data!C$2:C$2013,O25,Cleaned_Data!N$2:N$2013) -> 3377900000 | R25: =IFERROR(P25/Q25,"") -> 0.17143788 | T25: =IFERROR(__xludf.DUMMYFUNCTION("""COMPUTED_VALUE"""),"Verisign") -> Verisign | U25: =IFERROR(__xludf.DUMMYFUNCTION("""COMPUTED_VALUE"""),0.6463368259797753) -> 0.64633683
A26: Net Profit Margin | B26: =B20/B17 -> 0.085035776 | C26: =C20/C17 -> 0.127525 | D26: Alphabet (Class A) | E26: =SUMIF(Cleaned_Data!C$2:C$2013,D26,Cleaned_Data!N$2:N$2013) -> 220265000000 | J26: =IFERROR(__xludf.DUMMYFUNCTION("""COMPUTED_VALUE"""),"A. O. Smith") -> A. O. Smith | K26: =IFERROR(__xludf.DUMMYFUNCTION("""COMPUTED_VALUE"""),5.791E8) -> 579100000 | L26: =IFERROR(__xludf.DUMMYFUNCTION("""COMPUTED_VALUE"""),3.3779E9) -> 3377900000 | O26: Abbott Laboratories | P26: =SUMIF(Cleaned_Data!C$2:C$2013,O26,Cleaned_Data!K$2:K$2013) -> 9292000000 | Q26: =SUMIF(Cleaned_Data!C$2:C$2013,O26,Cleaned_Data!N$2:N$2013) -> 42308000000 | R26: =IFERROR(P26/Q26,"") -> 0.21962749 | T26: =IFERROR(__xludf.DUMMYFUNCTION("""COMPUTED_VALUE"""),"Discover Financial Services") -> Discover Financial Services | U26: =IFERROR(__xludf.DUMMYFUNCTION("""COMPUTED_VALUE"""),0.5950649111499862) -> 0.59506491
D27: Alphabet (Class C) | E27: =SUMIF(Cleaned_Data!C$2:C$2013,D27,Cleaned_Data!N$2:N$2013) -> 220265000000 | J27: =IFERROR(__xludf.DUMMYFUNCTION("""COMPUTED_VALUE"""),"ADM") -> ADM | K27: =IFERROR(__xludf.DUMMYFUNCTION("""COMPUTED_VALUE"""),2.707E9) -> 2707000000 | L27: =IFERROR(__xludf.DUMMYFUNCTION("""COMPUTED_VALUE"""),8.0137E10) -> 80137000000 | O27: AbbVie | P27: =SUMIF(Cleaned_Data!C$2:C$2013,O27,Cleaned_Data!K$2:K$2013) -> 19467000000 | Q27: =SUMIF(Cleaned_Data!C$2:C$2013,O27,Cleaned_Data!N$2:N$2013) -> 55169000000 | R27: =IFERROR(P27/Q27,"") -> 0.35286121 | T27: =IFERROR(__xludf.DUMMYFUNCTION("""COMPUTED_VALUE"""),"Synchrony Financial") -> Synchrony Financial | U27: =IFERROR(__xludf.DUMMYFUNCTION("""COMPUTED_VALUE"""),0.5730718004601041) -> 0.5730718
D28: Altria Group | E28: =SUMIF(Cleaned_Data!C$2:C$2013,D28,Cleaned_Data!N$2:N$2013) -> 21227000000 | J28: =IFERROR(__xludf.DUMMYFUNCTION("""COMPUTED_VALUE"""),"AES Corp") -> AES Corp | K28: =IFERROR(__xludf.DUMMYFUNCTION("""COMPUTED_VALUE"""),2.699E9) -> 2699000000 | L28: =IFERROR(__xludf.DUMMYFUNCTION("""COMPUTED_VALUE"""),1.0931E10) -> 10931000000 | O28: Abiomed | P28: =SUMIF(Cleaned_Data!C$2:C$2013,O28,Cleaned_Data!K$2:K$2013) -> 261956000 | Q28: =SUMIF(Cleaned_Data!C$2:C$2013,O28,Cleaned_Data!N$2:N$2013) -> 973635000 | R28: =IFERROR(P28/Q28,"") -> 0.26904949 | T28: =IFERROR(__xludf.DUMMYFUNCTION("""COMPUTED_VALUE"""),"Altria Group") -> Altria Group | U28: =IFERROR(__xludf.DUMMYFUNCTION("""COMPUTED_VALUE"""),0.5641871201771329) -> 0.56418712
A29: Cost Structure | B29: 2020 | C29: 2021 | D29: Amazon | E29: =SUMIF(Cleaned_Data!C$2:C$2013,D29,Cleaned_Data!N$2:N$2013) -> 443298000000 | J29: =IFERROR(__xludf.DUMMYFUNCTION("""COMPUTED_VALUE"""),"APA Corporation") -> APA Corporation | K29: =IFERROR(__xludf.DUMMYFUNCTION("""COMPUTED_VALUE"""),-2.676E9) -> -2676000000 | L29: =IFERROR(__xludf.DUMMYFUNCTION("""COMPUTED_VALUE"""),6.027E9) -> 6027000000 | O29: Accenture | P29: =SUMIF(Cleaned_Data!C$2:C$2013,O29,Cleaned_Data!K$2:K$2013) -> 7621529000 | Q29: =SUMIF(Cleaned_Data!C$2:C$2013,O29,Cleaned_Data!N$2:N$2013) -> 50533389000 | R29: =IFERROR(P29/Q29,"") -> 0.15082165 | T29: =IFERROR(__xludf.DUMMYFUNCTION("""COMPUTED_VALUE"""),"Moderna") -> Moderna | U29: =IFERROR(__xludf.DUMMYFUNCTION("""COMPUTED_VALUE"""),0.543879293213128) -> 0.54387929
A30: Cost of Revenue | B30: =SUMPRODUCT((YEAR(Cleaned_Data!$B$2:$B$2013)=B$29)*Cleaned_Data!$P$2:$P$2013) -> 3467317941000 | C30: =SUMPRODUCT((YEAR(Cleaned_Data!$B$2:$B$2013)=C$29)*Cleaned_Data!$P$2:$P$2013) -> 4537383866000 | D30: Amcor | E30: =SUMIF(Cleaned_Data!C$2:C$2013,D30,Cleaned_Data!N$2:N$2013) -> 12861000000 | J30: =IFERROR(__xludf.DUMMYFUNCTION("""COMPUTED_VALUE"""),"AT&T") -> AT&T | K30: =IFERROR(__xludf.DUMMYFUNCTION("""COMPUTED_VALUE"""),3.07E10) -> 30700000000 | L30: =IFERROR(__xludf.DUMMYFUNCTION("""COMPUTED_VALUE"""),1.76015E11) -> 176015000000 | O30: Activision Blizzard | P30: =SUMIF(Cleaned_Data!C$2:C$2013,O30,Cleaned_Data!K$2:K$2013) -> 3274000000 | Q30: =SUMIF(Cleaned_Data!C$2:C$2013,O30,Cleaned_Data!N$2:N$2013) -> 9053000000 | R30: =IFERROR(P30/Q30,"") -> 0.36164807 | T30: =IFERROR(__xludf.DUMMYFUNCTION("""COMPUTED_VALUE"""),"S&P Global") -> S&P Global | U30: =IFERROR(__xludf.DUMMYFUNCTION("""COMPUTED_VALUE"""),0.5418524021792966) -> 0.5418524
A31: Operating Expenses | B31: =SUMPRODUCT((YEAR(Cleaned_Data!$B$2:$B$2013)=B$29)*Cleaned_Data!$O$2:$O$2013) -> 4821060545000 | C31: =SUMPRODUCT((YEAR(Cleaned_Data!$B$2:$B$2013)=C$29)*Cleaned_Data!$O$2:$O$2013) -> 6298459761000 | D31: Ameren Corp | E31: =SUMIF(Cleaned_Data!C$2:C$2013,D31,Cleaned_Data!N$2:N$2013) -> 5735000000 | J31: =IFERROR(__xludf.DUMMYFUNCTION("""COMPUTED_VALUE"""),"AbbVie") -> AbbVie | K31: =IFERROR(__xludf.DUMMYFUNCTION("""COMPUTED_VALUE"""),1.9467E10) -> 19467000000 | L31: =IFERROR(__xludf.DUMMYFUNCTION("""COMPUTED_VALUE"""),5.5169E10) -> 55169000000 | O31: ADM | P31: =SUMIF(Cleaned_Data!C$2:C$2013,O31,Cleaned_Data!K$2:K$2013) -> 2707000000 | Q31: =SUMIF(Cleaned_Data!C$2:C$2013,O31,Cleaned_Data!N$2:N$2013) -> 80137000000 | R31: =IFERROR(P31/Q31,"") -> 0.033779652 | T31: =IFERROR(__xludf.DUMMYFUNCTION("""COMPUTED_VALUE"""),"Regeneron Pharmaceuticals") -> Regeneron Pharmaceuticals | U31: =IFERROR(__xludf.DUMMYFUNCTION("""COMPUTED_VALUE"""),0.538506461418667) -> 0.53850646
A32: SG&A | B32: =SUMPRODUCT((YEAR(Cleaned_Data!$B$2:$B$2013)=B$29)*Cleaned_Data!$H$2:$H$2013) -> 911532452000 | C32: =SUMPRODUCT((YEAR(Cleaned_Data!$B$2:$B$2013)=C$29)*Cleaned_Data!$H$2:$H$2013) -> 1243437938000 | D32: American Airlines Group | E32: =SUMIF(Cleaned_Data!C$2:C$2013,D32,Cleaned_Data!N$2:N$2013) -> 18687000000 | J32: =IFERROR(__xludf.DUMMYFUNCTION("""COMPUTED_VALUE"""),"Abbott Laboratories") -> Abbott Laboratories | K32: =IFERROR(__xludf.DUMMYFUNCTION("""COMPUTED_VALUE"""),9.292E9) -> 9292000000 | L32: =IFERROR(__xludf.DUMMYFUNCTION("""COMPUTED_VALUE"""),4.2308E10) -> 42308000000 | O32: Adobe | P32: =SUMIF(Cleaned_Data!C$2:C$2013,O32,Cleaned_Data!K$2:K$2013) -> 5516000000 | Q32: =SUMIF(Cleaned_Data!C$2:C$2013,O32,Cleaned_Data!N$2:N$2013) -> 15099000000 | R32: =IFERROR(P32/Q32,"") -> 0.36532221 | T32: =IFERROR(__xludf.DUMMYFUNCTION("""COMPUTED_VALUE"""),"CME Group") -> CME Group | U32: =IFERROR(__xludf.DUMMYFUNCTION("""COMPUTED_VALUE"""),0.5381939915655841) -> 0.53819399
A33: R&D | B33: =SUMPRODUCT((YEAR(Cleaned_Data!$B$2:$B$2013)=B$29)*Cleaned_Data!$E$2:$E$2013) -> 180628916000 | C33: =SUMPRODUCT((YEAR(Cleaned_Data!$B$2:$B$2013)=C$29)*Cleaned_Data!$E$2:$E$2013) -> 221617415000 | D33: American Electric Power | E33: =SUMIF(Cleaned_Data!C$2:C$2013,D33,Cleaned_Data!N$2:N$2013) -> 15784600000 | J33: =IFERROR(__xludf.DUMMYFUNCTION("""COMPUTED_VALUE"""),"Abiomed") -> Abiomed | K33: =IFERROR(__xludf.DUMMYFUNCTION("""COMPUTED_VALUE"""),2.61956E8) -> 261956000 | L33: =IFERROR(__xludf.DUMMYFUNCTION("""COMPUTED_VALUE"""),9.73635E8) -> 973635000 | O33: Advance Auto Parts | P33: =SUMIF(Cleaned_Data!C$2:C$2013,O33,Cleaned_Data!K$2:K$2013) -> 1087428000 | Q33: =SUMIF(Cleaned_Data!C$2:C$2013,O33,Cleaned_Data!N$2:N$2013) -> 11619092500 | R33: =IFERROR(P33/Q33,"") -> 0.093589753 | T33: =IFERROR(__xludf.DUMMYFUNCTION("""COMPUTED_VALUE"""),"MSCI") -> MSCI | U33: =IFERROR(__xludf.DUMMYFUNCTION("""COMPUTED_VALUE"""),0.5354430029957786) -> 0.535443
D34: American Express | E34: =SUMIF(Cleaned_Data!C$2:C$2013,D34,Cleaned_Data!N$2:N$2013) -> 38136000000 | J34: =IFERROR(__xludf.DUMMYFUNCTION("""COMPUTED_VALUE"""),"Accenture") -> Accenture | K34: =IFERROR(__xludf.DUMMYFUNCTION("""COMPUTED_VALUE"""),7.621529E9) -> 7621529000 | L34: =IFERROR(__xludf.DUMMYFUNCTION("""COMPUTED_VALUE"""),5.0533389E10) -> 50533389000 | O34: Advanced Micro Devices | P34: =SUMIF(Cleaned_Data!C$2:C$2013,O34,Cleaned_Data!K$2:K$2013) -> 3044000000 | Q34: =SUMIF(Cleaned_Data!C$2:C$2013,O34,Cleaned_Data!N$2:N$2013) -> 14852000000 | R34: =IFERROR(P34/Q34,"") -> 0.20495556
D35: American International Group | E35: =SUMIF(Cleaned_Data!C$2:C$2013,D35,Cleaned_Data!N$2:N$2013) -> 44339000000 | J35: =IFERROR(__xludf.DUMMYFUNCTION("""COMPUTED_VALUE"""),"Activision Blizzard") -> Activision Blizzard | K35: =IFERROR(__xludf.DUMMYFUNCTION("""COMPUTED_VALUE"""),3.274E9) -> 3274000000 | L35: =IFERROR(__xludf.DUMMYFUNCTION("""COMPUTED_VALUE"""),9.053E9) -> 9053000000 | O35: AES Corp | P35: =SUMIF(Cleaned_Data!C$2:C$2013,O35,Cleaned_Data!K$2:K$2013) -> 2699000000 | Q35: =SUMIF(Cleaned_Data!C$2:C$2013,O35,Cleaned_Data!N$2:N$2013) -> 10931000000 | R35: =IFERROR(P35/Q35,"") -> 0.24691245
D36: American Tower | E36: =SUMIF(Cleaned_Data!C$2:C$2013,D36,Cleaned_Data!N$2:N$2013) -> 8592800000 | J36: =IFERROR(__xludf.DUMMYFUNCTION("""COMPUTED_VALUE"""),"Adobe") -> Adobe | K36: =IFERROR(__xludf.DUMMYFUNCTION("""COMPUTED_VALUE"""),5.516E9) -> 5516000000 | L36: =IFERROR(__xludf.DUMMYFUNCTION("""COMPUTED_VALUE"""),1.5099E10) -> 15099000000 | O36: Aflac | P36: =SUMIF(Cleaned_Data!C$2:C$2013,O36,Cleaned_Data!K$2:K$2013) -> 5548000000 | Q36: =SUMIF(Cleaned_Data!C$2:C$2013,O36,Cleaned_Data!N$2:N$2013) -> 22583000000 | R36: =IFERROR(P36/Q36,"") -> 0.24567152
B37: =B30/B17 -> 0.61883777 | C37: =C30/C17 -> 0.5993591 | D37: American Water Works | E37: =SUMIF(Cleaned_Data!C$2:C$2013,D37,Cleaned_Data!N$2:N$2013) -> 3889000000 | J37: =IFERROR(__xludf.DUMMYFUNCTION("""COMPUTED_VALUE"""),"Advance Auto Parts") -> Advance Auto Parts | K37: =IFERROR(__xludf.DUMMYFUNCTION("""COMPUTED_VALUE"""),1.087428E9) -> 1087428000 | L37: =IFERROR(__xludf.DUMMYFUNCTION("""COMPUTED_VALUE"""),1.16190925E10) -> 11619092500 | O37: Agilent Technologies | P37: =SUMIF(Cleaned_Data!C$2:C$2013,O37,Cleaned_Data!K$2:K$2013) -> 1318000000 | Q37: =SUMIF(Cleaned_Data!C$2:C$2013,O37,Cleaned_Data!N$2:N$2013) -> 6142000000 | R37: =IFERROR(P37/Q37,"") -> 0.21458808
B38: =B31/B17 -> 0.86045019 | C38: =C31/C17 -> 0.83198585 | D38: Ameriprise Financial | E38: =SUMIF(Cleaned_Data!C$2:C$2013,D38,Cleaned_Data!N$2:N$2013) -> 12977000000 | J38: =IFERROR(__xludf.DUMMYFUNCTION("""COMPUTED_VALUE"""),"Advanced Micro Devices") -> Advanced Micro Devices | K38: =IFERROR(__xludf.DUMMYFUNCTION("""COMPUTED_VALUE"""),3.044E9) -> 3044000000 | L38: =IFERROR(__xludf.DUMMYFUNCTION("""COMPUTED_VALUE"""),1.4852E10) -> 14852000000 | O38: Air Products & Chemicals | P38: =SUMIF(Cleaned_Data!C$2:C$2013,O38,Cleaned_Data!K$2:K$2013) -> 2333400000 | Q38: =SUMIF(Cleaned_Data!C$2:C$2013,O38,Cleaned_Data!N$2:N$2013) -> 10323000000 | R38: =IFERROR(P38/Q38,"") -> 0.22603894
B39: =B32/B17 -> 0.16268791 | C39: =C32/C17 -> 0.16425012 | D39: AmerisourceBergen | E39: =SUMIF(Cleaned_Data!C$2:C$2013,D39,Cleaned_Data!N$2:N$2013) -> 204321190000 | J39: =IFERROR(__xludf.DUMMYFUNCTION("""COMPUTED_VALUE"""),"Aflac") -> Aflac | K39: =IFERROR(__xludf.DUMMYFUNCTION("""COMPUTED_VALUE"""),5.548E9) -> 5548000000 | L39: =IFERROR(__xludf.DUMMYFUNCTION("""COMPUTED_VALUE"""),2.2583E10) -> 22583000000 | O39: Akamai Technologies | P39: =SUMIF(Cleaned_Data!C$2:C$2013,O39,Cleaned_Data!K$2:K$2013) -> 759729000 | Q39: =SUMIF(Cleaned_Data!C$2:C$2013,O39,Cleaned_Data!N$2:N$2013) -> 3402152000 | R39: =IFERROR(P39/Q39,"") -> 0.22330836
B40: =B33/B17 -> 0.032238173 | C40: =C33/C17 -> 0.029274229 | D40: Ametek | E40: =SUMIF(Cleaned_Data!C$2:C$2013,D40,Cleaned_Data!N$2:N$2013) -> 4927977000 | J40: =IFERROR(__xludf.DUMMYFUNCTION("""COMPUTED_VALUE"""),"Agilent Technologies") -> Agilent Technologies | K40: =IFERROR(__xludf.DUMMYFUNCTION("""COMPUTED_VALUE"""),1.318E9) -> 1318000000 | L40: =IFERROR(__xludf.DUMMYFUNCTION("""COMPUTED_VALUE"""),6.142E9) -> 6142000000 | O40: Alaska Air Group | P40: =SUMIF(Cleaned_Data!C$2:C$2013,O40,Cleaned_Data!K$2:K$2013) -> 561132000 | Q40: =SUMIF(Cleaned_Data!C$2:C$2013,O40,Cleaned_Data!N$2:N$2013) -> 3312900000 | R40: =IFERROR(P40/Q40,"") -> 0.16937789
D41: Amgen | E41: =SUMIF(Cleaned_Data!C$2:C$2013,D41,Cleaned_Data!N$2:N$2013) -> 25484000000 | J41: =IFERROR(__xludf.DUMMYFUNCTION("""COMPUTED_VALUE"""),"Air Products & Chemicals") -> Air Products & Chemicals | K41: =IFERROR(__xludf.DUMMYFUNCTION("""COMPUTED_VALUE"""),2.3334E9) -> 2333400000 | L41: =IFERROR(__xludf.DUMMYFUNCTION("""COMPUTED_VALUE"""),1.0323E10) -> 10323000000 | O41: Albemarle Corporation | P41: =SUMIF(Cleaned_Data!C$2:C$2013,O41,Cleaned_Data!K$2:K$2013) -> -801000000 | Q41: =SUMIF(Cleaned_Data!C$2:C$2013,O41,Cleaned_Data!N$2:N$2013) -> 5085000000 | R41: =IFERROR(P41/Q41,"") -> -0.15752212
D42: Amphenol | E42: =SUMIF(Cleaned_Data!C$2:C$2013,D42,Cleaned_Data!N$2:N$2013) -> 9114000000 | J42: =IFERROR(__xludf.DUMMYFUNCTION("""COMPUTED_VALUE"""),"Akamai Technologies") -> Akamai Technologies | K42: =IFERROR(__xludf.DUMMYFUNCTION("""COMPUTED_VALUE"""),7.59729E8) -> 759729000 | L42: =IFERROR(__xludf.DUMMYFUNCTION("""COMPUTED_VALUE"""),3.402152E9) -> 3402152000 | O42: Alexandria Real Estate Equities | P42: =SUMIF(Cleaned_Data!C$2:C$2013,O42,Cleaned_Data!K$2:K$2013) -> 527118000 | Q42: =SUMIF(Cleaned_Data!C$2:C$2013,O42,Cleaned_Data!N$2:N$2013) -> 2013777000 | R42: =IFERROR(P42/Q42,"") -> 0.26175589
D43: Analog Devices | E43: =SUMIF(Cleaned_Data!C$2:C$2013,D43,Cleaned_Data!N$2:N$2013) -> 6505013000 | J43: =IFERROR(__xludf.DUMMYFUNCTION("""COMPUTED_VALUE"""),"Alaska Air Group") -> Alaska Air Group | K43: =IFERROR(__xludf.DUMMYFUNCTION("""COMPUTED_VALUE"""),5.61132E8) -> 561132000 | L43: =IFERROR(__xludf.DUMMYFUNCTION("""COMPUTED_VALUE"""),3.3129E9) -> 3312900000 | O43: Align Technology | P43: =SUMIF(Cleaned_Data!C$2:C$2013,O43,Cleaned_Data!K$2:K$2013) -> 968692000 | Q43: =SUMIF(Cleaned_Data!C$2:C$2013,O43,Cleaned_Data!N$2:N$2013) -> 3756005000 | R43: =IFERROR(P43/Q43,"") -> 0.25790487
D44: Ansys | E44: =SUMIF(Cleaned_Data!C$2:C$2013,D44,Cleaned_Data!N$2:N$2013) -> 1800531000 | J44: =IFERROR(__xludf.DUMMYFUNCTION("""COMPUTED_VALUE"""),"Albemarle Corporation") -> Albemarle Corporation | K44: =IFERROR(__xludf.DUMMYFUNCTION("""COMPUTED_VALUE"""),-8.01E8) -> -801000000 | L44: =IFERROR(__xludf.DUMMYFUNCTION("""COMPUTED_VALUE"""),5.085E9) -> 5085000000 | O44: Allegion | P44: =SUMIF(Cleaned_Data!C$2:C$2013,O44,Cleaned_Data!K$2:K$2013) -> 585200000 | Q44: =SUMIF(Cleaned_Data!C$2:C$2013,O44,Cleaned_Data!N$2:N$2013) -> 2885500000 | R44: =IFERROR(P44/Q44,"") -> 0.20280714
D45: Anthem | E45: =SUMIF(Cleaned_Data!C$2:C$2013,D45,Cleaned_Data!N$2:N$2013) -> 133883000000 | J45: =IFERROR(__xludf.DUMMYFUNCTION("""COMPUTED_VALUE"""),"Alexandria Real Estate Equities") -> Alexandria Real Estate Equities | K45: =IFERROR(__xludf.DUMMYFUNCTION("""COMPUTED_VALUE"""),5.27118E8) -> 527118000 | L45: =IFERROR(__xludf.DUMMYFUNCTION("""COMPUTED_VALUE"""),2.013777E9) -> 2013777000 | O45: Alliant Energy | P45: =SUMIF(Cleaned_Data!C$2:C$2013,O45,Cleaned_Data!K$2:K$2013) -> 751000000 | Q45: =SUMIF(Cleaned_Data!C$2:C$2013,O45,Cleaned_Data!N$2:N$2013) -> 3559000000 | R45: =IFERROR(P45/Q45,"") -> 0.21101433
D46: Aon | E46: =SUMIF(Cleaned_Data!C$2:C$2013,D46,Cleaned_Data!N$2:N$2013) -> 11761000000 | J46: =IFERROR(__xludf.DUMMYFUNCTION("""COMPUTED_VALUE"""),"Align Technology") -> Align Technology | K46: =IFERROR(__xludf.DUMMYFUNCTION("""COMPUTED_VALUE"""),9.68692E8) -> 968692000 | L46: =IFERROR(__xludf.DUMMYFUNCTION("""COMPUTED_VALUE"""),3.756005E9) -> 3756005000 | O46: Allstate Corp | P46: =SUMIF(Cleaned_Data!C$2:C$2013,O46,Cleaned_Data!K$2:K$2013) -> 8926000000 | Q46: =SUMIF(Cleaned_Data!C$2:C$2013,O46,Cleaned_Data!N$2:N$2013) -> 49595000000 | R46: =IFERROR(P46/Q46,"") -> 0.17997782
D47: APA Corporation | E47: =SUMIF(Cleaned_Data!C$2:C$2013,D47,Cleaned_Data!N$2:N$2013) -> 6027000000 | J47: =IFERROR(__xludf.DUMMYFUNCTION("""COMPUTED_VALUE"""),"Allegion") -> Allegion | K47: =IFERROR(__xludf.DUMMYFUNCTION("""COMPUTED_VALUE"""),5.852E8) -> 585200000 | L47: =IFERROR(__xludf.DUMMYFUNCTION("""COMPUTED_VALUE"""),2.8855E9) -> 2885500000 | O47: Alphabet (Class A) | P47: =SUMIF(Cleaned_Data!C$2:C$2013,O47,Cleaned_Data!K$2:K$2013) -> 62662000000 | Q47: =SUMIF(Cleaned_Data!C$2:C$2013,O47,Cleaned_Data!N$2:N$2013) -> 220265000000 | R47: =IFERROR(P47/Q47,"") -> 0.2844846
D48: Apple | E48: =SUMIF(Cleaned_Data!C$2:C$2013,D48,Cleaned_Data!N$2:N$2013) -> 347155000000 | J48: =IFERROR(__xludf.DUMMYFUNCTION("""COMPUTED_VALUE"""),"Alliant Energy") -> Alliant Energy | K48: =IFERROR(__xludf.DUMMYFUNCTION("""COMPUTED_VALUE"""),7.51E8) -> 751000000 | L48: =IFERROR(__xludf.DUMMYFUNCTION("""COMPUTED_VALUE"""),3.559E9) -> 3559000000 | O48: Alphabet (Class C) | P48: =SUMIF(Cleaned_Data!C$2:C$2013,O48,Cleaned_Data!K$2:K$2013) -> 62662000000 | Q48: =SUMIF(Cleaned_Data!C$2:C$2013,O48,Cleaned_Data!N$2:N$2013) -> 220265000000 | R48: =IFERROR(P48/Q48,"") -> 0.2844846
D49: Applied Materials | E49: =SUMIF(Cleaned_Data!C$2:C$2013,D49,Cleaned_Data!N$2:N$2013) -> 21628000000 | J49: =IFERROR(__xludf.DUMMYFUNCTION("""COMPUTED_VALUE"""),"Allstate Corp") -> Allstate Corp | K49: =IFERROR(__xludf.DUMMYFUNCTION("""COMPUTED_VALUE"""),8.926E9) -> 8926000000 | L49: =IFERROR(__xludf.DUMMYFUNCTION("""COMPUTED_VALUE"""),4.9595E10) -> 49595000000 | O49: Altria Group | P49: =SUMIF(Cleaned_Data!C$2:C$2013,O49,Cleaned_Data!K$2:K$2013) -> 11976000000 | Q49: =SUMIF(Cleaned_Data!C$2:C$2013,O49,Cleaned_Data!N$2:N$2013) -> 21227000000 | R49: =IFERROR(P49/Q49,"") -> 0.56418712
D50: Aptiv | E50: =SUMIF(Cleaned_Data!C$2:C$2013,D50,Cleaned_Data!N$2:N$2013) -> 15710000000 | J50: =IFERROR(__xludf.DUMMYFUNCTION("""COMPUTED_VALUE"""),"Alphabet (Class A)") -> Alphabet (Class A) | K50: =IFERROR(__xludf.DUMMYFUNCTION("""COMPUTED_VALUE"""),6.2662E10) -> 62662000000 | L50: =IFERROR(__xludf.DUMMYFUNCTION("""COMPUTED_VALUE"""),2.20265E11) -> 220265000000 | O50: Amazon | P50: =SUMIF(Cleaned_Data!C$2:C$2013,O50,Cleaned_Data!K$2:K$2013) -> 29634000000 | Q50: =SUMIF(Cleaned_Data!C$2:C$2013,O50,Cleaned_Data!N$2:N$2013) -> 443298000000 | R50: =IFERROR(P50/Q50,"") -> 0.066848937
D51: Arista Networks | E51: =SUMIF(Cleaned_Data!C$2:C$2013,D51,Cleaned_Data!N$2:N$2013) -> 2628794000 | J51: =IFERROR(__xludf.DUMMYFUNCTION("""COMPUTED_VALUE"""),"Alphabet (Class C)") -> Alphabet (Class C) | K51: =IFERROR(__xludf.DUMMYFUNCTION("""COMPUTED_VALUE"""),6.2662E10) -> 62662000000 | L51: =IFERROR(__xludf.DUMMYFUNCTION("""COMPUTED_VALUE"""),2.20265E11) -> 220265000000 | O51: Amcor | P51: =SUMIF(Cleaned_Data!C$2:C$2013,O51,Cleaned_Data!K$2:K$2013) -> 1438000000 | Q51: =SUMIF(Cleaned_Data!C$2:C$2013,O51,Cleaned_Data!N$2:N$2013) -> 12861000000 | R51: =IFERROR(P51/Q51,"") -> 0.1118109
D52: Arthur J. Gallagher & Co. | E52: =SUMIF(Cleaned_Data!C$2:C$2013,D52,Cleaned_Data!N$2:N$2013) -> 7426500000 | J52: =IFERROR(__xludf.DUMMYFUNCTION("""COMPUTED_VALUE"""),"Altria Group") -> Altria Group | K52: =IFERROR(__xludf.DUMMYFUNCTION("""COMPUTED_VALUE"""),1.1976E10) -> 11976000000 | L52: =IFERROR(__xludf.DUMMYFUNCTION("""COMPUTED_VALUE"""),2.1227E10) -> 21227000000 | O52: Ameren Corp | P52: =SUMIF(Cleaned_Data!C$2:C$2013,O52,Cleaned_Data!K$2:K$2013) -> 1438000000 | Q52: =SUMIF(Cleaned_Data!C$2:C$2013,O52,Cleaned_Data!N$2:N$2013) -> 5735000000 | R52: =IFERROR(P52/Q52,"") -> 0.25074106
D53: Assurant | E53: =SUMIF(Cleaned_Data!C$2:C$2013,D53,Cleaned_Data!N$2:N$2013) -> 10032500000 | J53: =IFERROR(__xludf.DUMMYFUNCTION("""COMPUTED_VALUE"""),"Amazon") -> Amazon | K53: =IFERROR(__xludf.DUMMYFUNCTION("""COMPUTED_VALUE"""),2.9634E10) -> 29634000000 | L53: =IFERROR(__xludf.DUMMYFUNCTION("""COMPUTED_VALUE"""),4.43298E11) -> 443298000000 | O53: American Airlines Group | P53: =SUMIF(Cleaned_Data!C$2:C$2013,O53,Cleaned_Data!K$2:K$2013) -> -9862000000 | Q53: =SUMIF(Cleaned_Data!C$2:C$2013,O53,Cleaned_Data!N$2:N$2013) -> 18687000000 | R53: =IFERROR(P53/Q53,"") -> -0.52774656
D54: AT&T | E54: =SUMIF(Cleaned_Data!C$2:C$2013,D54,Cleaned_Data!N$2:N$2013) -> 176015000000 | J54: =IFERROR(__xludf.DUMMYFUNCTION("""COMPUTED_VALUE"""),"Amcor") -> Amcor | K54: =IFERROR(__xludf.DUMMYFUNCTION("""COMPUTED_VALUE"""),1.438E9) -> 1438000000 | L54: =IFERROR(__xludf.DUMMYFUNCTION("""COMPUTED_VALUE"""),1.2861E10) -> 12861000000 | O54: American Electric Power | P54: =SUMIF(Cleaned_Data!C$2:C$2013,O54,Cleaned_Data!K$2:K$2013) -> 3252400000 | Q54: =SUMIF(Cleaned_Data!C$2:C$2013,O54,Cleaned_Data!N$2:N$2013) -> 15784600000 | R54: =IFERROR(P54/Q54,"") -> 0.20604893
D55: Atmos Energy | E55: =SUMIF(Cleaned_Data!C$2:C$2013,D55,Cleaned_Data!N$2:N$2013) -> 3314020000 | J55: =IFERROR(__xludf.DUMMYFUNCTION("""COMPUTED_VALUE"""),"Ameren Corp") -> Ameren Corp | K55: =IFERROR(__xludf.DUMMYFUNCTION("""COMPUTED_VALUE"""),1.438E9) -> 1438000000 | L55: =IFERROR(__xludf.DUMMYFUNCTION("""COMPUTED_VALUE"""),5.735E9) -> 5735000000 | O55: American Express | P55: =SUMIF(Cleaned_Data!C$2:C$2013,O55,Cleaned_Data!K$2:K$2013) -> 8677000000 | Q55: =SUMIF(Cleaned_Data!C$2:C$2013,O55,Cleaned_Data!N$2:N$2013) -> 38136000000 | R55: =IFERROR(P55/Q55,"") -> 0.2275278
D56: Autodesk | E56: =SUMIF(Cleaned_Data!C$2:C$2013,D56,Cleaned_Data!N$2:N$2013) -> 4040600000 | J56: =IFERROR(__xludf.DUMMYFUNCTION("""COMPUTED_VALUE"""),"American Airlines Group") -> American Airlines Group | K56: =IFERROR(__xludf.DUMMYFUNCTION("""COMPUTED_VALUE"""),-9.862E9) -> -9862000000 | L56: =IFERROR(__xludf.DUMMYFUNCTION("""COMPUTED_VALUE"""),1.8687E10) -> 18687000000 | O56: American International Group | P56: =SUMIF(Cleaned_Data!C$2:C$2013,O56,Cleaned_Data!K$2:K$2013) -> 5804000000 | Q56: =SUMIF(Cleaned_Data!C$2:C$2013,O56,Cleaned_Data!N$2:N$2013) -> 44339000000 | R56: =IFERROR(P56/Q56,"") -> 0.13090056
D57: Automatic Data Processing | E57: =SUMIF(Cleaned_Data!C$2:C$2013,D57,Cleaned_Data!N$2:N$2013) -> 15005400000 | J57: =IFERROR(__xludf.DUMMYFUNCTION("""COMPUTED_VALUE"""),"American Electric Power") -> American Electric Power | K57: =IFERROR(__xludf.DUMMYFUNCTION("""COMPUTED_VALUE"""),3.2524E9) -> 3252400000 | L57: =IFERROR(__xludf.DUMMYFUNCTION("""COMPUTED_VALUE"""),1.57846E10) -> 15784600000 | O57: American Tower | P57: =SUMIF(Cleaned_Data!C$2:C$2013,O57,Cleaned_Data!K$2:K$2013) -> 3425900000 | Q57: =SUMIF(Cleaned_Data!C$2:C$2013,O57,Cleaned_Data!N$2:N$2013) -> 8592800000 | R57: =IFERROR(P57/Q57,"") -> 0.39869426
D58: AutoZone | E58: =SUMIF(Cleaned_Data!C$2:C$2013,D58,Cleaned_Data!N$2:N$2013) -> 14629586000 | J58: =IFERROR(__xludf.DUMMYFUNCTION("""COMPUTED_VALUE"""),"American Express") -> American Express | K58: =IFERROR(__xludf.DUMMYFUNCTION("""COMPUTED_VALUE"""),8.677E9) -> 8677000000 | L58: =IFERROR(__xludf.DUMMYFUNCTION("""COMPUTED_VALUE"""),3.8136E10) -> 38136000000 | O58: American Water Works | P58: =SUMIF(Cleaned_Data!C$2:C$2013,O58,Cleaned_Data!K$2:K$2013) -> 1318000000 | Q58: =SUMIF(Cleaned_Data!C$2:C$2013,O58,Cleaned_Data!N$2:N$2013) -> 3889000000 | R58: =IFERROR(P58/Q58,"") -> 0.3389046
D59: AvalonBay Communities | E59: =SUMIF(Cleaned_Data!C$2:C$2013,D59,Cleaned_Data!N$2:N$2013) -> 2234664000 | J59: =IFERROR(__xludf.DUMMYFUNCTION("""COMPUTED_VALUE"""),"American International Group") -> American International Group | K59: =IFERROR(__xludf.DUMMYFUNCTION("""COMPUTED_VALUE"""),5.804E9) -> 5804000000 | L59: =IFERROR(__xludf.DUMMYFUNCTION("""COMPUTED_VALUE"""),4.4339E10) -> 44339000000 | O59: Ameriprise Financial | P59: =SUMIF(Cleaned_Data!C$2:C$2013,O59,Cleaned_Data!K$2:K$2013) -> 1985000000 | Q59: =SUMIF(Cleaned_Data!C$2:C$2013,O59,Cleaned_Data!N$2:N$2013) -> 12977000000 | R59: =IFERROR(P59/Q59,"") -> 0.15296293
D60: Avery Dennison | E60: =SUMIF(Cleaned_Data!C$2:C$2013,D60,Cleaned_Data!N$2:N$2013) -> 7873300000 | J60: =IFERROR(__xludf.DUMMYFUNCTION("""COMPUTED_VALUE"""),"American Tower") -> American Tower | K60: =IFERROR(__xludf.DUMMYFUNCTION("""COMPUTED_VALUE"""),3.4259E9) -> 3425900000 | L60: =IFERROR(__xludf.DUMMYFUNCTION("""COMPUTED_VALUE"""),8.5928E9) -> 8592800000 | O60: AmerisourceBergen | P60: =SUMIF(Cleaned_Data!C$2:C$2013,O60,Cleaned_Data!K$2:K$2013) -> 2745755000 | Q60: =SUMIF(Cleaned_Data!C$2:C$2013,O60,Cleaned_Data!N$2:N$2013) -> 204321190000 | R60: =IFERROR(P60/Q60,"") -> 0.013438425
D61: Baker Hughes | E61: =SUMIF(Cleaned_Data!C$2:C$2013,D61,Cleaned_Data!N$2:N$2013) -> 20512000000 | J61: =IFERROR(__xludf.DUMMYFUNCTION("""COMPUTED_VALUE"""),"American Water Works") -> American Water Works | K61: =IFERROR(__xludf.DUMMYFUNCTION("""COMPUTED_VALUE"""),1.318E9) -> 1318000000 | L61: =IFERROR(__xludf.DUMMYFUNCTION("""COMPUTED_VALUE"""),3.889E9) -> 3889000000 | O61: Ametek | P61: =SUMIF(Cleaned_Data!C$2:C$2013,O61,Cleaned_Data!K$2:K$2013) -> 1163411000 | Q61: =SUMIF(Cleaned_Data!C$2:C$2013,O61,Cleaned_Data!N$2:N$2013) -> 4927977000 | R61: =IFERROR(P61/Q61,"") -> 0.23608288
D62: Ball Corp | E62: =SUMIF(Cleaned_Data!C$2:C$2013,D62,Cleaned_Data!N$2:N$2013) -> 12779000000 | J62: =IFERROR(__xludf.DUMMYFUNCTION("""COMPUTED_VALUE"""),"Ameriprise Financial") -> Ameriprise Financial | K62: =IFERROR(__xludf.DUMMYFUNCTION("""COMPUTED_VALUE"""),1.985E9) -> 1985000000 | L62: =IFERROR(__xludf.DUMMYFUNCTION("""COMPUTED_VALUE"""),1.2977E10) -> 12977000000 | O62: Amgen | P62: =SUMIF(Cleaned_Data!C$2:C$2013,O62,Cleaned_Data!K$2:K$2013) -> 8950000000 | Q62: =SUMIF(Cleaned_Data!C$2:C$2013,O62,Cleaned_Data!N$2:N$2013) -> 25484000000 | R62: =IFERROR(P62/Q62,"") -> 0.35120075
D63: Bank of America | E63: =SUMIF(Cleaned_Data!C$2:C$2013,D63,Cleaned_Data!N$2:N$2013) -> 91204000000 | J63: =IFERROR(__xludf.DUMMYFUNCTION("""COMPUTED_VALUE"""),"AmerisourceBergen") -> AmerisourceBergen | K63: =IFERROR(__xludf.DUMMYFUNCTION("""COMPUTED_VALUE"""),2.745755E9) -> 2745755000 | L63: =IFERROR(__xludf.DUMMYFUNCTION("""COMPUTED_VALUE"""),2.0432119E11) -> 204321190000 | O63: Amphenol | P63: =SUMIF(Cleaned_Data!C$2:C$2013,O63,Cleaned_Data!K$2:K$2013) -> 1791000000 | Q63: =SUMIF(Cleaned_Data!C$2:C$2013,O63,Cleaned_Data!N$2:N$2013) -> 9114000000 | R63: =IFERROR(P63/Q63,"") -> 0.19651086
D64: Bath & Body Works Inc. | E64: =SUMIF(Cleaned_Data!C$2:C$2013,D64,Cleaned_Data!N$2:N$2013) -> 14215000000 | J64: =IFERROR(__xludf.DUMMYFUNCTION("""COMPUTED_VALUE"""),"Ametek") -> Ametek | K64: =IFERROR(__xludf.DUMMYFUNCTION("""COMPUTED_VALUE"""),1.163411E9) -> 1163411000 | L64: =IFERROR(__xludf.DUMMYFUNCTION("""COMPUTED_VALUE"""),4.927977E9) -> 4927977000 | O64: Analog Devices | P64: =SUMIF(Cleaned_Data!C$2:C$2013,O64,Cleaned_Data!K$2:K$2013) -> 2130126000 | Q64: =SUMIF(Cleaned_Data!C$2:C$2013,O64,Cleaned_Data!N$2:N$2013) -> 6505013000 | R64: =IFERROR(P64/Q64,"") -> 0.32745915
D65: Baxter International | E65: =SUMIF(Cleaned_Data!C$2:C$2013,D65,Cleaned_Data!N$2:N$2013) -> 12197000000 | J65: =IFERROR(__xludf.DUMMYFUNCTION("""COMPUTED_VALUE"""),"Amgen") -> Amgen | K65: =IFERROR(__xludf.DUMMYFUNCTION("""COMPUTED_VALUE"""),8.95E9) -> 8950000000 | L65: =IFERROR(__xludf.DUMMYFUNCTION("""COMPUTED_VALUE"""),2.5484E10) -> 25484000000 | O65: Ansys | P65: =SUMIF(Cleaned_Data!C$2:C$2013,O65,Cleaned_Data!K$2:K$2013) -> 523432000 | Q65: =SUMIF(Cleaned_Data!C$2:C$2013,O65,Cleaned_Data!N$2:N$2013) -> 1800531000 | R65: =IFERROR(P65/Q65,"") -> 0.2907098
D66: Becton Dickinson | E66: =SUMIF(Cleaned_Data!C$2:C$2013,D66,Cleaned_Data!N$2:N$2013) -> 19896000000 | J66: =IFERROR(__xludf.DUMMYFUNCTION("""COMPUTED_VALUE"""),"Amphenol") -> Amphenol | K66: =IFERROR(__xludf.DUMMYFUNCTION("""COMPUTED_VALUE"""),1.791E9) -> 1791000000 | L66: =IFERROR(__xludf.DUMMYFUNCTION("""COMPUTED_VALUE"""),9.114E9) -> 9114000000 | O66: Anthem | P66: =SUMIF(Cleaned_Data!C$2:C$2013,O66,Cleaned_Data!K$2:K$2013) -> 7933000000 | Q66: =SUMIF(Cleaned_Data!C$2:C$2013,O66,Cleaned_Data!N$2:N$2013) -> 133883000000 | R66: =IFERROR(P66/Q66,"") -> 0.059253229
D67: Best Buy | E67: =SUMIF(Cleaned_Data!C$2:C$2013,D67,Cleaned_Data!N$2:N$2013) -> 52276000000 | J67: =IFERROR(__xludf.DUMMYFUNCTION("""COMPUTED_VALUE"""),"Analog Devices") -> Analog Devices | K67: =IFERROR(__xludf.DUMMYFUNCTION("""COMPUTED_VALUE"""),2.130126E9) -> 2130126000 | L67: =IFERROR(__xludf.DUMMYFUNCTION("""COMPUTED_VALUE"""),6.505013E9) -> 6505013000 | O67: Aon | P67: =SUMIF(Cleaned_Data!C$2:C$2013,O67,Cleaned_Data!K$2:K$2013) -> 3237000000 | Q67: =SUMIF(Cleaned_Data!C$2:C$2013,O67,Cleaned_Data!N$2:N$2013) -> 11761000000 | R67: =IFERROR(P67/Q67,"") -> 0.2752317
D68: Bio-Rad Laboratories | E68: =SUMIF(Cleaned_Data!C$2:C$2013,D68,Cleaned_Data!N$2:N$2013) -> 2879829000 | J68: =IFERROR(__xludf.DUMMYFUNCTION("""COMPUTED_VALUE"""),"Ansys") -> Ansys | K68: =IFERROR(__xludf.DUMMYFUNCTION("""COMPUTED_VALUE"""),5.23432E8) -> 523432000 | L68: =IFERROR(__xludf.DUMMYFUNCTION("""COMPUTED_VALUE"""),1.800531E9) -> 1800531000 | O68: APA Corporation | P68: =SUMIF(Cleaned_Data!C$2:C$2013,O68,Cleaned_Data!K$2:K$2013) -> -2676000000 | Q68: =SUMIF(Cleaned_Data!C$2:C$2013,O68,Cleaned_Data!N$2:N$2013) -> 6027000000 | R68: =IFERROR(P68/Q68,"") -> -0.44400199
D69: Bio-Techne | E69: =SUMIF(Cleaned_Data!C$2:C$2013,D69,Cleaned_Data!N$2:N$2013) -> 931032000 | J69: =IFERROR(__xludf.DUMMYFUNCTION("""COMPUTED_VALUE"""),"Anthem") -> Anthem | K69: =IFERROR(__xludf.DUMMYFUNCTION("""COMPUTED_VALUE"""),7.933E9) -> 7933000000 | L69: =IFERROR(__xludf.DUMMYFUNCTION("""COMPUTED_VALUE"""),1.33883E11) -> 133883000000 | O69: Apple | P69: =SUMIF(Cleaned_Data!C$2:C$2013,O69,Cleaned_Data!K$2:K$2013) -> 99938000000 | Q69: =SUMIF(Cleaned_Data!C$2:C$2013,O69,Cleaned_Data!N$2:N$2013) -> 347155000000 | R69: =IFERROR(P69/Q69,"") -> 0.28787717
D70: Biogen | E70: =SUMIF(Cleaned_Data!C$2:C$2013,D70,Cleaned_Data!N$2:N$2013) -> 11697700000 | J70: =IFERROR(__xludf.DUMMYFUNCTION("""COMPUTED_VALUE"""),"Aon") -> Aon | K70: =IFERROR(__xludf.DUMMYFUNCTION("""COMPUTED_VALUE"""),3.237E9) -> 3237000000 | L70: =IFERROR(__xludf.DUMMYFUNCTION("""COMPUTED_VALUE"""),1.1761E10) -> 11761000000 | O70: Applied Materials | P70: =SUMIF(Cleaned_Data!C$2:C$2013,O70,Cleaned_Data!K$2:K$2013) -> 6549000000 | Q70: =SUMIF(Cleaned_Data!C$2:C$2013,O70,Cleaned_Data!N$2:N$2013) -> 21628000000 | R70: =IFERROR(P70/Q70,"") -> 0.30280192
D71: BlackRock | E71: =SUMIF(Cleaned_Data!C$2:C$2013,D71,Cleaned_Data!N$2:N$2013) -> 18065000000 | J71: =IFERROR(__xludf.DUMMYFUNCTION("""COMPUTED_VALUE"""),"Apple") -> Apple | K71: =IFERROR(__xludf.DUMMYFUNCTION("""COMPUTED_VALUE"""),9.9938E10) -> 99938000000 | L71: =IFERROR(__xludf.DUMMYFUNCTION("""COMPUTED_VALUE"""),3.47155E11) -> 347155000000 | O71: Aptiv | P71: =SUMIF(Cleaned_Data!C$2:C$2013,O71,Cleaned_Data!K$2:K$2013) -> 1562000000 | Q71: =SUMIF(Cleaned_Data!C$2:C$2013,O71,Cleaned_Data!N$2:N$2013) -> 15710000000 | R71: =IFERROR(P71/Q71,"") -> 0.099427116
D72: BNY Mellon | E72: =SUMIF(Cleaned_Data!C$2:C$2013,D72,Cleaned_Data!N$2:N$2013) -> 15958000000 | J72: =IFERROR(__xludf.DUMMYFUNCTION("""COMPUTED_VALUE"""),"Applied Materials") -> Applied Materials | K72: =IFERROR(__xludf.DUMMYFUNCTION("""COMPUTED_VALUE"""),6.549E9) -> 6549000000 | L72: =IFERROR(__xludf.DUMMYFUNCTION("""COMPUTED_VALUE"""),2.1628E10) -> 21628000000 | O72: Arista Networks | P72: =SUMIF(Cleaned_Data!C$2:C$2013,O72,Cleaned_Data!K$2:K$2013) -> 803390000 | Q72: =SUMIF(Cleaned_Data!C$2:C$2013,O72,Cleaned_Data!N$2:N$2013) -> 2628794000 | R72: =IFERROR(P72/Q72,"") -> 0.30561162
D73: Boeing | E73: =SUMIF(Cleaned_Data!C$2:C$2013,D73,Cleaned_Data!N$2:N$2013) -> 62797000000 | J73: =IFERROR(__xludf.DUMMYFUNCTION("""COMPUTED_VALUE"""),"Aptiv") -> Aptiv | K73: =IFERROR(__xludf.DUMMYFUNCTION("""COMPUTED_VALUE"""),1.562E9) -> 1562000000 | L73: =IFERROR(__xludf.DUMMYFUNCTION("""COMPUTED_VALUE"""),1.571E10) -> 15710000000 | O73: Arthur J. Gallagher & Co. | P73: =SUMIF(Cleaned_Data!C$2:C$2013,O73,Cleaned_Data!K$2:K$2013) -> 1323300000 | Q73: =SUMIF(Cleaned_Data!C$2:C$2013,O73,Cleaned_Data!N$2:N$2013) -> 7426500000 | R73: =IFERROR(P73/Q73,"") -> 0.17818623
D74: Booking Holdings | E74: =SUMIF(Cleaned_Data!C$2:C$2013,D74,Cleaned_Data!N$2:N$2013) -> 7179000000 | J74: =IFERROR(__xludf.DUMMYFUNCTION("""COMPUTED_VALUE"""),"Arista Networks") -> Arista Networks | K74: =IFERROR(__xludf.DUMMYFUNCTION("""COMPUTED_VALUE"""),8.0339E8) -> 803390000 | L74: =IFERROR(__xludf.DUMMYFUNCTION("""COMPUTED_VALUE"""),2.628794E9) -> 2628794000 | O74: Assurant | P74: =SUMIF(Cleaned_Data!C$2:C$2013,O74,Cleaned_Data!K$2:K$2013) -> 881700000 | Q74: =SUMIF(Cleaned_Data!C$2:C$2013,O74,Cleaned_Data!N$2:N$2013) -> 10032500000 | R74: =IFERROR(P74/Q74,"") -> 0.087884376
D75: BorgWarner | E75: =SUMIF(Cleaned_Data!C$2:C$2013,D75,Cleaned_Data!N$2:N$2013) -> 14227000000 | J75: =IFERROR(__xludf.DUMMYFUNCTION("""COMPUTED_VALUE"""),"Arthur J. Gallagher & Co.") -> Arthur J. Gallagher & Co. | K75: =IFERROR(__xludf.DUMMYFUNCTION("""COMPUTED_VALUE"""),1.3233E9) -> 1323300000 | L75: =IFERROR(__xludf.DUMMYFUNCTION("""COMPUTED_VALUE"""),7.4265E9) -> 7426500000 | O75: AT&T | P75: =SUMIF(Cleaned_Data!C$2:C$2013,O75,Cleaned_Data!K$2:K$2013) -> 30700000000 | Q75: =SUMIF(Cleaned_Data!C$2:C$2013,O75,Cleaned_Data!N$2:N$2013) -> 176015000000 | R75: =IFERROR(P75/Q75,"") -> 0.17441695
D76: Boston Properties | E76: =SUMIF(Cleaned_Data!C$2:C$2013,D76,Cleaned_Data!N$2:N$2013) -> 2752285000 | J76: =IFERROR(__xludf.DUMMYFUNCTION("""COMPUTED_VALUE"""),"Assurant") -> Assurant | K76: =IFERROR(__xludf.DUMMYFUNCTION("""COMPUTED_VALUE"""),8.817E8) -> 881700000 | L76: =IFERROR(__xludf.DUMMYFUNCTION("""COMPUTED_VALUE"""),1.00325E10) -> 10032500000 | O76: Atmos Energy | P76: =SUMIF(Cleaned_Data!C$2:C$2013,O76,Cleaned_Data!K$2:K$2013) -> 904107000 | Q76: =SUMIF(Cleaned_Data!C$2:C$2013,O76,Cleaned_Data!N$2:N$2013) -> 3314020000 | R76: =IFERROR(P76/Q76,"") -> 0.27281278
D77: Boston Scientific | E77: =SUMIF(Cleaned_Data!C$2:C$2013,D77,Cleaned_Data!N$2:N$2013) -> 11197000000 | J77: =IFERROR(__xludf.DUMMYFUNCTION("""COMPUTED_VALUE"""),"Atmos Energy") -> Atmos Energy | K77: =IFERROR(__xludf.DUMMYFUNCTION("""COMPUTED_VALUE"""),9.04107E8) -> 904107000 | L77: =IFERROR(__xludf.DUMMYFUNCTION("""COMPUTED_VALUE"""),3.31402E9) -> 3314020000 | O77: Autodesk | P77: =SUMIF(Cleaned_Data!C$2:C$2013,O77,Cleaned_Data!K$2:K$2013) -> 665600000 | Q77: =SUMIF(Cleaned_Data!C$2:C$2013,O77,Cleaned_Data!N$2:N$2013) -> 4040600000 | R77: =IFERROR(P77/Q77,"") -> 0.16472801
D78: Bristol Myers Squibb | E78: =SUMIF(Cleaned_Data!C$2:C$2013,D78,Cleaned_Data!N$2:N$2013) -> 44384000000 | J78: =IFERROR(__xludf.DUMMYFUNCTION("""COMPUTED_VALUE"""),"AutoZone") -> AutoZone | K78: =IFERROR(__xludf.DUMMYFUNCTION("""COMPUTED_VALUE"""),2.981427E9) -> 2981427000 | L78: =IFERROR(__xludf.DUMMYFUNCTION("""COMPUTED_VALUE"""),1.4629586E10) -> 14629586000 | O78: Automatic Data Processing | P78: =SUMIF(Cleaned_Data!C$2:C$2013,O78,Cleaned_Data!K$2:K$2013) -> 3355400000 | Q78: =SUMIF(Cleaned_Data!C$2:C$2013,O78,Cleaned_Data!N$2:N$2013) -> 15005400000 | R78: =IFERROR(P78/Q78,"") -> 0.22361283
D79: Broadcom | E79: =SUMIF(Cleaned_Data!C$2:C$2013,D79,Cleaned_Data!N$2:N$2013) -> 26510000000 | J79: =IFERROR(__xludf.DUMMYFUNCTION("""COMPUTED_VALUE"""),"Autodesk") -> Autodesk | K79: =IFERROR(__xludf.DUMMYFUNCTION("""COMPUTED_VALUE"""),6.656E8) -> 665600000 | L79: =IFERROR(__xludf.DUMMYFUNCTION("""COMPUTED_VALUE"""),4.0406E9) -> 4040600000 | O79: AutoZone | P79: =SUMIF(Cleaned_Data!C$2:C$2013,O79,Cleaned_Data!K$2:K$2013) -> 2981427000 | Q79: =SUMIF(Cleaned_Data!C$2:C$2013,O79,Cleaned_Data!N$2:N$2013) -> 14629586000 | R79: =IFERROR(P79/Q79,"") -> 0.20379435
D80: Broadridge Financial Solutions | E80: =SUMIF(Cleaned_Data!C$2:C$2013,D80,Cleaned_Data!N$2:N$2013) -> 4824000000 | J80: =IFERROR(__xludf.DUMMYFUNCTION("""COMPUTED_VALUE"""),"Automatic Data Processing") -> Automatic Data Processing | K80: =IFERROR(__xludf.DUMMYFUNCTION("""COMPUTED_VALUE"""),3.3554E9) -> 3355400000 | L80: =IFERROR(__xludf.DUMMYFUNCTION("""COMPUTED_VALUE"""),1.50054E10) -> 15005400000 | O80: AvalonBay Communities | P80: =SUMIF(Cleaned_Data!C$2:C$2013,O80,Cleaned_Data!K$2:K$2013) -> 603917000 | Q80: =SUMIF(Cleaned_Data!C$2:C$2013,O80,Cleaned_Data!N$2:N$2013) -> 2234664000 | R80: =IFERROR(P80/Q80,"") -> 0.27024958
D81: Brown & Brown | E81: =SUMIF(Cleaned_Data!C$2:C$2013,D81,Cleaned_Data!N$2:N$2013) -> 2729087000 | J81: =IFERROR(__xludf.DUMMYFUNCTION("""COMPUTED_VALUE"""),"AvalonBay Communities") -> AvalonBay Communities | K81: =IFERROR(__xludf.DUMMYFUNCTION("""COMPUTED_VALUE"""),6.03917E8) -> 603917000 | L81: =IFERROR(__xludf.DUMMYFUNCTION("""COMPUTED_VALUE"""),2.234664E9) -> 2234664000 | O81: Avery Dennison | P81: =SUMIF(Cleaned_Data!C$2:C$2013,O81,Cleaned_Data!K$2:K$2013) -> 1060000000 | Q81: =SUMIF(Cleaned_Data!C$2:C$2013,O81,Cleaned_Data!N$2:N$2013) -> 7873300000 | R81: =IFERROR(P81/Q81,"") -> 0.13463224
D82: C. H. Robinson | E82: =SUMIF(Cleaned_Data!C$2:C$2013,D82,Cleaned_Data!N$2:N$2013) -> 17205967000 | J82: =IFERROR(__xludf.DUMMYFUNCTION("""COMPUTED_VALUE"""),"Avery Dennison") -> Avery Dennison | K82: =IFERROR(__xludf.DUMMYFUNCTION("""COMPUTED_VALUE"""),1.06E9) -> 1060000000 | L82: =IFERROR(__xludf.DUMMYFUNCTION("""COMPUTED_VALUE"""),7.8733E9) -> 7873300000 | O82: Baker Hughes | P82: =SUMIF(Cleaned_Data!C$2:C$2013,O82,Cleaned_Data!K$2:K$2013) -> 1407000000 | Q82: =SUMIF(Cleaned_Data!C$2:C$2013,O82,Cleaned_Data!N$2:N$2013) -> 20512000000 | R82: =IFERROR(P82/Q82,"") -> 0.068593994
D83: Cadence Design Systems | E83: =SUMIF(Cleaned_Data!C$2:C$2013,D83,Cleaned_Data!N$2:N$2013) -> 2890829000 | J83: =IFERROR(__xludf.DUMMYFUNCTION("""COMPUTED_VALUE"""),"BNY Mellon") -> BNY Mellon | K83: =IFERROR(__xludf.DUMMYFUNCTION("""COMPUTED_VALUE"""),4.575E9) -> 4575000000 | L83: =IFERROR(__xludf.DUMMYFUNCTION("""COMPUTED_VALUE"""),1.5958E10) -> 15958000000 | O83: Ball Corp | P83: =SUMIF(Cleaned_Data!C$2:C$2013,O83,Cleaned_Data!K$2:K$2013) -> 1373000000 | Q83: =SUMIF(Cleaned_Data!C$2:C$2013,O83,Cleaned_Data!N$2:N$2013) -> 12779000000 | R83: =IFERROR(P83/Q83,"") -> 0.1074419
D84: Caesars Entertainment | E84: =SUMIF(Cleaned_Data!C$2:C$2013,D84,Cleaned_Data!N$2:N$2013) -> 7160000000 | J84: =IFERROR(__xludf.DUMMYFUNCTION("""COMPUTED_VALUE"""),"Baker Hughes") -> Baker Hughes | K84: =IFERROR(__xludf.DUMMYFUNCTION("""COMPUTED_VALUE"""),1.407E9) -> 1407000000 | L84: =IFERROR(__xludf.DUMMYFUNCTION("""COMPUTED_VALUE"""),2.0512E10) -> 20512000000 | O84: Bank of America | P84: =SUMIF(Cleaned_Data!C$2:C$2013,O84,Cleaned_Data!K$2:K$2013) -> 32277000000 | Q84: =SUMIF(Cleaned_Data!C$2:C$2013,O84,Cleaned_Data!N$2:N$2013) -> 91204000000 | R84: =IFERROR(P84/Q84,"") -> 0.35389895
D85: Campbell Soup | E85: =SUMIF(Cleaned_Data!C$2:C$2013,D85,Cleaned_Data!N$2:N$2013) -> 8711000000 | J85: =IFERROR(__xludf.DUMMYFUNCTION("""COMPUTED_VALUE"""),"Ball Corp") -> Ball Corp | K85: =IFERROR(__xludf.DUMMYFUNCTION("""COMPUTED_VALUE"""),1.373E9) -> 1373000000 | L85: =IFERROR(__xludf.DUMMYFUNCTION("""COMPUTED_VALUE"""),1.2779E10) -> 12779000000 | O85: Bath & Body Works Inc. | P85: =SUMIF(Cleaned_Data!C$2:C$2013,O85,Cleaned_Data!K$2:K$2013) -> 3060000000 | Q85: =SUMIF(Cleaned_Data!C$2:C$2013,O85,Cleaned_Data!N$2:N$2013) -> 14215000000 | R85: =IFERROR(P85/Q85,"") -> 0.21526556
D86: Capital One Financial | E86: =SUMIF(Cleaned_Data!C$2:C$2013,D86,Cleaned_Data!N$2:N$2013) -> 30593000000 | J86: =IFERROR(__xludf.DUMMYFUNCTION("""COMPUTED_VALUE"""),"Bank of America") -> Bank of America | K86: =IFERROR(__xludf.DUMMYFUNCTION("""COMPUTED_VALUE"""),3.2277E10) -> 32277000000 | L86: =IFERROR(__xludf.DUMMYFUNCTION("""COMPUTED_VALUE"""),9.1204E10) -> 91204000000 | O86: Baxter International | P86: =SUMIF(Cleaned_Data!C$2:C$2013,O86,Cleaned_Data!K$2:K$2013) -> 1905000000 | Q86: =SUMIF(Cleaned_Data!C$2:C$2013,O86,Cleaned_Data!N$2:N$2013) -> 12197000000 | R86: =IFERROR(P86/Q86,"") -> 0.15618595
D87: Cardinal Health | E87: =SUMIF(Cleaned_Data!C$2:C$2013,D87,Cleaned_Data!N$2:N$2013) -> 162467000000 | J87: =IFERROR(__xludf.DUMMYFUNCTION("""COMPUTED_VALUE"""),"Bath & Body Works Inc.") -> Bath & Body Works Inc. | K87: =IFERROR(__xludf.DUMMYFUNCTION("""COMPUTED_VALUE"""),3.06E9) -> 3060000000 | L87: =IFERROR(__xludf.DUMMYFUNCTION("""COMPUTED_VALUE"""),1.4215E10) -> 14215000000 | O87: Becton Dickinson | P87: =SUMIF(Cleaned_Data!C$2:C$2013,O87,Cleaned_Data!K$2:K$2013) -> 3729000000 | Q87: =SUMIF(Cleaned_Data!C$2:C$2013,O87,Cleaned_Data!N$2:N$2013) -> 19896000000 | R87: =IFERROR(P87/Q87,"") -> 0.18742461
D88: CarMax | E88: =SUMIF(Cleaned_Data!C$2:C$2013,D88,Cleaned_Data!N$2:N$2013) -> 24588766000 | J88: =IFERROR(__xludf.DUMMYFUNCTION("""COMPUTED_VALUE"""),"Baxter International") -> Baxter International | K88: =IFERROR(__xludf.DUMMYFUNCTION("""COMPUTED_VALUE"""),1.905E9) -> 1905000000 | L88: =IFERROR(__xludf.DUMMYFUNCTION("""COMPUTED_VALUE"""),1.2197E10) -> 12197000000 | O88: Best Buy | P88: =SUMIF(Cleaned_Data!C$2:C$2013,O88,Cleaned_Data!K$2:K$2013) -> 3392000000 | Q88: =SUMIF(Cleaned_Data!C$2:C$2013,O88,Cleaned_Data!N$2:N$2013) -> 52276000000 | R88: =IFERROR(P88/Q88,"") -> 0.064886372
D89: Carnival Corporation | E89: =SUMIF(Cleaned_Data!C$2:C$2013,D89,Cleaned_Data!N$2:N$2013) -> 139000000 | J89: =IFERROR(__xludf.DUMMYFUNCTION("""COMPUTED_VALUE"""),"Becton Dickinson") -> Becton Dickinson | K89: =IFERROR(__xludf.DUMMYFUNCTION("""COMPUTED_VALUE"""),3.729E9) -> 3729000000 | L89: =IFERROR(__xludf.DUMMYFUNCTION("""COMPUTED_VALUE"""),1.9896E10) -> 19896000000 | O89: Bio-Rad Laboratories | P89: =SUMIF(Cleaned_Data!C$2:C$2013,O89,Cleaned_Data!K$2:K$2013) -> 576286000 | Q89: =SUMIF(Cleaned_Data!C$2:C$2013,O89,Cleaned_Data!N$2:N$2013) -> 2879829000 | R89: =IFERROR(P89/Q89,"") -> 0.20011119
D90: Carrier Global | E90: =SUMIF(Cleaned_Data!C$2:C$2013,D90,Cleaned_Data!N$2:N$2013) -> 19735000000 | J90: =IFERROR(__xludf.DUMMYFUNCTION("""COMPUTED_VALUE"""),"Best Buy") -> Best Buy | K90: =IFERROR(__xludf.DUMMYFUNCTION("""COMPUTED_VALUE"""),3.392E9) -> 3392000000 | L90: =IFERROR(__xludf.DUMMYFUNCTION("""COMPUTED_VALUE"""),5.2276E10) -> 52276000000 | O90: Bio-Techne | P90: =SUMIF(Cleaned_Data!C$2:C$2013,O90,Cleaned_Data!K$2:K$2013) -> 245835000 | Q90: =SUMIF(Cleaned_Data!C$2:C$2013,O90,Cleaned_Data!N$2:N$2013) -> 931032000 | R90: =IFERROR(P90/Q90,"") -> 0.2640457
D91: Catalent | E91: =SUMIF(Cleaned_Data!C$2:C$2013,D91,Cleaned_Data!N$2:N$2013) -> 3998000000 | J91: =IFERROR(__xludf.DUMMYFUNCTION("""COMPUTED_VALUE"""),"Bio-Rad Laboratories") -> Bio-Rad Laboratories | K91: =IFERROR(__xludf.DUMMYFUNCTION("""COMPUTED_VALUE"""),5.76286E8) -> 576286000 | L91: =IFERROR(__xludf.DUMMYFUNCTION("""COMPUTED_VALUE"""),2.879829E9) -> 2879829000 | O91: Biogen | P91: =SUMIF(Cleaned_Data!C$2:C$2013,O91,Cleaned_Data!K$2:K$2013) -> 2224600000 | Q91: =SUMIF(Cleaned_Data!C$2:C$2013,O91,Cleaned_Data!N$2:N$2013) -> 11697700000 | R91: =IFERROR(P91/Q91,"") -> 0.19017414
D92: Caterpillar | E92: =SUMIF(Cleaned_Data!C$2:C$2013,D92,Cleaned_Data!N$2:N$2013) -> 43000000000 | J92: =IFERROR(__xludf.DUMMYFUNCTION("""COMPUTED_VALUE"""),"Bio-Techne") -> Bio-Techne | K92: =IFERROR(__xludf.DUMMYFUNCTION("""COMPUTED_VALUE"""),2.45835E8) -> 245835000 | L92: =IFERROR(__xludf.DUMMYFUNCTION("""COMPUTED_VALUE"""),9.31032E8) -> 931032000 | O92: BlackRock | P92: =SUMIF(Cleaned_Data!C$2:C$2013,O92,Cleaned_Data!K$2:K$2013) -> 7085000000 | Q92: =SUMIF(Cleaned_Data!C$2:C$2013,O92,Cleaned_Data!N$2:N$2013) -> 18065000000 | R92: =IFERROR(P92/Q92,"") -> 0.39219485
D93: Cboe Global Markets | E93: =SUMIF(Cleaned_Data!C$2:C$2013,D93,Cleaned_Data!N$2:N$2013) -> 3448500000 | J93: =IFERROR(__xludf.DUMMYFUNCTION("""COMPUTED_VALUE"""),"Biogen") -> Biogen | K93: =IFERROR(__xludf.DUMMYFUNCTION("""COMPUTED_VALUE"""),2.2246E9) -> 2224600000 | L93: =IFERROR(__xludf.DUMMYFUNCTION("""COMPUTED_VALUE"""),1.16977E10) -> 11697700000 | O93: BNY Mellon | P93: =SUMIF(Cleaned_Data!C$2:C$2013,O93,Cleaned_Data!K$2:K$2013) -> 4575000000 | Q93: =SUMIF(Cleaned_Data!C$2:C$2013,O93,Cleaned_Data!N$2:N$2013) -> 15958000000 | R93: =IFERROR(P93/Q93,"") -> 0.28669006
D94: CBRE | E94: =SUMIF(Cleaned_Data!C$2:C$2013,D94,Cleaned_Data!N$2:N$2013) -> 24953135000 | J94: =IFERROR(__xludf.DUMMYFUNCTION("""COMPUTED_VALUE"""),"BlackRock") -> BlackRock | K94: =IFERROR(__xludf.DUMMYFUNCTION("""COMPUTED_VALUE"""),7.085E9) -> 7085000000 | L94: =IFERROR(__xludf.DUMMYFUNCTION("""COMPUTED_VALUE"""),1.8065E10) -> 18065000000 | O94: Boeing | P94: =SUMIF(Cleaned_Data!C$2:C$2013,O94,Cleaned_Data!K$2:K$2013) -> -3700000000 | Q94: =SUMIF(Cleaned_Data!C$2:C$2013,O94,Cleaned_Data!N$2:N$2013) -> 62797000000 | R94: =IFERROR(P94/Q94,"") -> -0.058920012
D95: CDW | E95: =SUMIF(Cleaned_Data!C$2:C$2013,D95,Cleaned_Data!N$2:N$2013) -> 19696500000 | J95: =IFERROR(__xludf.DUMMYFUNCTION("""COMPUTED_VALUE"""),"Boeing") -> Boeing | K95: =IFERROR(__xludf.DUMMYFUNCTION("""COMPUTED_VALUE"""),-3.7E9) -> -3700000000 | L95: =IFERROR(__xludf.DUMMYFUNCTION("""COMPUTED_VALUE"""),6.2797E10) -> 62797000000 | O95: Booking Holdings | P95: =SUMIF(Cleaned_Data!C$2:C$2013,O95,Cleaned_Data!K$2:K$2013) -> 492000000 | Q95: =SUMIF(Cleaned_Data!C$2:C$2013,O95,Cleaned_Data!N$2:N$2013) -> 7179000000 | R95: =IFERROR(P95/Q95,"") -> 0.068533222
D96: Celanese | E96: =SUMIF(Cleaned_Data!C$2:C$2013,D96,Cleaned_Data!N$2:N$2013) -> 6998000000 | J96: =IFERROR(__xludf.DUMMYFUNCTION("""COMPUTED_VALUE"""),"Booking Holdings") -> Booking Holdings | K96: =IFERROR(__xludf.DUMMYFUNCTION("""COMPUTED_VALUE"""),4.92E8) -> 492000000 | L96: =IFERROR(__xludf.DUMMYFUNCTION("""COMPUTED_VALUE"""),7.179E9) -> 7179000000 | O96: BorgWarner | P96: =SUMIF(Cleaned_Data!C$2:C$2013,O96,Cleaned_Data!K$2:K$2013) -> 1610000000 | Q96: =SUMIF(Cleaned_Data!C$2:C$2013,O96,Cleaned_Data!N$2:N$2013) -> 14227000000 | R96: =IFERROR(P96/Q96,"") -> 0.11316511
D97: Centene Corporation | E97: =SUMIF(Cleaned_Data!C$2:C$2013,D97,Cleaned_Data!N$2:N$2013) -> 114130000000 | J97: =IFERROR(__xludf.DUMMYFUNCTION("""COMPUTED_VALUE"""),"BorgWarner") -> BorgWarner | K97: =IFERROR(__xludf.DUMMYFUNCTION("""COMPUTED_VALUE"""),1.61E9) -> 1610000000 | L97: =IFERROR(__xludf.DUMMYFUNCTION("""COMPUTED_VALUE"""),1.4227E10) -> 14227000000 | O97: Boston Properties | P97: =SUMIF(Cleaned_Data!C$2:C$2013,O97,Cleaned_Data!K$2:K$2013) -> 900832000 | Q97: =SUMIF(Cleaned_Data!C$2:C$2013,O97,Cleaned_Data!N$2:N$2013) -> 2752285000 | R97: =IFERROR(P97/Q97,"") -> 0.32730331
D98: CenterPoint Energy | E98: =SUMIF(Cleaned_Data!C$2:C$2013,D98,Cleaned_Data!N$2:N$2013) -> 7965000000 | J98: =IFERROR(__xludf.DUMMYFUNCTION("""COMPUTED_VALUE"""),"Boston Properties") -> Boston Properties | K98: =IFERROR(__xludf.DUMMYFUNCTION("""COMPUTED_VALUE"""),9.00832E8) -> 900832000 | L98: =IFERROR(__xludf.DUMMYFUNCTION("""COMPUTED_VALUE"""),2.752285E9) -> 2752285000 | O98: Boston Scientific | P98: =SUMIF(Cleaned_Data!C$2:C$2013,O98,Cleaned_Data!K$2:K$2013) -> 1803000000 | Q98: =SUMIF(Cleaned_Data!C$2:C$2013,O98,Cleaned_Data!N$2:N$2013) -> 11197000000 | R98: =IFERROR(P98/Q98,"") -> 0.16102527
D99: Ceridian | E99: =SUMIF(Cleaned_Data!C$2:C$2013,D99,Cleaned_Data!N$2:N$2013) -> 912100000 | J99: =IFERROR(__xludf.DUMMYFUNCTION("""COMPUTED_VALUE"""),"Boston Scientific") -> Boston Scientific | K99: =IFERROR(__xludf.DUMMYFUNCTION("""COMPUTED_VALUE"""),1.803E9) -> 1803000000 | L99: =IFERROR(__xludf.DUMMYFUNCTION("""COMPUTED_VALUE"""),1.1197E10) -> 11197000000 | O99: Bristol Myers Squibb | P99: =SUMIF(Cleaned_Data!C$2:C$2013,O99,Cleaned_Data!K$2:K$2013) -> 8197000000 | Q99: =SUMIF(Cleaned_Data!C$2:C$2013,O99,Cleaned_Data!N$2:N$2013) -> 44384000000 | R99: =IFERROR(P99/Q99,"") -> 0.18468367
D100: Cerner | E100: =SUMIF(Cleaned_Data!C$2:C$2013,D100,Cleaned_Data!N$2:N$2013) -> 5608231000 | J100: =IFERROR(__xludf.DUMMYFUNCTION("""COMPUTED_VALUE"""),"Bristol Myers Squibb") -> Bristol Myers Squibb | K100: =IFERROR(__xludf.DUMMYFUNCTION("""COMPUTED_VALUE"""),8.197E9) -> 8197000000 | L100: =IFERROR(__xludf.DUMMYFUNCTION("""COMPUTED_VALUE"""),4.4384E10) -> 44384000000 | O100: Broadcom | P100: =SUMIF(Cleaned_Data!C$2:C$2013,O100,Cleaned_Data!K$2:K$2013) -> 7536000000 | Q100: =SUMIF(Cleaned_Data!C$2:C$2013,O100,Cleaned_Data!N$2:N$2013) -> 26510000000 | R100: =IFERROR(P100/Q100,"") -> 0.28427009
...

Sheet Pivot Table 1

Sheet Dashboard
A1: S&P 500 Financial Performance Dashboard
A3: Total Revenue | C3: Total Gross Profit | E3: Total Operating Income | G3: Total Net Income | I3: Revenue Growth (2020–2021)
A4: =Financial_Analysis!B2 -> 13173344212500 | C4: =Financial_Analysis!B3 -> 5165530836500 | E4: =Financial_Analysis!B4 -> 2049131813000 | G4: =Financial_Analysis!B5 -> 1441865680000 | I4: =Financial_Analysis!K17 -> 0.35114378
A47: Key Financial Insights
A48: Revenue increased by 35.11% from 2020 to 2021.
A49: Operating income grew 62.07%, showing improved operating profitability in 2021.
A50: Net income increased 102.63%, indicating a significant improvement in overall profitability.
A51: Gross profit margin improved from 38.12% to 40.02%.
A52: Operating margin improved from 13.95% to 16.74%.
A53: Net profit margin improved from 8.50% to 12.75%.
